Workbook
Name LISTA_CATEGORIAS: CATEGORIAS!$C$4:$C$33

Sheet PORTADA
A1: CASHFLOW PERSONAL · panel del año
A2: AÑO | B2: 2026 | D2: Cambia el año acá y las doce hojas del mes se recalculan solas.
A3: CÓDIGO DE COLOR | B3: lo escribes tú | C3: se calcula solo
A5: EL AÑO MES A MES
A6: MES | B6: INGRESOS | C6: EGRESOS | D6: SALDO | E6: ACUMULADO | F6: % GASTADO
A7: ENERO | B7: ='ENERO'!D13 | C7: ='ENERO'!D40 | D7: =B7-C7 | E7: =D7 | F7: =IFERROR(C7/B7,"")
A8: FEBRERO | B8: ='FEBRERO'!D13 | C8: ='FEBRERO'!D40 | D8: =B8-C8 | E8: =E7+D8 | F8: =IFERROR(C8/B8,"")
A9: MARZO | B9: ='MARZO'!D13 | C9: ='MARZO'!D40 | D9: =B9-C9 | E9: =E8+D9 | F9: =IFERROR(C9/B9,"")
A10: ABRIL | B10: ='ABRIL'!D13 | C10: ='ABRIL'!D40 | D10: =B10-C10 | E10: =E9+D10 | F10: =IFERROR(C10/B10,"")
A11: MAYO | B11: ='MAYO'!D13 | C11: ='MAYO'!D40 | D11: =B11-C11 | E11: =E10+D11 | F11: =IFERROR(C11/B11,"")
A12: JUNIO | B12: ='JUNIO'!D13 | C12: ='JUNIO'!D40 | D12: =B12-C12 | E12: =E11+D12 | F12: =IFERROR(C12/B12,"")
A13: JULIO | B13: ='JULIO'!D13 | C13: ='JULIO'!D40 | D13: =B13-C13 | E13: =E12+D13 | F13: =IFERROR(C13/B13,"")
A14: AGOSTO | B14: ='AGOSTO'!D13 | C14: ='AGOSTO'!D40 | D14: =B14-C14 | E14: =E13+D14 | F14: =IFERROR(C14/B14,"")
A15: SEPTIEMBRE | B15: ='SEPTIEMBRE'!D13 | C15: ='SEPTIEMBRE'!D40 | D15: =B15-C15 | E15: =E14+D15 | F15: =IFERROR(C15/B15,"")
A16: OCTUBRE | B16: ='OCTUBRE'!D13 | C16: ='OCTUBRE'!D40 | D16: =B16-C16 | E16: =E15+D16 | F16: =IFERROR(C16/B16,"")
A17: NOVIEMBRE | B17: ='NOVIEMBRE'!D13 | C17: ='NOVIEMBRE'!D40 | D17: =B17-C17 | E17: =E16+D17 | F17: =IFERROR(C17/B17,"")
A18: DICIEMBRE | B18: ='DICIEMBRE'!D13 | C18: ='DICIEMBRE'!D40 | D18: =B18-C18 | E18: =E17+D18 | F18: =IFERROR(C18/B18,"")
A19: TOTAL AÑO | B19: =SUM(B7:B18) | C19: =SUM(C7:C18) | D19: =SUM(D7:D18)
A21: COMPROMETIDO CADA MES
A22: Gastos fijos | B22: =FIJOS!C11
A23: Cuotas de créditos | B23: =COMPROMISOS!C7
A24: Ingreso presupuestado | B24: =SUMIFS(CATEGORIAS!$E:$E,CATEGORIAS!$A:$A,"INGRESO")
A25: LIBRE DESPUÉS DE LO FIJO | B25: =B24-B22-B23
A27: DEUDA PENDIENTE | B27: =COMPROMISOS!F7
A28: INVERTIDO SIN RECUPERAR | B28: =-INVERSIONES!E7
A30: QUÉ DICEN LOS NÚMEROS
A31: =IF(B19=0,"Todavía no hay movimientos cargados.",CONCATENATE("En el año llevas ",TEXT(B19,"$#,##0")," de ingreso y ",TEXT(C19,"$#,##0")," de egreso. Te queda ",TEXT(D19,"$#,##0"),"."))
A32: =IF(B19=0,"",IF(D19<0,"Estás gastando más de lo que entra. El saldo del año es negativo.",CONCATENATE("Estás guardando el ",TEXT(D19/B19,"0%")," de lo que entra.")))
A33: =CONCATENATE("Antes de gastar un peso ya tienes comprometidos ",TEXT(B22+B23,"$#,##0")," al mes. Te quedan libres ",TEXT(B25,"$#,##0"),".")
A34: =IF(COMPROMISOS!F7=0,"No tienes deuda pendiente.",CONCATENATE("Debes ",TEXT(COMPROMISOS!F7,"$#,##0")," en cuotas. La última se paga en ",TEXT(MAX(COMPROMISOS!I4:I6),"mm/yyyy"),"."))
A35: =IFERROR(CONCATENATE("El mes que más gastaste fue ",INDEX(A7:A18,MATCH(MAX(C7:C18),C7:C18,0))," con ",TEXT(MAX(C7:C18),"$#,##0"),"."),"")

Sheet ANALISIS
A1: ANÁLISIS FINANCIERO · qué está pasando con tu plata
A3: 1. CÓMO VA CADA MES | B3: ¿Cuánto del ingreso se queda y cuánto se va en cuotas?
A4: MES | B4: INGRESO | C4: EGRESO | D4: QUEDA | E4: AHORRO DEL MES | F4: TASA DE AHORRO | G4: CARGA DE DEUDA
A5: ENERO | B5: =PORTADA!B7 | C5: =PORTADA!C7 | D5: =B5-C5 | E5: =SUMIFS(MOVIMIENTOS!$F:$F,MOVIMIENTOS!$E:$E,"AHORRO",MOVIMIENTOS!$A:$A,">="&DATE(PORTADA!$B$2,1,1),MOVIMIENTOS!$A:$A,"<="&EOMONTH(DATE(PORTADA!$B$2,1,1),0)) | F5: =IFERROR((D5+E5)/B5,"") | G5: =IFERROR(COMPROMISOS!$C$7/B5,"")
A6: FEBRERO | B6: =PORTADA!B8 | C6: =PORTADA!C8 | D6: =B6-C6 | E6: =SUMIFS(MOVIMIENTOS!$F:$F,MOVIMIENTOS!$E:$E,"AHORRO",MOVIMIENTOS!$A:$A,">="&DATE(PORTADA!$B$2,2,1),MOVIMIENTOS!$A:$A,"<="&EOMONTH(DATE(PORTADA!$B$2,2,1),0)) | F6: =IFERROR((D6+E6)/B6,"") | G6: =IFERROR(COMPROMISOS!$C$7/B6,"")
A7: MARZO | B7: =PORTADA!B9 | C7: =PORTADA!C9 | D7: =B7-C7 | E7: =SUMIFS(MOVIMIENTOS!$F:$F,MOVIMIENTOS!$E:$E,"AHORRO",MOVIMIENTOS!$A:$A,">="&DATE(PORTADA!$B$2,3,1),MOVIMIENTOS!$A:$A,"<="&EOMONTH(DATE(PORTADA!$B$2,3,1),0)) | F7: =IFERROR((D7+E7)/B7,"") | G7: =IFERROR(COMPROMISOS!$C$7/B7,"")
A8: ABRIL | B8: =PORTADA!B10 | C8: =PORTADA!C10 | D8: =B8-C8 | E8: =SUMIFS(MOVIMIENTOS!$F:$F,MOVIMIENTOS!$E:$E,"AHORRO",MOVIMIENTOS!$A:$A,">="&DATE(PORTADA!$B$2,4,1),MOVIMIENTOS!$A:$A,"<="&EOMONTH(DATE(PORTADA!$B$2,4,1),0)) | F8: =IFERROR((D8+E8)/B8,"") | G8: =IFERROR(COMPROMISOS!$C$7/B8,"")
A9: MAYO | B9: =PORTADA!B11 | C9: =PORTADA!C11 | D9: =B9-C9 | E9: =SUMIFS(MOVIMIENTOS!$F:$F,MOVIMIENTOS!$E:$E,"AHORRO",MOVIMIENTOS!$A:$A,">="&DATE(PORTADA!$B$2,5,1),MOVIMIENTOS!$A:$A,"<="&EOMONTH(DATE(PORTADA!$B$2,5,1),0)) | F9: =IFERROR((D9+E9)/B9,"") | G9: =IFERROR(COMPROMISOS!$C$7/B9,"")
A10: JUNIO | B10: =PORTADA!B12 | C10: =PORTADA!C12 | D10: =B10-C10 | E10: =SUMIFS(MOVIMIENTOS!$F:$F,MOVIMIENTOS!$E:$E,"AHORRO",MOVIMIENTOS!$A:$A,">="&DATE(PORTADA!$B$2,6,1),MOVIMIENTOS!$A:$A,"<="&EOMONTH(DATE(PORTADA!$B$2,6,1),0)) | F10: =IFERROR((D10+E10)/B10,"") | G10: =IFERROR(COMPROMISOS!$C$7/B10,"")
A11: JULIO | B11: =PORTADA!B13 | C11: =PORTADA!C13 | D11: =B11-C11 | E11: =SUMIFS(MOVIMIENTOS!$F:$F,MOVIMIENTOS!$E:$E,"AHORRO",MOVIMIENTOS!$A:$A,">="&DATE(PORTADA!$B$2,7,1),MOVIMIENTOS!$A:$A,"<="&EOMONTH(DATE(PORTADA!$B$2,7,1),0)) | F11: =IFERROR((D11+E11)/B11,"") | G11: =IFERROR(COMPROMISOS!$C$7/B11,"")
A12: AGOSTO | B12: =PORTADA!B14 | C12: =PORTADA!C14 | D12: =B12-C12 | E12: =SUMIFS(MOVIMIENTOS!$F:$F,MOVIMIENTOS!$E:$E,"AHORRO",MOVIMIENTOS!$A:$A,">="&DATE(PORTADA!$B$2,8,1),MOVIMIENTOS!$A:$A,"<="&EOMONTH(DATE(PORTADA!$B$2,8,1),0)) | F12: =IFERROR((D12+E12)/B12,"") | G12: =IFERROR(COMPROMISOS!$C$7/B12,"")
A13: SEPTIEMBRE | B13: =PORTADA!B15 | C13: =PORTADA!C15 | D13: =B13-C13 | E13: =SUMIFS(MOVIMIENTOS!$F:$F,MOVIMIENTOS!$E:$E,"AHORRO",MOVIMIENTOS!$A:$A,">="&DATE(PORTADA!$B$2,9,1),MOVIMIENTOS!$A:$A,"<="&EOMONTH(DATE(PORTADA!$B$2,9,1),0)) | F13: =IFERROR((D13+E13)/B13,"") | G13: =IFERROR(COMPROMISOS!$C$7/B13,"")
A14: OCTUBRE | B14: =PORTADA!B16 | C14: =PORTADA!C16 | D14: =B14-C14 | E14: =SUMIFS(MOVIMIENTOS!$F:$F,MOVIMIENTOS!$E:$E,"AHORRO",MOVIMIENTOS!$A:$A,">="&DATE(PORTADA!$B$2,10,1),MOVIMIENTOS!$A:$A,"<="&EOMONTH(DATE(PORTADA!$B$2,10,1),0)) | F14: =IFERROR((D14+E14)/B14,"") | G14: =IFERROR(COMPROMISOS!$C$7/B14,"")
A15: NOVIEMBRE | B15: =PORTADA!B17 | C15: =PORTADA!C17 | D15: =B15-C15 | E15: =SUMIFS(MOVIMIENTOS!$F:$F,MOVIMIENTOS!$E:$E,"AHORRO",MOVIMIENTOS!$A:$A,">="&DATE(PORTADA!$B$2,11,1),MOVIMIENTOS!$A:$A,"<="&EOMONTH(DATE(PORTADA!$B$2,11,1),0)) | F15: =IFERROR((D15+E15)/B15,"") | G15: =IFERROR(COMPROMISOS!$C$7/B15,"")
A16: DICIEMBRE | B16: =PORTADA!B18 | C16: =PORTADA!C18 | D16: =B16-C16 | E16: =SUMIFS(MOVIMIENTOS!$F:$F,MOVIMIENTOS!$E:$E,"AHORRO",MOVIMIENTOS!$A:$A,">="&DATE(PORTADA!$B$2,12,1),MOVIMIENTOS!$A:$A,"<="&EOMONTH(DATE(PORTADA!$B$2,12,1),0)) | F16: =IFERROR((D16+E16)/B16,"") | G16: =IFERROR(COMPROMISOS!$C$7/B16,"")
A18: 2. PUNTO DE EQUILIBRIO | B18: ¿Cuánto tienes que ganar para no perder?
A19: Gastos fijos del mes | B19: =FIJOS!C11 | C19: Lo de FIJOS, que se paga si o si
A20: Cuotas de créditos | B20: =COMPROMISOS!C7 | C20: Lo de COMPROMISOS
A21: MÍNIMO PARA NO PERDER | B21: =B19+B20 | C21: Bajo esto, el mes cierra en rojo
A22: Ingreso promedio real | B22: =IFERROR(AVERAGEIF(B5:B16,">0"),0) | C22: Promedio de los meses con movimiento
A23: Margen sobre el mínimo | B23: =B22-B21 | C23: Lo que te queda libre cada mes
A24: Días del mes que cubre tu ingreso | B24: =IFERROR(MIN(31,ROUND(B22/(B21/30),0)),0) | C24: Con 30 o más, llegas a fin de mes
A26: 3. EN QUÉ SE VA | B26: Gasto del año por categoría. CLASE separa gasto de ahorro y deuda
A27: CATEGORÍA | B27: GASTO DEL AÑO | C27: % DEL TOTAL | D27: PRESUPUESTO AÑO | E27: DIFERENCIA | F27: VECES | G27: CLASE | H27: SOLO GASTO
A28: =CATEGORIAS!$C$11 | B28: =SUMIFS(MOVIMIENTOS!$F:$F,MOVIMIENTOS!$A:$A,">="&DATE(PORTADA!$B$2,1,1),MOVIMIENTOS!$A:$A,"<="&DATE(PORTADA!$B$2,12,31),MOVIMIENTOS!$D:$D,$A28) | C28: =IFERROR(B28/SUM($B$28:$B$50),"") | D28: =CATEGORIAS!$E$11*12 | E28: =D28-B28 | F28: =COUNTIFS(MOVIMIENTOS!$D:$D,$A28,MOVIMIENTOS!$A:$A,">="&DATE(PORTADA!$B$2,1,1),MOVIMIENTOS!$A:$A,"<="&DATE(PORTADA!$B$2,12,31)) | G28: =CATEGORIAS!$D$11 | H28: =IF(G28="GASTO",B28,"")
A29: =CATEGORIAS!$C$12 | B29: =SUMIFS(MOVIMIENTOS!$F:$F,MOVIMIENTOS!$A:$A,">="&DATE(PORTADA!$B$2,1,1),MOVIMIENTOS!$A:$A,"<="&DATE(PORTADA!$B$2,12,31),MOVIMIENTOS!$D:$D,$A29) | C29: =IFERROR(B29/SUM($B$28:$B$50),"") | D29: =CATEGORIAS!$E$12*12 | E29: =D29-B29 | F29: =COUNTIFS(MOVIMIENTOS!$D:$D,$A29,MOVIMIENTOS!$A:$A,">="&DATE(PORTADA!$B$2,1,1),MOVIMIENTOS!$A:$A,"<="&DATE(PORTADA!$B$2,12,31)) | G29: =CATEGORIAS!$D$12 | H29: =IF(G29="GASTO",B29,"")
A30: =CATEGORIAS!$C$13 | B30: =SUMIFS(MOVIMIENTOS!$F:$F,MOVIMIENTOS!$A:$A,">="&DATE(PORTADA!$B$2,1,1),MOVIMIENTOS!$A:$A,"<="&DATE(PORTADA!$B$2,12,31),MOVIMIENTOS!$D:$D,$A30) | C30: =IFERROR(B30/SUM($B$28:$B$50),"") | D30: =CATEGORIAS!$E$13*12 | E30: =D30-B30 | F30: =COUNTIFS(MOVIMIENTOS!$D:$D,$A30,MOVIMIENTOS!$A:$A,">="&DATE(PORTADA!$B$2,1,1),MOVIMIENTOS!$A:$A,"<="&DATE(PORTADA!$B$2,12,31)) | G30: =CATEGORIAS!$D$13 | H30: =IF(G30="GASTO",B30,"")
A31: =CATEGORIAS!$C$14 | B31: =SUMIFS(MOVIMIENTOS!$F:$F,MOVIMIENTOS!$A:$A,">="&DATE(PORTADA!$B$2,1,1),MOVIMIENTOS!$A:$A,"<="&DATE(PORTADA!$B$2,12,31),MOVIMIENTOS!$D:$D,$A31) | C31: =IFERROR(B31/SUM($B$28:$B$50),"") | D31: =CATEGORIAS!$E$14*12 | E31: =D31-B31 | F31: =COUNTIFS(MOVIMIENTOS!$D:$D,$A31,MOVIMIENTOS!$A:$A,">="&DATE(PORTADA!$B$2,1,1),MOVIMIENTOS!$A:$A,"<="&DATE(PORTADA!$B$2,12,31)) | G31: =CATEGORIAS!$D$14 | H31: =IF(G31="GASTO",B31,"")
A32: =CATEGORIAS!$C$15 | B32: =SUMIFS(MOVIMIENTOS!$F:$F,MOVIMIENTOS!$A:$A,">="&DATE(PORTADA!$B$2,1,1),MOVIMIENTOS!$A:$A,"<="&DATE(PORTADA!$B$2,12,31),MOVIMIENTOS!$D:$D,$A32) | C32: =IFERROR(B32/SUM($B$28:$B$50),"") | D32: =CATEGORIAS!$E$15*12 | E32: =D32-B32 | F32: =COUNTIFS(MOVIMIENTOS!$D:$D,$A32,MOVIMIENTOS!$A:$A,">="&DATE(PORTADA!$B$2,1,1),MOVIMIENTOS!$A:$A,"<="&DATE(PORTADA!$B$2,12,31)) | G32: =CATEGORIAS!$D$15 | H32: =IF(G32="GASTO",B32,"")
A33: =CATEGORIAS!$C$16 | B33: =SUMIFS(MOVIMIENTOS!$F:$F,MOVIMIENTOS!$A:$A,">="&DATE(PORTADA!$B$2,1,1),MOVIMIENTOS!$A:$A,"<="&DATE(PORTADA!$B$2,12,31),MOVIMIENTOS!$D:$D,$A33) | C33: =IFERROR(B33/SUM($B$28:$B$50),"") | D33: =CATEGORIAS!$E$16*12 | E33: =D33-B33 | F33: =COUNTIFS(MOVIMIENTOS!$D:$D,$A33,MOVIMIENTOS!$A:$A,">="&DATE(PORTADA!$B$2,1,1),MOVIMIENTOS!$A:$A,"<="&DATE(PORTADA!$B$2,12,31)) | G33: =CATEGORIAS!$D$16 | H33: =IF(G33="GASTO",B33,"")
A34: =CATEGORIAS!$C$17 | B34: =SUMIFS(MOVIMIENTOS!$F:$F,MOVIMIENTOS!$A:$A,">="&DATE(PORTADA!$B$2,1,1),MOVIMIENTOS!$A:$A,"<="&DATE(PORTADA!$B$2,12,31),MOVIMIENTOS!$D:$D,$A34) | C34: =IFERROR(B34/SUM($B$28:$B$50),"") | D34: =CATEGORIAS!$E$17*12 | E34: =D34-B34 | F34: =COUNTIFS(MOVIMIENTOS!$D:$D,$A34,MOVIMIENTOS!$A:$A,">="&DATE(PORTADA!$B$2,1,1),MOVIMIENTOS!$A:$A,"<="&DATE(PORTADA!$B$2,12,31)) | G34: =CATEGORIAS!$D$17 | H34: =IF(G34="GASTO",B34,"")
A35: =CATEGORIAS!$C$18 | B35: =SUMIFS(MOVIMIENTOS!$F:$F,MOVIMIENTOS!$A:$A,">="&DATE(PORTADA!$B$2,1,1),MOVIMIENTOS!$A:$A,"<="&DATE(PORTADA!$B$2,12,31),MOVIMIENTOS!$D:$D,$A35) | C35: =IFERROR(B35/SUM($B$28:$B$50),"") | D35: =CATEGORIAS!$E$18*12 | E35: =D35-B35 | F35: =COUNTIFS(MOVIMIENTOS!$D:$D,$A35,MOVIMIENTOS!$A:$A,">="&DATE(PORTADA!$B$2,1,1),MOVIMIENTOS!$A:$A,"<="&DATE(PORTADA!$B$2,12,31)) | G35: =CATEGORIAS!$D$18 | H35: =IF(G35="GASTO",B35,"")
A36: =CATEGORIAS!$C$19 | B36: =SUMIFS(MOVIMIENTOS!$F:$F,MOVIMIENTOS!$A:$A,">="&DATE(PORTADA!$B$2,1,1),MOVIMIENTOS!$A:$A,"<="&DATE(PORTADA!$B$2,12,31),MOVIMIENTOS!$D:$D,$A36) | C36: =IFERROR(B36/SUM($B$28:$B$50),"") | D36: =CATEGORIAS!$E$19*12 | E36: =D36-B36 | F36: =COUNTIFS(MOVIMIENTOS!$D:$D,$A36,MOVIMIENTOS!$A:$A,">="&DATE(PORTADA!$B$2,1,1),MOVIMIENTOS!$A:$A,"<="&DATE(PORTADA!$B$2,12,31)) | G36: =CATEGORIAS!$D$19 | H36: =IF(G36="GASTO",B36,"")
A37: =CATEGORIAS!$C$20 | B37: =SUMIFS(MOVIMIENTOS!$F:$F,MOVIMIENTOS!$A:$A,">="&DATE(PORTADA!$B$2,1,1),MOVIMIENTOS!$A:$A,"<="&DATE(PORTADA!$B$2,12,31),MOVIMIENTOS!$D:$D,$A37) | C37: =IFERROR(B37/SUM($B$28:$B$50),"") | D37: =CATEGORIAS!$E$20*12 | E37: =D37-B37 | F37: =COUNTIFS(MOVIMIENTOS!$D:$D,$A37,MOVIMIENTOS!$A:$A,">="&DATE(PORTADA!$B$2,1,1),MOVIMIENTOS!$A:$A,"<="&DATE(PORTADA!$B$2,12,31)) | G37: =CATEGORIAS!$D$20 | H37: =IF(G37="GASTO",B37,"")
A38: =CATEGORIAS!$C$21 | B38: =SUMIFS(MOVIMIENTOS!$F:$F,MOVIMIENTOS!$A:$A,">="&DATE(PORTADA!$B$2,1,1),MOVIMIENTOS!$A:$A,"<="&DATE(PORTADA!$B$2,12,31),MOVIMIENTOS!$D:$D,$A38) | C38: =IFERROR(B38/SUM($B$28:$B$50),"") | D38: =CATEGORIAS!$E$21*12 | E38: =D38-B38 | F38: =COUNTIFS(MOVIMIENTOS!$D:$D,$A38,MOVIMIENTOS!$A:$A,">="&DATE(PORTADA!$B$2,1,1),MOVIMIENTOS!$A:$A,"<="&DATE(PORTADA!$B$2,12,31)) | G38: =CATEGORIAS!$D$21 | H38: =IF(G38="GASTO",B38,"")
A39: =CATEGORIAS!$C$22 | B39: =SUMIFS(MOVIMIENTOS!$F:$F,MOVIMIENTOS!$A:$A,">="&DATE(PORTADA!$B$2,1,1),MOVIMIENTOS!$A:$A,"<="&DATE(PORTADA!$B$2,12,31),MOVIMIENTOS!$D:$D,$A39) | C39: =IFERROR(B39/SUM($B$28:$B$50),"") | D39: =CATEGORIAS!$E$22*12 | E39: =D39-B39 | F39: =COUNTIFS(MOVIMIENTOS!$D:$D,$A39,MOVIMIENTOS!$A:$A,">="&DATE(PORTADA!$B$2,1,1),MOVIMIENTOS!$A:$A,"<="&DATE(PORTADA!$B$2,12,31)) | G39: =CATEGORIAS!$D$22 | H39: =IF(G39="GASTO",B39,"")
A40: =CATEGORIAS!$C$23 | B40: =SUMIFS(MOVIMIENTOS!$F:$F,MOVIMIENTOS!$A:$A,">="&DATE(PORTADA!$B$2,1,1),MOVIMIENTOS!$A:$A,"<="&DATE(PORTADA!$B$2,12,31),MOVIMIENTOS!$D:$D,$A40) | C40: =IFERROR(B40/SUM($B$28:$B$50),"") | D40: =CATEGORIAS!$E$23*12 | E40: =D40-B40 | F40: =COUNTIFS(MOVIMIENTOS!$D:$D,$A40,MOVIMIENTOS!$A:$A,">="&DATE(PORTADA!$B$2,1,1),MOVIMIENTOS!$A:$A,"<="&DATE(PORTADA!$B$2,12,31)) | G40: =CATEGORIAS!$D$23 | H40: =IF(G40="GASTO",B40,"")
A41: =CATEGORIAS!$C$24 | B41: =SUMIFS(MOVIMIENTOS!$F:$F,MOVIMIENTOS!$A:$A,">="&DATE(PORTADA!$B$2,1,1),MOVIMIENTOS!$A:$A,"<="&DATE(PORTADA!$B$2,12,31),MOVIMIENTOS!$D:$D,$A41) | C41: =IFERROR(B41/SUM($B$28:$B$50),"") | D41: =CATEGORIAS!$E$24*12 | E41: =D41-B41 | F41: =COUNTIFS(MOVIMIENTOS!$D:$D,$A41,MOVIMIENTOS!$A:$A,">="&DATE(PORTADA!$B$2,1,1),MOVIMIENTOS!$A:$A,"<="&DATE(PORTADA!$B$2,12,31)) | G41: =CATEGORIAS!$D$24 | H41: =IF(G41="GASTO",B41,"")
A42: =CATEGORIAS!$C$25 | B42: =SUMIFS(MOVIMIENTOS!$F:$F,MOVIMIENTOS!$A:$A,">="&DATE(PORTADA!$B$2,1,1),MOVIMIENTOS!$A:$A,"<="&DATE(PORTADA!$B$2,12,31),MOVIMIENTOS!$D:$D,$A42) | C42: =IFERROR(B42/SUM($B$28:$B$50),"") | D42: =CATEGORIAS!$E$25*12 | E42: =D42-B42 | F42: =COUNTIFS(MOVIMIENTOS!$D:$D,$A42,MOVIMIENTOS!$A:$A,">="&DATE(PORTADA!$B$2,1,1),MOVIMIENTOS!$A:$A,"<="&DATE(PORTADA!$B$2,12,31)) | G42: =CATEGORIAS!$D$25 | H42: =IF(G42="GASTO",B42,"")
A43: =CATEGORIAS!$C$26 | B43: =SUMIFS(MOVIMIENTOS!$F:$F,MOVIMIENTOS!$A:$A,">="&DATE(PORTADA!$B$2,1,1),MOVIMIENTOS!$A:$A,"<="&DATE(PORTADA!$B$2,12,31),MOVIMIENTOS!$D:$D,$A43) | C43: =IFERROR(B43/SUM($B$28:$B$50),"") | D43: =CATEGORIAS!$E$26*12 | E43: =D43-B43 | F43: =COUNTIFS(MOVIMIENTOS!$D:$D,$A43,MOVIMIENTOS!$A:$A,">="&DATE(PORTADA!$B$2,1,1),MOVIMIENTOS!$A:$A,"<="&DATE(PORTADA!$B$2,12,31)) | G43: =CATEGORIAS!$D$26 | H43: =IF(G43="GASTO",B43,"")
A44: =CATEGORIAS!$C$27 | B44: =SUMIFS(MOVIMIENTOS!$F:$F,MOVIMIENTOS!$A:$A,">="&DATE(PORTADA!$B$2,1,1),MOVIMIENTOS!$A:$A,"<="&DATE(PORTADA!$B$2,12,31),MOVIMIENTOS!$D:$D,$A44) | C44: =IFERROR(B44/SUM($B$28:$B$50),"") | D44: =CATEGORIAS!$E$27*12 | E44: =D44-B44 | F44: =COUNTIFS(MOVIMIENTOS!$D:$D,$A44,MOVIMIENTOS!$A:$A,">="&DATE(PORTADA!$B$2,1,1),MOVIMIENTOS!$A:$A,"<="&DATE(PORTADA!$B$2,12,31)) | G44: =CATEGORIAS!$D$27 | H44: =IF(G44="GASTO",B44,"")
A45: =CATEGORIAS!$C$28 | B45: =SUMIFS(MOVIMIENTOS!$F:$F,MOVIMIENTOS!$A:$A,">="&DATE(PORTADA!$B$2,1,1),MOVIMIENTOS!$A:$A,"<="&DATE(PORTADA!$B$2,12,31),MOVIMIENTOS!$D:$D,$A45) | C45: =IFERROR(B45/SUM($B$28:$B$50),"") | D45: =CATEGORIAS!$E$28*12 | E45: =D45-B45 | F45: =COUNTIFS(MOVIMIENTOS!$D:$D,$A45,MOVIMIENTOS!$A:$A,">="&DATE(PORTADA!$B$2,1,1),MOVIMIENTOS!$A:$A,"<="&DATE(PORTADA!$B$2,12,31)) | G45: =CATEGORIAS!$D$28 | H45: =IF(G45="GASTO",B45,"")
A46: =CATEGORIAS!$C$29 | B46: =SUMIFS(MOVIMIENTOS!$F:$F,MOVIMIENTOS!$A:$A,">="&DATE(PORTADA!$B$2,1,1),MOVIMIENTOS!$A:$A,"<="&DATE(PORTADA!$B$2,12,31),MOVIMIENTOS!$D:$D,$A46) | C46: =IFERROR(B46/SUM($B$28:$B$50),"") | D46: =CATEGORIAS!$E$29*12 | E46: =D46-B46 | F46: =COUNTIFS(MOVIMIENTOS!$D:$D,$A46,MOVIMIENTOS!$A:$A,">="&DATE(PORTADA!$B$2,1,1),MOVIMIENTOS!$A:$A,"<="&DATE(PORTADA!$B$2,12,31)) | G46: =CATEGORIAS!$D$29 | H46: =IF(G46="GASTO",B46,"")
A47: =CATEGORIAS!$C$30 | B47: =SUMIFS(MOVIMIENTOS!$F:$F,MOVIMIENTOS!$A:$A,">="&DATE(PORTADA!$B$2,1,1),MOVIMIENTOS!$A:$A,"<="&DATE(PORTADA!$B$2,12,31),MOVIMIENTOS!$D:$D,$A47) | C47: =IFERROR(B47/SUM($B$28:$B$50),"") | D47: =CATEGORIAS!$E$30*12 | E47: =D47-B47 | F47: =COUNTIFS(MOVIMIENTOS!$D:$D,$A47,MOVIMIENTOS!$A:$A,">="&DATE(PORTADA!$B$2,1,1),MOVIMIENTOS!$A:$A,"<="&DATE(PORTADA!$B$2,12,31)) | G47: =CATEGORIAS!$D$30 | H47: =IF(G47="GASTO",B47,"")
A48: =CATEGORIAS!$C$31 | B48: =SUMIFS(MOVIMIENTOS!$F:$F,MOVIMIENTOS!$A:$A,">="&DATE(PORTADA!$B$2,1,1),MOVIMIENTOS!$A:$A,"<="&DATE(PORTADA!$B$2,12,31),MOVIMIENTOS!$D:$D,$A48) | C48: =IFERROR(B48/SUM($B$28:$B$50),"") | D48: =CATEGORIAS!$E$31*12 | E48: =D48-B48 | F48: =COUNTIFS(MOVIMIENTOS!$D:$D,$A48,MOVIMIENTOS!$A:$A,">="&DATE(PORTADA!$B$2,1,1),MOVIMIENTOS!$A:$A,"<="&DATE(PORTADA!$B$2,12,31)) | G48: =CATEGORIAS!$D$31 | H48: =IF(G48="GASTO",B48,"")
A49: =CATEGORIAS!$C$32 | B49: =SUMIFS(MOVIMIENTOS!$F:$F,MOVIMIENTOS!$A:$A,">="&DATE(PORTADA!$B$2,1,1),MOVIMIENTOS!$A:$A,"<="&DATE(PORTADA!$B$2,12,31),MOVIMIENTOS!$D:$D,$A49) | C49: =IFERROR(B49/SUM($B$28:$B$50),"") | D49: =CATEGORIAS!$E$32*12 | E49: =D49-B49 | F49: =COUNTIFS(MOVIMIENTOS!$D:$D,$A49,MOVIMIENTOS!$A:$A,">="&DATE(PORTADA!$B$2,1,1),MOVIMIENTOS!$A:$A,"<="&DATE(PORTADA!$B$2,12,31)) | G49: =CATEGORIAS!$D$32 | H49: =IF(G49="GASTO",B49,"")
A50: =CATEGORIAS!$C$33 | B50: =SUMIFS(MOVIMIENTOS!$F:$F,MOVIMIENTOS!$A:$A,">="&DATE(PORTADA!$B$2,1,1),MOVIMIENTOS!$A:$A,"<="&DATE(PORTADA!$B$2,12,31),MOVIMIENTOS!$D:$D,$A50) | C50: =IFERROR(B50/SUM($B$28:$B$50),"") | D50: =CATEGORIAS!$E$33*12 | E50: =D50-B50 | F50: =COUNTIFS(MOVIMIENTOS!$D:$D,$A50,MOVIMIENTOS!$A:$A,">="&DATE(PORTADA!$B$2,1,1),MOVIMIENTOS!$A:$A,"<="&DATE(PORTADA!$B$2,12,31)) | G50: =CATEGORIAS!$D$33 | H50: =IF(G50="GASTO",B50,"")
A52: 4. LAS CINCO QUE MÁS PESAN | B52: Solo gasto de verdad: el ahorro y las cuotas no cuentan acá
A53: PUESTO | B53: CATEGORÍA | C53: GASTO DEL AÑO | D53: % DEL TOTAL
A54: 1 | B54: =IFERROR(INDEX($A$28:$A$50,MATCH(LARGE($H$28:$H$50,1),$H$28:$H$50,0)),"") | C54: =IFERROR(LARGE($H$28:$H$50,1),0) | D54: =IFERROR(C54/SUM($H$28:$H$50),"")
A55: 2 | B55: =IFERROR(INDEX($A$28:$A$50,MATCH(LARGE($H$28:$H$50,2),$H$28:$H$50,0)),"") | C55: =IFERROR(LARGE($H$28:$H$50,2),0) | D55: =IFERROR(C55/SUM($H$28:$H$50),"")
A56: 3 | B56: =IFERROR(INDEX($A$28:$A$50,MATCH(LARGE($H$28:$H$50,3),$H$28:$H$50,0)),"") | C56: =IFERROR(LARGE($H$28:$H$50,3),0) | D56: =IFERROR(C56/SUM($H$28:$H$50),"")
A57: 4 | B57: =IFERROR(INDEX($A$28:$A$50,MATCH(LARGE($H$28:$H$50,4),$H$28:$H$50,0)),"") | C57: =IFERROR(LARGE($H$28:$H$50,4),0) | D57: =IFERROR(C57/SUM($H$28:$H$50),"")
A58: 5 | B58: =IFERROR(INDEX($A$28:$A$50,MATCH(LARGE($H$28:$H$50,5),$H$28:$H$50,0)),"") | C58: =IFERROR(LARGE($H$28:$H$50,5),0) | D58: =IFERROR(C58/SUM($H$28:$H$50),"")
A60: 5. GASTO HORMIGA | B60: Las compras chicas que por separado no duelen
A61: Monto bajo el cual cuenta como hormiga | B61: 10000 | C61: Cámbialo si tu criterio es otro
A62: Compras chicas en el año | B62: =COUNTIFS(MOVIMIENTOS!$F:$F,"<"&$B$61,MOVIMIENTOS!$F:$F,">0",MOVIMIENTOS!$B:$B,"EGRESO",MOVIMIENTOS!$A:$A,">="&DATE(PORTADA!$B$2,1,1),MOVIMIENTOS!$A:$A,"<="&DATE(PORTADA!$B$2,12,31))
A63: Cuánto suman | B63: =SUMIFS(MOVIMIENTOS!$F:$F,MOVIMIENTOS!$F:$F,"<"&$B$61,MOVIMIENTOS!$B:$B,"EGRESO",MOVIMIENTOS!$A:$A,">="&DATE(PORTADA!$B$2,1,1),MOVIMIENTOS!$A:$A,"<="&DATE(PORTADA!$B$2,12,31))
A64: Qué porcentaje del gasto son | B64: =IFERROR(B63/SUM($H$28:$H$50),"")
A65: Equivalen a este gasto fijo | B65: =IFERROR(B63/12,0)
A67: 6. PRECIOS QUE VIGILO | B67: Escribe un producto y la planilla te dice cuánto subió
A68: PRODUCTO (escríbelo tú) | B68: PRIMERA COMPRA | C68: ÚLTIMA COMPRA | D68: VARIACIÓN | E68: VECES COMPRADO | F68: GASTO TOTAL
B69: =IFERROR(INDEX(DETALLE!$F:$F,MATCH(1,INDEX((ISNUMBER(SEARCH($A69,DETALLE!$D:$D)))*(DETALLE!$D:$D<>""),0),0)),"") | C69: =IFERROR(LOOKUP(2,1/(ISNUMBER(SEARCH($A69,DETALLE!$D:$D))*(DETALLE!$F:$F>0)),DETALLE!$F:$F),"") | D69: =IFERROR(C69/B69-1,"") | E69: =IF($A69="","",SUMPRODUCT(--ISNUMBER(SEARCH($A69,DETALLE!$D$4:$D$500)))) | F69: =IF($A69="","",SUMPRODUCT(--ISNUMBER(SEARCH($A69,DETALLE!$D$4:$D$500)),DETALLE!$G$4:$G$500))
B70: =IFERROR(INDEX(DETALLE!$F:$F,MATCH(1,INDEX((ISNUMBER(SEARCH($A70,DETALLE!$D:$D)))*(DETALLE!$D:$D<>""),0),0)),"") | C70: =IFERROR(LOOKUP(2,1/(ISNUMBER(SEARCH($A70,DETALLE!$D:$D))*(DETALLE!$F:$F>0)),DETALLE!$F:$F),"") | D70: =IFERROR(C70/B70-1,"") | E70: =IF($A70="","",SUMPRODUCT(--ISNUMBER(SEARCH($A70,DETALLE!$D$4:$D$500)))) | F70: =IF($A70="","",SUMPRODUCT(--ISNUMBER(SEARCH($A70,DETALLE!$D$4:$D$500)),DETALLE!$G$4:$G$500))
B71: =IFERROR(INDEX(DETALLE!$F:$F,MATCH(1,INDEX((ISNUMBER(SEARCH($A71,DETALLE!$D:$D)))*(DETALLE!$D:$D<>""),0),0)),"") | C71: =IFERROR(LOOKUP(2,1/(ISNUMBER(SEARCH($A71,DETALLE!$D:$D))*(DETALLE!$F:$F>0)),DETALLE!$F:$F),"") | D71: =IFERROR(C71/B71-1,"") | E71: =IF($A71="","",SUMPRODUCT(--ISNUMBER(SEARCH($A71,DETALLE!$D$4:$D$500)))) | F71: =IF($A71="","",SUMPRODUCT(--ISNUMBER(SEARCH($A71,DETALLE!$D$4:$D$500)),DETALLE!$G$4:$G$500))
B72: =IFERROR(INDEX(DETALLE!$F:$F,MATCH(1,INDEX((ISNUMBER(SEARCH($A72,DETALLE!$D:$D)))*(DETALLE!$D:$D<>""),0),0)),"") | C72: =IFERROR(LOOKUP(2,1/(ISNUMBER(SEARCH($A72,DETALLE!$D:$D))*(DETALLE!$F:$F>0)),DETALLE!$F:$F),"") | D72: =IFERROR(C72/B72-1,"") | E72: =IF($A72="","",SUMPRODUCT(--ISNUMBER(SEARCH($A72,DETALLE!$D$4:$D$500)))) | F72: =IF($A72="","",SUMPRODUCT(--ISNUMBER(SEARCH($A72,DETALLE!$D$4:$D$500)),DETALLE!$G$4:$G$500))
B73: =IFERROR(INDEX(DETALLE!$F:$F,MATCH(1,INDEX((ISNUMBER(SEARCH($A73,DETALLE!$D:$D)))*(DETALLE!$D:$D<>""),0),0)),"") | C73: =IFERROR(LOOKUP(2,1/(ISNUMBER(SEARCH($A73,DETALLE!$D:$D))*(DETALLE!$F:$F>0)),DETALLE!$F:$F),"") | D73: =IFERROR(C73/B73-1,"") | E73: =IF($A73="","",SUMPRODUCT(--ISNUMBER(SEARCH($A73,DETALLE!$D$4:$D$500)))) | F73: =IF($A73="","",SUMPRODUCT(--ISNUMBER(SEARCH($A73,DETALLE!$D$4:$D$500)),DETALLE!$G$4:$G$500))
B74: =IFERROR(INDEX(DETALLE!$F:$F,MATCH(1,INDEX((ISNUMBER(SEARCH($A74,DETALLE!$D:$D)))*(DETALLE!$D:$D<>""),0),0)),"") | C74: =IFERROR(LOOKUP(2,1/(ISNUMBER(SEARCH($A74,DETALLE!$D:$D))*(DETALLE!$F:$F>0)),DETALLE!$F:$F),"") | D74: =IFERROR(C74/B74-1,"") | E74: =IF($A74="","",SUMPRODUCT(--ISNUMBER(SEARCH($A74,DETALLE!$D$4:$D$500)))) | F74: =IF($A74="","",SUMPRODUCT(--ISNUMBER(SEARCH($A74,DETALLE!$D$4:$D$500)),DETALLE!$G$4:$G$500))
B75: =IFERROR(INDEX(DETALLE!$F:$F,MATCH(1,INDEX((ISNUMBER(SEARCH($A75,DETALLE!$D:$D)))*(DETALLE!$D:$D<>""),0),0)),"") | C75: =IFERROR(LOOKUP(2,1/(ISNUMBER(SEARCH($A75,DETALLE!$D:$D))*(DETALLE!$F:$F>0)),DETALLE!$F:$F),"") | D75: =IFERROR(C75/B75-1,"") | E75: =IF($A75="","",SUMPRODUCT(--ISNUMBER(SEARCH($A75,DETALLE!$D$4:$D$500)))) | F75: =IF($A75="","",SUMPRODUCT(--ISNUMBER(SEARCH($A75,DETALLE!$D$4:$D$500)),DETALLE!$G$4:$G$500))
B76: =IFERROR(INDEX(DETALLE!$F:$F,MATCH(1,INDEX((ISNUMBER(SEARCH($A76,DETALLE!$D:$D)))*(DETALLE!$D:$D<>""),0),0)),"") | C76: =IFERROR(LOOKUP(2,1/(ISNUMBER(SEARCH($A76,DETALLE!$D:$D))*(DETALLE!$F:$F>0)),DETALLE!$F:$F),"") | D76: =IFERROR(C76/B76-1,"") | E76: =IF($A76="","",SUMPRODUCT(--ISNUMBER(SEARCH($A76,DETALLE!$D$4:$D$500)))) | F76: =IF($A76="","",SUMPRODUCT(--ISNUMBER(SEARCH($A76,DETALLE!$D$4:$D$500)),DETALLE!$G$4:$G$500))
A78: 7. QUÉ HACER CON ESTO
A79: =IF(B22=0,"Carga movimientos y esta hoja empieza a hablar.",IF(B23<0,CONCATENATE("Tu ingreso promedio no alcanza a cubrir lo fijo. Te faltan ",TEXT(-B23,"$#,##0")," al mes."),CONCATENATE("Después de lo fijo te quedan ",TEXT(B23,"$#,##0")," al mes.")))
A80: =IFERROR(IF(AVERAGEIF(G5:G16,">0")>0.3,CONCATENATE("Las cuotas se llevan el ",TEXT(AVERAGEIF(G5:G16,">0"),"0%")," de tu ingreso. Sobre 30% la deuda manda sobre el presupuesto."),CONCATENATE("Las cuotas se llevan el ",TEXT(AVERAGEIF(G5:G16,">0"),"0%")," de tu ingreso, que está en rango sano.")),"")
A81: =IFERROR(CONCATENATE("Tu mayor gasto es ",INDEX(B54:B58,1)," con ",TEXT(INDEX(C54:C58,1),"$#,##0"),", el ",TEXT(INDEX(D54:D58,1),"0%")," de todo lo que gastas."),"")
A82: =IFERROR(IF(B64=0,"",CONCATENATE("Las compras bajo ",TEXT($B$61,"$#,##0")," suman ",TEXT(B63,"$#,##0")," al año: el ",TEXT(B64,"0%")," de tu gasto. Es como tener un gasto fijo de ",TEXT(B65,"$#,##0")," al mes.")),"")
A83: =IFERROR(CONCATENATE("Estás ahorrando el ",TEXT(AVERAGEIF(F5:F16,"<>"),"0%")," de lo que entra."),"")

Sheet CATEGORIAS
A1: CATEGORÍAS · la lista maestra: aquí se agrega o se renombra
A2: La columna PALABRAS CLAVE es lo que la app usa para adivinar la categoría de una boleta. Agrega ahí el comercio que no reconozca.
A3: TIPO | B3: GRUPO | C3: CATEGORÍA | D3: CLASE | E3: PRESUPUESTO MES | F3: PALABRAS CLAVE
A4: INGRESO | B4: SUELDO | C4: QUINCENA | D4: INGRESO | E4: 250000
A5: INGRESO | B5: SUELDO | C5: PAGO FIN DE MES | D5: INGRESO | E5: 650000
A6: INGRESO | B6: NEGOCIO | C6: EFFICIENTCHILE | D6: INGRESO | E6: 100000
A7: INGRESO | B7: NEGOCIO | C7: VENTA DE ARTICULO | D7: INGRESO | E7: 0
A8: INGRESO | B8: NEGOCIO | C8: VENTA DE SERVICIO | D8: INGRESO | E8: 0
A9: INGRESO | B9: OTROS | C9: COBROS PENDIENTES | D9: INGRESO | E9: 0
A10: INGRESO | B10: OTROS | C10: OTROS INGRESOS | D10: INGRESO | E10: 0
A11: EGRESO | B11: CUENTAS PERSONALES | C11: PREST. AUTO | D11: DEUDA | E11: 118000
A12: EGRESO | B12: CUENTAS PERSONALES | C12: AHORRO CASA | D12: AHORRO | E12: 370000
A13: EGRESO | B13: HIJOS | C13: PENSIONES | D13: GASTO | E13: 240800
A14: EGRESO | B14: HIJOS | C14: ROPA Y REGALOS | D14: GASTO | E14: 25000 | F14: JUGUETERIA, JUGUETE, REGALO
A15: EGRESO | B15: HIJOS | C15: AHORRO EMERGENCIAS | D15: AHORRO | E15: 15000
A16: EGRESO | B16: HIJOS | C16: SALIDAS CON FAMILIA | D16: GASTO | E16: 20000 | F16: CINEMARK, CINE HOYTS, CINEPLANET, ZOOLOGICO, MUSEO
A17: EGRESO | B17: CASA | C17: COMIDA CASA | D17: GASTO | E17: 10000 | F17: LIDER, JUMBO, SANTA ISABEL, UNIMARC, TOTTUS, ACUENTA, SUPERMERCADO, MAYORISTA, ALVI, VERDULERIA, CARNICERIA, PANADERIA, FERIA, ABARROTE, MINIMARKET
A18: EGRESO | B18: CASA | C18: COMIDA PERSONAL | D18: GASTO | E18: 10000 | F18: MCDONALD, BURGER, DOMINO, PAPA JOHN, SUBWAY, STARBUCKS, JUAN MAESTRO, DOGGIS, PIZZA, SUSHI, CAFE, RESTAURANT, EMPANADA, COMPLETO, PEDIDOSYA, RAPPI
A19: EGRESO | B19: CASA | C19: CUENTAS | D19: GASTO | E19: 80000 | F19: ENEL, CGE, CHILQUINTA, SAESA, ESVAL, ESSBIO, AGUAS, LIPIGAS, ABASTIBLE, GASCO, ENTEL, MOVISTAR, WOM, CLARO, VTR, CONTRIBUCION, TESORERIA
A20: EGRESO | B20: SALUD | C20: MEDICAMENTOS | D20: GASTO | E20: 5000 | F20: FARMACIA, CRUZ VERDE, SALCOBRAND, AHUMADA, DR SIMI, BOTICA, CLINICA, LABORATORIO
A21: EGRESO | B21: SALUD | C21: ROPA | D21: GASTO | E21: 0 | F21: ZARA, H&M, FALABELLA, PARIS, RIPLEY, HITES, TRICOT, CALZADO, ZAPATERIA
A22: EGRESO | B22: SALUD | C22: DEPORTE | D22: GASTO | E22: 12000 | F22: GIMNASIO, SPORTLIFE, SMART FIT, DECATHLON, DEPORTE, PADEL, GYM
A23: EGRESO | B23: AUTO | C23: BENCINA | D23: GASTO | E23: 30000 | F23: COPEC, SHELL, PETROBRAS, ARAMCO, ENEX, TERPEL, COMBUSTIBLE, BENCINA, DIESEL, SERVICENTRO
A24: EGRESO | B24: AUTO | C24: OTROS | D24: GASTO | E24: 5000 | F24: AUTOMOTRIZ, REPUESTO, VULCANIZACION, NEUMATICO, SERVITECA, LAVADO DE AUTO, TALLER MECANICO, REVISION TECNICA
A25: EGRESO | B25: DIVERSION | C25: COPETE | D25: GASTO | E25: 10000 | F25: BOTILLERIA, LICOR, CERVEZA, VINO, PISCO, WHISKY, CERVECERIA
A26: EGRESO | B26: DIVERSION | C26: WEED | D26: GASTO | E26: 5000
A27: EGRESO | B27: DIVERSION | C27: CARCASA CELULAR | D27: GASTO | E27: 8000
A28: EGRESO | B28: DIVERSION | C28: SALIDA CON AMIGOS | D28: GASTO | E28: 6000 | F28: DISCOTEQUE, KARAOKE
A29: EGRESO | B29: OTROS | C29: CHICHES | D29: GASTO | E29: 5000 | F29: PC FACTORY, SPDIGITAL, WINPY, TECNOLOGIA, ELECTRONICA, CELULAR, AUDIFONO, CARGADOR, LIBRERIA
A30: EGRESO | B30: OTROS | C30: DONACIONES | D30: GASTO | E30: 5000
A31: EGRESO | B31: OTROS | C31: PRESTAMOS | D31: GASTO | E31: 0
A32: EGRESO | B32: OTROS | C32: LOCOMOCION | D32: GASTO | E32: 0 | F32: UBER, CABIFY, DIDI, TAXI, METRO, PEAJE, AUTOPISTA, ESTACIONAMIENTO, PULLMAN, TURBUS, PASAJE
A33: EGRESO | B33: OTROS | C33: OTROS GASTOS | D33: GASTO | E33: 10000 | F33: FERRETERIA, SODIMAC, EASY, CONSTRUMART, IMPERIAL, PREUNIC, LA POLAR, MERCADO LIBRE, CORREOS, CHILEXPRESS, STARKEN

Sheet MOVIMIENTOS
A1: MOVIMIENTOS · la base de datos: una fila por ingreso o gasto
A2: La app escribe acá sola. Puedes agregar filas a mano abajo de todo; no borres la fila de títulos.
A3: FECHA | B3: TIPO | C3: GRUPO | D3: CATEGORÍA | E3: CLASE | F3: MONTO | G3: DETALLE | H3: DOCUMENTO | I3: ORIGEN | J3: ID

Sheet FIJOS
A1: GASTOS FIJOS · lo que se paga todos los meses
A2: Lo que vive acá no se escanea: se repite solo. Las cuotas de créditos NO van acá sino en COMPROMISOS, o se contarían dos veces.
A3: CONCEPTO | B3: CATEGORÍA | C3: MONTO | D3: DÍA DE PAGO | E3: NOTA
A4: Pensiones hijos | B4: PENSIONES | C4: 240800 | D4: 5 | E4: Dos pensiones
A5: Wom | B5: CUENTAS | C5: 28981 | D5: 15
A6: Luz | B6: CUENTAS | C6: 15000 | D6: 20
A7: Gas | B7: CUENTAS | C7: 20000 | D7: 20
A8: Agua | B8: CUENTAS | C8: 12000 | D8: 20
A9: Ahorro casa | B9: AHORRO CASA | C9: 370000 | D9: 30 | E9: Meta de vivienda
A10: Ahorro emergencias | B10: AHORRO EMERGENCIAS | C10: 15000 | D10: 30
A11: TOTAL FIJO AL MES | C11: =SUM(C4:C10)

Sheet COMPROMISOS
A1: COMPROMISOS · créditos en cuotas
A2: Escribe la cuota inicial una vez. Las cuotas pagadas se calculan solas con la fecha de hoy, y la columna TERMINA te dice cuándo se acaba.
A3: ACREEDOR | B3: QUÉ ES | C3: CUOTA | D3: PAGADAS | E3: TOTAL | F3: PENDIENTE | G3: AVANCE | H3: PRIMERA CUOTA | I3: TERMINA
A4: Caja los Andes | B4: Credito consumo | C4: 117650 | D4: =MEDIAN(0,E4,DATEDIF(H4,TODAY(),"M")+1) | E4: 24 | F4: =(E4-D4)*C4 | G4: =IFERROR(D4/E4,0) | H4: 2025-03-05 | I4: =EDATE(H4,E4-1)
A5: Wom | B5: Equipo en cuotas | C5: 5000 | D5: =MEDIAN(0,E5,DATEDIF(H5,TODAY(),"M")+1) | E5: 12 | F5: =(E5-D5)*C5 | G5: =IFERROR(D5/E5,0) | H5: 2026-05-10 | I5: =EDATE(H5,E5-1)
A6: Contador | B6: Servicio | C6: 60000 | D6: =MEDIAN(0,E6,DATEDIF(H6,TODAY(),"M")+1) | E6: 1 | F6: =(E6-D6)*C6 | G6: =IFERROR(D6/E6,0) | H6: 2026-08-01 | I6: =EDATE(H6,E6-1)
A7: TOTAL | C7: =SUM(C4:C6) | F7: =SUM(F4:F6)

Sheet INVERSIONES
A1: INVERSIONES · plata puesta que espera volver
A2: Separado de los gastos a propósito: una inversión no es plata que se fue, es plata que cambió de forma.
A3: PROYECTO | B3: TIPO | C3: INVERTIDO | D3: RECUPERADO | E3: SALDO | F3: ESTADO
A4: Restauracion Daewoo | B4: Auto | C4: 22000 | D4: 0 | E4: =D4-C4 | F4: En curso
A5: Paneles Quintero | B5: Servicio | C5: 0 | D5: 65000 | E5: =D5-C5 | F5: Por cobrar
A6: Carrera Ingenieria | B6: Estudios | C6: 260000 | D6: 0 | E6: =D6-C6 | F6: En curso
A7: TOTAL | C7: =SUM(C4:C6) | D7: =SUM(D4:D6) | E7: =SUM(E4:E6)

Sheet ENERO
A1: ENERO · ingresos y egresos
A2: =CONCATENATE("Año ",PORTADA!$B$2," · verde = lo escribes tú · azul = se calcula solo")
S3: DÍA A DÍA
A4: INGRESOS | S4: DÍA | T4: CUENTAS PERSONALES | U4: HIJOS | V4: CASA | W4: SALUD | X4: AUTO | Y4: DIVERSION | Z4: OTROS | AA4: TOTAL
A5: GRUPO | B5: CATEGORÍA | C5: PRESUPUESTO | D5: REAL | E5: DIFERENCIA | F5: % LOGRO | S5: =IF(DAY(DATE(PORTADA!$B$2,1,1))<>1,"",1) | T5: =IF(DAY(DATE(PORTADA!$B$2,1,1))<>1,"",SUMIFS(MOVIMIENTOS!$F:$F,MOVIMIENTOS!$A:$A,DATE(PORTADA!$B$2,1,1),MOVIMIENTOS!$C:$C,T$4)) | U5: =IF(DAY(DATE(PORTADA!$B$2,1,1))<>1,"",SUMIFS(MOVIMIENTOS!$F:$F,MOVIMIENTOS!$A:$A,DATE(PORTADA!$B$2,1,1),MOVIMIENTOS!$C:$C,U$4)) | V5: =IF(DAY(DATE(PORTADA!$B$2,1,1))<>1,"",SUMIFS(MOVIMIENTOS!$F:$F,MOVIMIENTOS!$A:$A,DATE(PORTADA!$B$2,1,1),MOVIMIENTOS!$C:$C,V$4)) | W5: =IF(DAY(DATE(PORTADA!$B$2,1,1))<>1,"",SUMIFS(MOVIMIENTOS!$F:$F,MOVIMIENTOS!$A:$A,DATE(PORTADA!$B$2,1,1),MOVIMIENTOS!$C:$C,W$4)) | X5: =IF(DAY(DATE(PORTADA!$B$2,1,1))<>1,"",SUMIFS(MOVIMIENTOS!$F:$F,MOVIMIENTOS!$A:$A,DATE(PORTADA!$B$2,1,1),MOVIMIENTOS!$C:$C,X$4)) | Y5: =IF(DAY(DATE(PORTADA!$B$2,1,1))<>1,"",SUMIFS(MOVIMIENTOS!$F:$F,MOVIMIENTOS!$A:$A,DATE(PORTADA!$B$2,1,1),MOVIMIENTOS!$C:$C,Y$4)) | Z5: =IF(DAY(DATE(PORTADA!$B$2,1,1))<>1,"",SUMIFS(MOVIMIENTOS!$F:$F,MOVIMIENTOS!$A:$A,DATE(PORTADA!$B$2,1,1),MOVIMIENTOS!$C:$C,Z$4)) | AA5: =IF(DAY(DATE(PORTADA!$B$2,1,1))<>1,"",SUM(T5:Z5))
A6: SUELDO | B6: QUINCENA | C6: =CATEGORIAS!$E$4 | D6: =SUMIFS(MOVIMIENTOS!$F:$F,MOVIMIENTOS!$A:$A,">="&DATE(PORTADA!$B$2,1,1),MOVIMIENTOS!$A:$A,"<="&EOMONTH(DATE(PORTADA!$B$2,1,1),0),MOVIMIENTOS!$D:$D,$B6) | E6: =D6-C6 | F6: =IFERROR(D6/C6,"") | S6: =IF(DAY(DATE(PORTADA!$B$2,1,2))<>2,"",2) | T6: =IF(DAY(DATE(PORTADA!$B$2,1,2))<>2,"",SUMIFS(MOVIMIENTOS!$F:$F,MOVIMIENTOS!$A:$A,DATE(PORTADA!$B$2,1,2),MOVIMIENTOS!$C:$C,T$4)) | U6: =IF(DAY(DATE(PORTADA!$B$2,1,2))<>2,"",SUMIFS(MOVIMIENTOS!$F:$F,MOVIMIENTOS!$A:$A,DATE(PORTADA!$B$2,1,2),MOVIMIENTOS!$C:$C,U$4)) | V6: =IF(DAY(DATE(PORTADA!$B$2,1,2))<>2,"",SUMIFS(MOVIMIENTOS!$F:$F,MOVIMIENTOS!$A:$A,DATE(PORTADA!$B$2,1,2),MOVIMIENTOS!$C:$C,V$4)) | W6: =IF(DAY(DATE(PORTADA!$B$2,1,2))<>2,"",SUMIFS(MOVIMIENTOS!$F:$F,MOVIMIENTOS!$A:$A,DATE(PORTADA!$B$2,1,2),MOVIMIENTOS!$C:$C,W$4)) | X6: =IF(DAY(DATE(PORTADA!$B$2,1,2))<>2,"",SUMIFS(MOVIMIENTOS!$F:$F,MOVIMIENTOS!$A:$A,DATE(PORTADA!$B$2,1,2),MOVIMIENTOS!$C:$C,X$4)) | Y6: =IF(DAY(DATE(PORTADA!$B$2,1,2))<>2,"",SUMIFS(MOVIMIENTOS!$F:$F,MOVIMIENTOS!$A:$A,DATE(PORTADA!$B$2,1,2),MOVIMIENTOS!$C:$C,Y$4)) | Z6: =IF(DAY(DATE(PORTADA!$B$2,1,2))<>2,"",SUMIFS(MOVIMIENTOS!$F:$F,MOVIMIENTOS!$A:$A,DATE(PORTADA!$B$2,1,2),MOVIMIENTOS!$C:$C,Z$4)) | AA6: =IF(DAY(DATE(PORTADA!$B$2,1,2))<>2,"",SUM(T6:Z6))
A7: SUELDO | B7: PAGO FIN DE MES | C7: =CATEGORIAS!$E$5 | D7: =SUMIFS(MOVIMIENTOS!$F:$F,MOVIMIENTOS!$A:$A,">="&DATE(PORTADA!$B$2,1,1),MOVIMIENTOS!$A:$A,"<="&EOMONTH(DATE(PORTADA!$B$2,1,1),0),MOVIMIENTOS!$D:$D,$B7) | E7: =D7-C7 | F7: =IFERROR(D7/C7,"") | S7: =IF(DAY(DATE(PORTADA!$B$2,1,3))<>3,"",3) | T7: =IF(DAY(DATE(PORTADA!$B$2,1,3))<>3,"",SUMIFS(MOVIMIENTOS!$F:$F,MOVIMIENTOS!$A:$A,DATE(PORTADA!$B$2,1,3),MOVIMIENTOS!$C:$C,T$4)) | U7: =IF(DAY(DATE(PORTADA!$B$2,1,3))<>3,"",SUMIFS(MOVIMIENTOS!$F:$F,MOVIMIENTOS!$A:$A,DATE(PORTADA!$B$2,1,3),MOVIMIENTOS!$C:$C,U$4)) | V7: =IF(DAY(DATE(PORTADA!$B$2,1,3))<>3,"",SUMIFS(MOVIMIENTOS!$F:$F,MOVIMIENTOS!$A:$A,DATE(PORTADA!$B$2,1,3),MOVIMIENTOS!$C:$C,V$4)) | W7: =IF(DAY(DATE(PORTADA!$B$2,1,3))<>3,"",SUMIFS(MOVIMIENTOS!$F:$F,MOVIMIENTOS!$A:$A,DATE(PORTADA!$B$2,1,3),MOVIMIENTOS!$C:$C,W$4)) | X7: =IF(DAY(DATE(PORTADA!$B$2,1,3))<>3,"",SUMIFS(MOVIMIENTOS!$F:$F,MOVIMIENTOS!$A:$A,DATE(PORTADA!$B$2,1,3),MOVIMIENTOS!$C:$C,X$4)) | Y7: =IF(DAY(DATE(PORTADA!$B$2,1,3))<>3,"",SUMIFS(MOVIMIENTOS!$F:$F,MOVIMIENTOS!$A:$A,DATE(PORTADA!$B$2,1,3),MOVIMIENTOS!$C:$C,Y$4)) | Z7: =IF(DAY(DATE(PORTADA!$B$2,1,3))<>3,"",SUMIFS(MOVIMIENTOS!$F:$F,MOVIMIENTOS!$A:$A,DATE(PORTADA!$B$2,1,3),MOVIMIENTOS!$C:$C,Z$4)) | AA7: =IF(DAY(DATE(PORTADA!$B$2,1,3))<>3,"",SUM(T7:Z7))
A8: NEGOCIO | B8: EFFICIENTCHILE | C8: =CATEGORIAS!$E$6 | D8: =SUMIFS(MOVIMIENTOS!$F:$F,MOVIMIENTOS!$A:$A,">="&DATE(PORTADA!$B$2,1,1),MOVIMIENTOS!$A:$A,"<="&EOMONTH(DATE(PORTADA!$B$2,1,1),0),MOVIMIENTOS!$D:$D,$B8) | E8: =D8-C8 | F8: =IFERROR(D8/C8,"") | S8: =IF(DAY(DATE(PORTADA!$B$2,1,4))<>4,"",4) | T8: =IF(DAY(DATE(PORTADA!$B$2,1,4))<>4,"",SUMIFS(MOVIMIENTOS!$F:$F,MOVIMIENTOS!$A:$A,DATE(PORTADA!$B$2,1,4),MOVIMIENTOS!$C:$C,T$4)) | U8: =IF(DAY(DATE(PORTADA!$B$2,1,4))<>4,"",SUMIFS(MOVIMIENTOS!$F:$F,MOVIMIENTOS!$A:$A,DATE(PORTADA!$B$2,1,4),MOVIMIENTOS!$C:$C,U$4)) | V8: =IF(DAY(DATE(PORTADA!$B$2,1,4))<>4,"",SUMIFS(MOVIMIENTOS!$F:$F,MOVIMIENTOS!$A:$A,DATE(PORTADA!$B$2,1,4),MOVIMIENTOS!$C:$C,V$4)) | W8: =IF(DAY(DATE(PORTADA!$B$2,1,4))<>4,"",SUMIFS(MOVIMIENTOS!$F:$F,MOVIMIENTOS!$A:$A,DATE(PORTADA!$B$2,1,4),MOVIMIENTOS!$C:$C,W$4)) | X8: =IF(DAY(DATE(PORTADA!$B$2,1,4))<>4,"",SUMIFS(MOVIMIENTOS!$F:$F,MOVIMIENTOS!$A:$A,DATE(PORTADA!$B$2,1,4),MOVIMIENTOS!$C:$C,X$4)) | Y8: =IF(DAY(DATE(PORTADA!$B$2,1,4))<>4,"",SUMIFS(MOVIMIENTOS!$F:$F,MOVIMIENTOS!$A:$A,DATE(PORTADA!$B$2,1,4),MOVIMIENTOS!$C:$C,Y$4)) | Z8: =IF(DAY(DATE(PORTADA!$B$2,1,4))<>4,"",SUMIFS(MOVIMIENTOS!$F:$F,MOVIMIENTOS!$A:$A,DATE(PORTADA!$B$2,1,4),MOVIMIENTOS!$C:$C,Z$4)) | AA8: =IF(DAY(DATE(PORTADA!$B$2,1,4))<>4,"",SUM(T8:Z8))
A9: NEGOCIO | B9: VENTA DE ARTICULO | C9: =CATEGORIAS!$E$7 | D9: =SUMIFS(MOVIMIENTOS!$F:$F,MOVIMIENTOS!$A:$A,">="&DATE(PORTADA!$B$2,1,1),MOVIMIENTOS!$A:$A,"<="&EOMONTH(DATE(PORTADA!$B$2,1,1),0),MOVIMIENTOS!$D:$D,$B9) | E9: =D9-C9 | F9: =IFERROR(D9/C9,"") | S9: =IF(DAY(DATE(PORTADA!$B$2,1,5))<>5,"",5) | T9: =IF(DAY(DATE(PORTADA!$B$2,1,5))<>5,"",SUMIFS(MOVIMIENTOS!$F:$F,MOVIMIENTOS!$A:$A,DATE(PORTADA!$B$2,1,5),MOVIMIENTOS!$C:$C,T$4)) | U9: =IF(DAY(DATE(PORTADA!$B$2,1,5))<>5,"",SUMIFS(MOVIMIENTOS!$F:$F,MOVIMIENTOS!$A:$A,DATE(PORTADA!$B$2,1,5),MOVIMIENTOS!$C:$C,U$4)) | V9: =IF(DAY(DATE(PORTADA!$B$2,1,5))<>5,"",SUMIFS(MOVIMIENTOS!$F:$F,MOVIMIENTOS!$A:$A,DATE(PORTADA!$B$2,1,5),MOVIMIENTOS!$C:$C,V$4)) | W9: =IF(DAY(DATE(PORTADA!$B$2,1,5))<>5,"",SUMIFS(MOVIMIENTOS!$F:$F,MOVIMIENTOS!$A:$A,DATE(PORTADA!$B$2,1,5),MOVIMIENTOS!$C:$C,W$4)) | X9: =IF(DAY(DATE(PORTADA!$B$2,1,5))<>5,"",SUMIFS(MOVIMIENTOS!$F:$F,MOVIMIENTOS!$A:$A,DATE(PORTADA!$B$2,1,5),MOVIMIENTOS!$C:$C,X$4)) | Y9: =IF(DAY(DATE(PORTADA!$B$2,1,5))<>5,"",SUMIFS(MOVIMIENTOS!$F:$F,MOVIMIENTOS!$A:$A,DATE(PORTADA!$B$2,1,5),MOVIMIENTOS!$C:$C,Y$4)) | Z9: =IF(DAY(DATE(PORTADA!$B$2,1,5))<>5,"",SUMIFS(MOVIMIENTOS!$F:$F,MOVIMIENTOS!$A:$A,DATE(PORTADA!$B$2,1,5),MOVIMIENTOS!$C:$C,Z$4)) | AA9: =IF(DAY(DATE(PORTADA!$B$2,1,5))<>5,"",SUM(T9:Z9))
A10: NEGOCIO | B10: VENTA DE SERVICIO | C10: =CATEGORIAS!$E$8 | D10: =SUMIFS(MOVIMIENTOS!$F:$F,MOVIMIENTOS!$A:$A,">="&DATE(PORTADA!$B$2,1,1),MOVIMIENTOS!$A:$A,"<="&EOMONTH(DATE(PORTADA!$B$2,1,1),0),MOVIMIENTOS!$D:$D,$B10) | E10: =D10-C10 | F10: =IFERROR(D10/C10,"") | S10: =IF(DAY(DATE(PORTADA!$B$2,1,6))<>6,"",6) | T10: =IF(DAY(DATE(PORTADA!$B$2,1,6))<>6,"",SUMIFS(MOVIMIENTOS!$F:$F,MOVIMIENTOS!$A:$A,DATE(PORTADA!$B$2,1,6),MOVIMIENTOS!$C:$C,T$4)) | U10: =IF(DAY(DATE(PORTADA!$B$2,1,6))<>6,"",SUMIFS(MOVIMIENTOS!$F:$F,MOVIMIENTOS!$A:$A,DATE(PORTADA!$B$2,1,6),MOVIMIENTOS!$C:$C,U$4)) | V10: =IF(DAY(DATE(PORTADA!$B$2,1,6))<>6,"",SUMIFS(MOVIMIENTOS!$F:$F,MOVIMIENTOS!$A:$A,DATE(PORTADA!$B$2,1,6),MOVIMIENTOS!$C:$C,V$4)) | W10: =IF(DAY(DATE(PORTADA!$B$2,1,6))<>6,"",SUMIFS(MOVIMIENTOS!$F:$F,MOVIMIENTOS!$A:$A,DATE(PORTADA!$B$2,1,6),MOVIMIENTOS!$C:$C,W$4)) | X10: =IF(DAY(DATE(PORTADA!$B$2,1,6))<>6,"",SUMIFS(MOVIMIENTOS!$F:$F,MOVIMIENTOS!$A:$A,DATE(PORTADA!$B$2,1,6),MOVIMIENTOS!$C:$C,X$4)) | Y10: =IF(DAY(DATE(PORTADA!$B$2,1,6))<>6,"",SUMIFS(MOVIMIENTOS!$F:$F,MOVIMIENTOS!$A:$A,DATE(PORTADA!$B$2,1,6),MOVIMIENTOS!$C:$C,Y$4)) | Z10: =IF(DAY(DATE(PORTADA!$B$2,1,6))<>6,"",SUMIFS(MOVIMIENTOS!$F:$F,MOVIMIENTOS!$A:$A,DATE(PORTADA!$B$2,1,6),MOVIMIENTOS!$C:$C,Z$4)) | AA10: =IF(DAY(DATE(PORTADA!$B$2,1,6))<>6,"",SUM(T10:Z10))
A11: OTROS | B11: COBROS PENDIENTES | C11: =CATEGORIAS!$E$9 | D11: =SUMIFS(MOVIMIENTOS!$F:$F,MOVIMIENTOS!$A:$A,">="&DATE(PORTADA!$B$2,1,1),MOVIMIENTOS!$A:$A,"<="&EOMONTH(DATE(PORTADA!$B$2,1,1),0),MOVIMIENTOS!$D:$D,$B11) | E11: =D11-C11 | F11: =IFERROR(D11/C11,"") | S11: =IF(DAY(DATE(PORTADA!$B$2,1,7))<>7,"",7) | T11: =IF(DAY(DATE(PORTADA!$B$2,1,7))<>7,"",SUMIFS(MOVIMIENTOS!$F:$F,MOVIMIENTOS!$A:$A,DATE(PORTADA!$B$2,1,7),MOVIMIENTOS!$C:$C,T$4)) | U11: =IF(DAY(DATE(PORTADA!$B$2,1,7))<>7,"",SUMIFS(MOVIMIENTOS!$F:$F,MOVIMIENTOS!$A:$A,DATE(PORTADA!$B$2,1,7),MOVIMIENTOS!$C:$C,U$4)) | V11: =IF(DAY(DATE(PORTADA!$B$2,1,7))<>7,"",SUMIFS(MOVIMIENTOS!$F:$F,MOVIMIENTOS!$A:$A,DATE(PORTADA!$B$2,1,7),MOVIMIENTOS!$C:$C,V$4)) | W11: =IF(DAY(DATE(PORTADA!$B$2,1,7))<>7,"",SUMIFS(MOVIMIENTOS!$F:$F,MOVIMIENTOS!$A:$A,DATE(PORTADA!$B$2,1,7),MOVIMIENTOS!$C:$C,W$4)) | X11: =IF(DAY(DATE(PORTADA!$B$2,1,7))<>7,"",SUMIFS(MOVIMIENTOS!$F:$F,MOVIMIENTOS!$A:$A,DATE(PORTADA!$B$2,1,7),MOVIMIENTOS!$C:$C,X$4)) | Y11: =IF(DAY(DATE(PORTADA!$B$2,1,7))<>7,"",SUMIFS(MOVIMIENTOS!$F:$F,MOVIMIENTOS!$A:$A,DATE(PORTADA!$B$2,1,7),MOVIMIENTOS!$C:$C,Y$4)) | Z11: =IF(DAY(DATE(PORTADA!$B$2,1,7))<>7,"",SUMIFS(MOVIMIENTOS!$F:$F,MOVIMIENTOS!$A:$A,DATE(PORTADA!$B$2,1,7),MOVIMIENTOS!$C:$C,Z$4)) | AA11: =IF(DAY(DATE(PORTADA!$B$2,1,7))<>7,"",SUM(T11:Z11))
A12: OTROS | B12: OTROS INGRESOS | C12: =CATEGORIAS!$E$10 | D12: =SUMIFS(MOVIMIENTOS!$F:$F,MOVIMIENTOS!$A:$A,">="&DATE(PORTADA!$B$2,1,1),MOVIMIENTOS!$A:$A,"<="&EOMONTH(DATE(PORTADA!$B$2,1,1),0),MOVIMIENTOS!$D:$D,$B12) | E12: =D12-C12 | F12: =IFERROR(D12/C12,"") | S12: =IF(DAY(DATE(PORTADA!$B$2,1,8))<>8,"",8) | T12: =IF(DAY(DATE(PORTADA!$B$2,1,8))<>8,"",SUMIFS(MOVIMIENTOS!$F:$F,MOVIMIENTOS!$A:$A,DATE(PORTADA!$B$2,1,8),MOVIMIENTOS!$C:$C,T$4)) | U12: =IF(DAY(DATE(PORTADA!$B$2,1,8))<>8,"",SUMIFS(MOVIMIENTOS!$F:$F,MOVIMIENTOS!$A:$A,DATE(PORTADA!$B$2,1,8),MOVIMIENTOS!$C:$C,U$4)) | V12: =IF(DAY(DATE(PORTADA!$B$2,1,8))<>8,"",SUMIFS(MOVIMIENTOS!$F:$F,MOVIMIENTOS!$A:$A,DATE(PORTADA!$B$2,1,8),MOVIMIENTOS!$C:$C,V$4)) | W12: =IF(DAY(DATE(PORTADA!$B$2,1,8))<>8,"",SUMIFS(MOVIMIENTOS!$F:$F,MOVIMIENTOS!$A:$A,DATE(PORTADA!$B$2,1,8),MOVIMIENTOS!$C:$C,W$4)) | X12: =IF(DAY(DATE(PORTADA!$B$2,1,8))<>8,"",SUMIFS(MOVIMIENTOS!$F:$F,MOVIMIENTOS!$A:$A,DATE(PORTADA!$B$2,1,8),MOVIMIENTOS!$C:$C,X$4)) | Y12: =IF(DAY(DATE(PORTADA!$B$2,1,8))<>8,"",SUMIFS(MOVIMIENTOS!$F:$F,MOVIMIENTOS!$A:$A,DATE(PORTADA!$B$2,1,8),MOVIMIENTOS!$C:$C,Y$4)) | Z12: =IF(DAY(DATE(PORTADA!$B$2,1,8))<>8,"",SUMIFS(MOVIMIENTOS!$F:$F,MOVIMIENTOS!$A:$A,DATE(PORTADA!$B$2,1,8),MOVIMIENTOS!$C:$C,Z$4)) | AA12: =IF(DAY(DATE(PORTADA!$B$2,1,8))<>8,"",SUM(T12:Z12))
B13: TOTAL INGRESOS | C13: =SUM(C6:C12) | D13: =SUM(D6:D12) | E13: =SUM(E6:E12) | S13: =IF(DAY(DATE(PORTADA!$B$2,1,9))<>9,"",9) | T13: =IF(DAY(DATE(PORTADA!$B$2,1,9))<>9,"",SUMIFS(MOVIMIENTOS!$F:$F,MOVIMIENTOS!$A:$A,DATE(PORTADA!$B$2,1,9),MOVIMIENTOS!$C:$C,T$4)) | U13: =IF(DAY(DATE(PORTADA!$B$2,1,9))<>9,"",SUMIFS(MOVIMIENTOS!$F:$F,MOVIMIENTOS!$A:$A,DATE(PORTADA!$B$2,1,9),MOVIMIENTOS!$C:$C,U$4)) | V13: =IF(DAY(DATE(PORTADA!$B$2,1,9))<>9,"",SUMIFS(MOVIMIENTOS!$F:$F,MOVIMIENTOS!$A:$A,DATE(PORTADA!$B$2,1,9),MOVIMIENTOS!$C:$C,V$4)) | W13: =IF(DAY(DATE(PORTADA!$B$2,1,9))<>9,"",SUMIFS(MOVIMIENTOS!$F:$F,MOVIMIENTOS!$A:$A,DATE(PORTADA!$B$2,1,9),MOVIMIENTOS!$C:$C,W$4)) | X13: =IF(DAY(DATE(PORTADA!$B$2,1,9))<>9,"",SUMIFS(MOVIMIENTOS!$F:$F,MOVIMIENTOS!$A:$A,DATE(PORTADA!$B$2,1,9),MOVIMIENTOS!$C:$C,X$4)) | Y13: =IF(DAY(DATE(PORTADA!$B$2,1,9))<>9,"",SUMIFS(MOVIMIENTOS!$F:$F,MOVIMIENTOS!$A:$A,DATE(PORTADA!$B$2,1,9),MOVIMIENTOS!$C:$C,Y$4)) | Z13: =IF(DAY(DATE(PORTADA!$B$2,1,9))<>9,"",SUMIFS(MOVIMIENTOS!$F:$F,MOVIMIENTOS!$A:$A,DATE(PORTADA!$B$2,1,9),MOVIMIENTOS!$C:$C,Z$4)) | AA13: =IF(DAY(DATE(PORTADA!$B$2,1,9))<>9,"",SUM(T13:Z13))
S14: =IF(DAY(DATE(PORTADA!$B$2,1,10))<>10,"",10) | T14: =IF(DAY(DATE(PORTADA!$B$2,1,10))<>10,"",SUMIFS(MOVIMIENTOS!$F:$F,MOVIMIENTOS!$A:$A,DATE(PORTADA!$B$2,1,10),MOVIMIENTOS!$C:$C,T$4)) | U14: =IF(DAY(DATE(PORTADA!$B$2,1,10))<>10,"",SUMIFS(MOVIMIENTOS!$F:$F,MOVIMIENTOS!$A:$A,DATE(PORTADA!$B$2,1,10),MOVIMIENTOS!$C:$C,U$4)) | V14: =IF(DAY(DATE(PORTADA!$B$2,1,10))<>10,"",SUMIFS(MOVIMIENTOS!$F:$F,MOVIMIENTOS!$A:$A,DATE(PORTADA!$B$2,1,10),MOVIMIENTOS!$C:$C,V$4)) | W14: =IF(DAY(DATE(PORTADA!$B$2,1,10))<>10,"",SUMIFS(MOVIMIENTOS!$F:$F,MOVIMIENTOS!$A:$A,DATE(PORTADA!$B$2,1,10),MOVIMIENTOS!$C:$C,W$4)) | X14: =IF(DAY(DATE(PORTADA!$B$2,1,10))<>10,"",SUMIFS(MOVIMIENTOS!$F:$F,MOVIMIENTOS!$A:$A,DATE(PORTADA!$B$2,1,10),MOVIMIENTOS!$C:$C,X$4)) | Y14: =IF(DAY(DATE(PORTADA!$B$2,1,10))<>10,"",SUMIFS(MOVIMIENTOS!$F:$F,MOVIMIENTOS!$A:$A,DATE(PORTADA!$B$2,1,10),MOVIMIENTOS!$C:$C,Y$4)) | Z14: =IF(DAY(DATE(PORTADA!$B$2,1,10))<>10,"",SUMIFS(MOVIMIENTOS!$F:$F,MOVIMIENTOS!$A:$A,DATE(PORTADA!$B$2,1,10),MOVIMIENTOS!$C:$C,Z$4)) | AA14: =IF(DAY(DATE(PORTADA!$B$2,1,10))<>10,"",SUM(T14:Z14))
A15: EGRESOS | S15: =IF(DAY(DATE(PORTADA!$B$2,1,11))<>11,"",11) | T15: =IF(DAY(DATE(PORTADA!$B$2,1,11))<>11,"",SUMIFS(MOVIMIENTOS!$F:$F,MOVIMIENTOS!$A:$A,DATE(PORTADA!$B$2,1,11),MOVIMIENTOS!$C:$C,T$4)) | U15: =IF(DAY(DATE(PORTADA!$B$2,1,11))<>11,"",SUMIFS(MOVIMIENTOS!$F:$F,MOVIMIENTOS!$A:$A,DATE(PORTADA!$B$2,1,11),MOVIMIENTOS!$C:$C,U$4)) | V15: =IF(DAY(DATE(PORTADA!$B$2,1,11))<>11,"",SUMIFS(MOVIMIENTOS!$F:$F,MOVIMIENTOS!$A:$A,DATE(PORTADA!$B$2,1,11),MOVIMIENTOS!$C:$C,V$4)) | W15: =IF(DAY(DATE(PORTADA!$B$2,1,11))<>11,"",SUMIFS(MOVIMIENTOS!$F:$F,MOVIMIENTOS!$A:$A,DATE(PORTADA!$B$2,1,11),MOVIMIENTOS!$C:$C,W$4)) | X15: =IF(DAY(DATE(PORTADA!$B$2,1,11))<>11,"",SUMIFS(MOVIMIENTOS!$F:$F,MOVIMIENTOS!$A:$A,DATE(PORTADA!$B$2,1,11),MOVIMIENTOS!$C:$C,X$4)) | Y15: =IF(DAY(DATE(PORTADA!$B$2,1,11))<>11,"",SUMIFS(MOVIMIENTOS!$F:$F,MOVIMIENTOS!$A:$A,DATE(PORTADA!$B$2,1,11),MOVIMIENTOS!$C:$C,Y$4)) | Z15: =IF(DAY(DATE(PORTADA!$B$2,1,11))<>11,"",SUMIFS(MOVIMIENTOS!$F:$F,MOVIMIENTOS!$A:$A,DATE(PORTADA!$B$2,1,11),MOVIMIENTOS!$C:$C,Z$4)) | AA15: =IF(DAY(DATE(PORTADA!$B$2,1,11))<>11,"",SUM(T15:Z15))
A16: GRUPO | B16: CATEGORÍA | C16: PRESUPUESTO | D16: REAL | E16: DIFERENCIA | F16: % USADO | S16: =IF(DAY(DATE(PORTADA!$B$2,1,12))<>12,"",12) | T16: =IF(DAY(DATE(PORTADA!$B$2,1,12))<>12,"",SUMIFS(MOVIMIENTOS!$F:$F,MOVIMIENTOS!$A:$A,DATE(PORTADA!$B$2,1,12),MOVIMIENTOS!$C:$C,T$4)) | U16: =IF(DAY(DATE(PORTADA!$B$2,1,12))<>12,"",SUMIFS(MOVIMIENTOS!$F:$F,MOVIMIENTOS!$A:$A,DATE(PORTADA!$B$2,1,12),MOVIMIENTOS!$C:$C,U$4)) | V16: =IF(DAY(DATE(PORTADA!$B$2,1,12))<>12,"",SUMIFS(MOVIMIENTOS!$F:$F,MOVIMIENTOS!$A:$A,DATE(PORTADA!$B$2,1,12),MOVIMIENTOS!$C:$C,V$4)) | W16: =IF(DAY(DATE(PORTADA!$B$2,1,12))<>12,"",SUMIFS(MOVIMIENTOS!$F:$F,MOVIMIENTOS!$A:$A,DATE(PORTADA!$B$2,1,12),MOVIMIENTOS!$C:$C,W$4)) | X16: =IF(DAY(DATE(PORTADA!$B$2,1,12))<>12,"",SUMIFS(MOVIMIENTOS!$F:$F,MOVIMIENTOS!$A:$A,DATE(PORTADA!$B$2,1,12),MOVIMIENTOS!$C:$C,X$4)) | Y16: =IF(DAY(DATE(PORTADA!$B$2,1,12))<>12,"",SUMIFS(MOVIMIENTOS!$F:$F,MOVIMIENTOS!$A:$A,DATE(PORTADA!$B$2,1,12),MOVIMIENTOS!$C:$C,Y$4)) | Z16: =IF(DAY(DATE(PORTADA!$B$2,1,12))<>12,"",SUMIFS(MOVIMIENTOS!$F:$F,MOVIMIENTOS!$A:$A,DATE(PORTADA!$B$2,1,12),MOVIMIENTOS!$C:$C,Z$4)) | AA16: =IF(DAY(DATE(PORTADA!$B$2,1,12))<>12,"",SUM(T16:Z16))
A17: CUENTAS PERSONALES | B17: PREST. AUTO | C17: =CATEGORIAS!$E$11 | D17: =SUMIFS(MOVIMIENTOS!$F:$F,MOVIMIENTOS!$A:$A,">="&DATE(PORTADA!$B$2,1,1),MOVIMIENTOS!$A:$A,"<="&EOMONTH(DATE(PORTADA!$B$2,1,1),0),MOVIMIENTOS!$D:$D,$B17) | E17: =C17-D17 | F17: =IFERROR(D17/C17,"") | S17: =IF(DAY(DATE(PORTADA!$B$2,1,13))<>13,"",13) | T17: =IF(DAY(DATE(PORTADA!$B$2,1,13))<>13,"",SUMIFS(MOVIMIENTOS!$F:$F,MOVIMIENTOS!$A:$A,DATE(PORTADA!$B$2,1,13),MOVIMIENTOS!$C:$C,T$4)) | U17: =IF(DAY(DATE(PORTADA!$B$2,1,13))<>13,"",SUMIFS(MOVIMIENTOS!$F:$F,MOVIMIENTOS!$A:$A,DATE(PORTADA!$B$2,1,13),MOVIMIENTOS!$C:$C,U$4)) | V17: =IF(DAY(DATE(PORTADA!$B$2,1,13))<>13,"",SUMIFS(MOVIMIENTOS!$F:$F,MOVIMIENTOS!$A:$A,DATE(PORTADA!$B$2,1,13),MOVIMIENTOS!$C:$C,V$4)) | W17: =IF(DAY(DATE(PORTADA!$B$2,1,13))<>13,"",SUMIFS(MOVIMIENTOS!$F:$F,MOVIMIENTOS!$A:$A,DATE(PORTADA!$B$2,1,13),MOVIMIENTOS!$C:$C,W$4)) | X17: =IF(DAY(DATE(PORTADA!$B$2,1,13))<>13,"",SUMIFS(MOVIMIENTOS!$F:$F,MOVIMIENTOS!$A:$A,DATE(PORTADA!$B$2,1,13),MOVIMIENTOS!$C:$C,X$4)) | Y17: =IF(DAY(DATE(PORTADA!$B$2,1,13))<>13,"",SUMIFS(MOVIMIENTOS!$F:$F,MOVIMIENTOS!$A:$A,DATE(PORTADA!$B$2,1,13),MOVIMIENTOS!$C:$C,Y$4)) | Z17: =IF(DAY(DATE(PORTADA!$B$2,1,13))<>13,"",SUMIFS(MOVIMIENTOS!$F:$F,MOVIMIENTOS!$A:$A,DATE(PORTADA!$B$2,1,13),MOVIMIENTOS!$C:$C,Z$4)) | AA17: =IF(DAY(DATE(PORTADA!$B$2,1,13))<>13,"",SUM(T17:Z17))
A18: CUENTAS PERSONALES | B18: AHORRO CASA | C18: =CATEGORIAS!$E$12 | D18: =SUMIFS(MOVIMIENTOS!$F:$F,MOVIMIENTOS!$A:$A,">="&DATE(PORTADA!$B$2,1,1),MOVIMIENTOS!$A:$A,"<="&EOMONTH(DATE(PORTADA!$B$2,1,1),0),MOVIMIENTOS!$D:$D,$B18) | E18: =C18-D18 | F18: =IFERROR(D18/C18,"") | S18: =IF(DAY(DATE(PORTADA!$B$2,1,14))<>14,"",14) | T18: =IF(DAY(DATE(PORTADA!$B$2,1,14))<>14,"",SUMIFS(MOVIMIENTOS!$F:$F,MOVIMIENTOS!$A:$A,DATE(PORTADA!$B$2,1,14),MOVIMIENTOS!$C:$C,T$4)) | U18: =IF(DAY(DATE(PORTADA!$B$2,1,14))<>14,"",SUMIFS(MOVIMIENTOS!$F:$F,MOVIMIENTOS!$A:$A,DATE(PORTADA!$B$2,1,14),MOVIMIENTOS!$C:$C,U$4)) | V18: =IF(DAY(DATE(PORTADA!$B$2,1,14))<>14,"",SUMIFS(MOVIMIENTOS!$F:$F,MOVIMIENTOS!$A:$A,DATE(PORTADA!$B$2,1,14),MOVIMIENTOS!$C:$C,V$4)) | W18: =IF(DAY(DATE(PORTADA!$B$2,1,14))<>14,"",SUMIFS(MOVIMIENTOS!$F:$F,MOVIMIENTOS!$A:$A,DATE(PORTADA!$B$2,1,14),MOVIMIENTOS!$C:$C,W$4)) | X18: =IF(DAY(DATE(PORTADA!$B$2,1,14))<>14,"",SUMIFS(MOVIMIENTOS!$F:$F,MOVIMIENTOS!$A:$A,DATE(PORTADA!$B$2,1,14),MOVIMIENTOS!$C:$C,X$4)) | Y18: =IF(DAY(DATE(PORTADA!$B$2,1,14))<>14,"",SUMIFS(MOVIMIENTOS!$F:$F,MOVIMIENTOS!$A:$A,DATE(PORTADA!$B$2,1,14),MOVIMIENTOS!$C:$C,Y$4)) | Z18: =IF(DAY(DATE(PORTADA!$B$2,1,14))<>14,"",SUMIFS(MOVIMIENTOS!$F:$F,MOVIMIENTOS!$A:$A,DATE(PORTADA!$B$2,1,14),MOVIMIENTOS!$C:$C,Z$4)) | AA18: =IF(DAY(DATE(PORTADA!$B$2,1,14))<>14,"",SUM(T18:Z18))
A19: HIJOS | B19: PENSIONES | C19: =CATEGORIAS!$E$13 | D19: =SUMIFS(MOVIMIENTOS!$F:$F,MOVIMIENTOS!$A:$A,">="&DATE(PORTADA!$B$2,1,1),MOVIMIENTOS!$A:$A,"<="&EOMONTH(DATE(PORTADA!$B$2,1,1),0),MOVIMIENTOS!$D:$D,$B19) | E19: =C19-D19 | F19: =IFERROR(D19/C19,"") | S19: =IF(DAY(DATE(PORTADA!$B$2,1,15))<>15,"",15) | T19: =IF(DAY(DATE(PORTADA!$B$2,1,15))<>15,"",SUMIFS(MOVIMIENTOS!$F:$F,MOVIMIENTOS!$A:$A,DATE(PORTADA!$B$2,1,15),MOVIMIENTOS!$C:$C,T$4)) | U19: =IF(DAY(DATE(PORTADA!$B$2,1,15))<>15,"",SUMIFS(MOVIMIENTOS!$F:$F,MOVIMIENTOS!$A:$A,DATE(PORTADA!$B$2,1,15),MOVIMIENTOS!$C:$C,U$4)) | V19: =IF(DAY(DATE(PORTADA!$B$2,1,15))<>15,"",SUMIFS(MOVIMIENTOS!$F:$F,MOVIMIENTOS!$A:$A,DATE(PORTADA!$B$2,1,15),MOVIMIENTOS!$C:$C,V$4)) | W19: =IF(DAY(DATE(PORTADA!$B$2,1,15))<>15,"",SUMIFS(MOVIMIENTOS!$F:$F,MOVIMIENTOS!$A:$A,DATE(PORTADA!$B$2,1,15),MOVIMIENTOS!$C:$C,W$4)) | X19: =IF(DAY(DATE(PORTADA!$B$2,1,15))<>15,"",SUMIFS(MOVIMIENTOS!$F:$F,MOVIMIENTOS!$A:$A,DATE(PORTADA!$B$2,1,15),MOVIMIENTOS!$C:$C,X$4)) | Y19: =IF(DAY(DATE(PORTADA!$B$2,1,15))<>15,"",SUMIFS(MOVIMIENTOS!$F:$F,MOVIMIENTOS!$A:$A,DATE(PORTADA!$B$2,1,15),MOVIMIENTOS!$C:$C,Y$4)) | Z19: =IF(DAY(DATE(PORTADA!$B$2,1,15))<>15,"",SUMIFS(MOVIMIENTOS!$F:$F,MOVIMIENTOS!$A:$A,DATE(PORTADA!$B$2,1,15),MOVIMIENTOS!$C:$C,Z$4)) | AA19: =IF(DAY(DATE(PORTADA!$B$2,1,15))<>15,"",SUM(T19:Z19))
A20: HIJOS | B20: ROPA Y REGALOS | C20: =CATEGORIAS!$E$14 | D20: =SUMIFS(MOVIMIENTOS!$F:$F,MOVIMIENTOS!$A:$A,">="&DATE(PORTADA!$B$2,1,1),MOVIMIENTOS!$A:$A,"<="&EOMONTH(DATE(PORTADA!$B$2,1,1),0),MOVIMIENTOS!$D:$D,$B20) | E20: =C20-D20 | F20: =IFERROR(D20/C20,"") | S20: =IF(DAY(DATE(PORTADA!$B$2,1,16))<>16,"",16) | T20: =IF(DAY(DATE(PORTADA!$B$2,1,16))<>16,"",SUMIFS(MOVIMIENTOS!$F:$F,MOVIMIENTOS!$A:$A,DATE(PORTADA!$B$2,1,16),MOVIMIENTOS!$C:$C,T$4)) | U20: =IF(DAY(DATE(PORTADA!$B$2,1,16))<>16,"",SUMIFS(MOVIMIENTOS!$F:$F,MOVIMIENTOS!$A:$A,DATE(PORTADA!$B$2,1,16),MOVIMIENTOS!$C:$C,U$4)) | V20: =IF(DAY(DATE(PORTADA!$B$2,1,16))<>16,"",SUMIFS(MOVIMIENTOS!$F:$F,MOVIMIENTOS!$A:$A,DATE(PORTADA!$B$2,1,16),MOVIMIENTOS!$C:$C,V$4)) | W20: =IF(DAY(DATE(PORTADA!$B$2,1,16))<>16,"",SUMIFS(MOVIMIENTOS!$F:$F,MOVIMIENTOS!$A:$A,DATE(PORTADA!$B$2,1,16),MOVIMIENTOS!$C:$C,W$4)) | X20: =IF(DAY(DATE(PORTADA!$B$2,1,16))<>16,"",SUMIFS(MOVIMIENTOS!$F:$F,MOVIMIENTOS!$A:$A,DATE(PORTADA!$B$2,1,16),MOVIMIENTOS!$C:$C,X$4)) | Y20: =IF(DAY(DATE(PORTADA!$B$2,1,16))<>16,"",SUMIFS(MOVIMIENTOS!$F:$F,MOVIMIENTOS!$A:$A,DATE(PORTADA!$B$2,1,16),MOVIMIENTOS!$C:$C,Y$4)) | Z20: =IF(DAY(DATE(PORTADA!$B$2,1,16))<>16,"",SUMIFS(MOVIMIENTOS!$F:$F,MOVIMIENTOS!$A:$A,DATE(PORTADA!$B$2,1,16),MOVIMIENTOS!$C:$C,Z$4)) | AA20: =IF(DAY(DATE(PORTADA!$B$2,1,16))<>16,"",SUM(T20:Z20))
A21: HIJOS | B21: AHORRO EMERGENCIAS | C21: =CATEGORIAS!$E$15 | D21: =SUMIFS(MOVIMIENTOS!$F:$F,MOVIMIENTOS!$A:$A,">="&DATE(PORTADA!$B$2,1,1),MOVIMIENTOS!$A:$A,"<="&EOMONTH(DATE(PORTADA!$B$2,1,1),0),MOVIMIENTOS!$D:$D,$B21) | E21: =C21-D21 | F21: =IFERROR(D21/C21,"") | S21: =IF(DAY(DATE(PORTADA!$B$2,1,17))<>17,"",17) | T21: =IF(DAY(DATE(PORTADA!$B$2,1,17))<>17,"",SUMIFS(MOVIMIENTOS!$F:$F,MOVIMIENTOS!$A:$A,DATE(PORTADA!$B$2,1,17),MOVIMIENTOS!$C:$C,T$4)) | U21: =IF(DAY(DATE(PORTADA!$B$2,1,17))<>17,"",SUMIFS(MOVIMIENTOS!$F:$F,MOVIMIENTOS!$A:$A,DATE(PORTADA!$B$2,1,17),MOVIMIENTOS!$C:$C,U$4)) | V21: =IF(DAY(DATE(PORTADA!$B$2,1,17))<>17,"",SUMIFS(MOVIMIENTOS!$F:$F,MOVIMIENTOS!$A:$A,DATE(PORTADA!$B$2,1,17),MOVIMIENTOS!$C:$C,V$4)) | W21: =IF(DAY(DATE(PORTADA!$B$2,1,17))<>17,"",SUMIFS(MOVIMIENTOS!$F:$F,MOVIMIENTOS!$A:$A,DATE(PORTADA!$B$2,1,17),MOVIMIENTOS!$C:$C,W$4)) | X21: =IF(DAY(DATE(PORTADA!$B$2,1,17))<>17,"",SUMIFS(MOVIMIENTOS!$F:$F,MOVIMIENTOS!$A:$A,DATE(PORTADA!$B$2,1,17),MOVIMIENTOS!$C:$C,X$4)) | Y21: =IF(DAY(DATE(PORTADA!$B$2,1,17))<>17,"",SUMIFS(MOVIMIENTOS!$F:$F,MOVIMIENTOS!$A:$A,DATE(PORTADA!$B$2,1,17),MOVIMIENTOS!$C:$C,Y$4)) | Z21: =IF(DAY(DATE(PORTADA!$B$2,1,17))<>17,"",SUMIFS(MOVIMIENTOS!$F:$F,MOVIMIENTOS!$A:$A,DATE(PORTADA!$B$2,1,17),MOVIMIENTOS!$C:$C,Z$4)) | AA21: =IF(DAY(DATE(PORTADA!$B$2,1,17))<>17,"",SUM(T21:Z21))
A22: HIJOS | B22: SALIDAS CON FAMILIA | C22: =CATEGORIAS!$E$16 | D22: =SUMIFS(MOVIMIENTOS!$F:$F,MOVIMIENTOS!$A:$A,">="&DATE(PORTADA!$B$2,1,1),MOVIMIENTOS!$A:$A,"<="&EOMONTH(DATE(PORTADA!$B$2,1,1),0),MOVIMIENTOS!$D:$D,$B22) | E22: =C22-D22 | F22: =IFERROR(D22/C22,"") | S22: =IF(DAY(DATE(PORTADA!$B$2,1,18))<>18,"",18) | T22: =IF(DAY(DATE(PORTADA!$B$2,1,18))<>18,"",SUMIFS(MOVIMIENTOS!$F:$F,MOVIMIENTOS!$A:$A,DATE(PORTADA!$B$2,1,18),MOVIMIENTOS!$C:$C,T$4)) | U22: =IF(DAY(DATE(PORTADA!$B$2,1,18))<>18,"",SUMIFS(MOVIMIENTOS!$F:$F,MOVIMIENTOS!$A:$A,DATE(PORTADA!$B$2,1,18),MOVIMIENTOS!$C:$C,U$4)) | V22: =IF(DAY(DATE(PORTADA!$B$2,1,18))<>18,"",SUMIFS(MOVIMIENTOS!$F:$F,MOVIMIENTOS!$A:$A,DATE(PORTADA!$B$2,1,18),MOVIMIENTOS!$C:$C,V$4)) | W22: =IF(DAY(DATE(PORTADA!$B$2,1,18))<>18,"",SUMIFS(MOVIMIENTOS!$F:$F,MOVIMIENTOS!$A:$A,DATE(PORTADA!$B$2,1,18),MOVIMIENTOS!$C:$C,W$4)) | X22: =IF(DAY(DATE(PORTADA!$B$2,1,18))<>18,"",SUMIFS(MOVIMIENTOS!$F:$F,MOVIMIENTOS!$A:$A,DATE(PORTADA!$B$2,1,18),MOVIMIENTOS!$C:$C,X$4)) | Y22: =IF(DAY(DATE(PORTADA!$B$2,1,18))<>18,"",SUMIFS(MOVIMIENTOS!$F:$F,MOVIMIENTOS!$A:$A,DATE(PORTADA!$B$2,1,18),MOVIMIENTOS!$C:$C,Y$4)) | Z22: =IF(DAY(DATE(PORTADA!$B$2,1,18))<>18,"",SUMIFS(MOVIMIENTOS!$F:$F,MOVIMIENTOS!$A:$A,DATE(PORTADA!$B$2,1,18),MOVIMIENTOS!$C:$C,Z$4)) | AA22: =IF(DAY(DATE(PORTADA!$B$2,1,18))<>18,"",SUM(T22:Z22))
A23: CASA | B23: COMIDA CASA | C23: =CATEGORIAS!$E$17 | D23: =SUMIFS(MOVIMIENTOS!$F:$F,MOVIMIENTOS!$A:$A,">="&DATE(PORTADA!$B$2,1,1),MOVIMIENTOS!$A:$A,"<="&EOMONTH(DATE(PORTADA!$B$2,1,1),0),MOVIMIENTOS!$D:$D,$B23) | E23: =C23-D23 | F23: =IFERROR(D23/C23,"") | S23: =IF(DAY(DATE(PORTADA!$B$2,1,19))<>19,"",19) | T23: =IF(DAY(DATE(PORTADA!$B$2,1,19))<>19,"",SUMIFS(MOVIMIENTOS!$F:$F,MOVIMIENTOS!$A:$A,DATE(PORTADA!$B$2,1,19),MOVIMIENTOS!$C:$C,T$4)) | U23: =IF(DAY(DATE(PORTADA!$B$2,1,19))<>19,"",SUMIFS(MOVIMIENTOS!$F:$F,MOVIMIENTOS!$A:$A,DATE(PORTADA!$B$2,1,19),MOVIMIENTOS!$C:$C,U$4)) | V23: =IF(DAY(DATE(PORTADA!$B$2,1,19))<>19,"",SUMIFS(MOVIMIENTOS!$F:$F,MOVIMIENTOS!$A:$A,DATE(PORTADA!$B$2,1,19),MOVIMIENTOS!$C:$C,V$4)) | W23: =IF(DAY(DATE(PORTADA!$B$2,1,19))<>19,"",SUMIFS(MOVIMIENTOS!$F:$F,MOVIMIENTOS!$A:$A,DATE(PORTADA!$B$2,1,19),MOVIMIENTOS!$C:$C,W$4)) | X23: =IF(DAY(DATE(PORTADA!$B$2,1,19))<>19,"",SUMIFS(MOVIMIENTOS!$F:$F,MOVIMIENTOS!$A:$A,DATE(PORTADA!$B$2,1,19),MOVIMIENTOS!$C:$C,X$4)) | Y23: =IF(DAY(DATE(PORTADA!$B$2,1,19))<>19,"",SUMIFS(MOVIMIENTOS!$F:$F,MOVIMIENTOS!$A:$A,DATE(PORTADA!$B$2,1,19),MOVIMIENTOS!$C:$C,Y$4)) | Z23: =IF(DAY(DATE(PORTADA!$B$2,1,19))<>19,"",SUMIFS(MOVIMIENTOS!$F:$F,MOVIMIENTOS!$A:$A,DATE(PORTADA!$B$2,1,19),MOVIMIENTOS!$C:$C,Z$4)) | AA23: =IF(DAY(DATE(PORTADA!$B$2,1,19))<>19,"",SUM(T23:Z23))
A24: CASA | B24: COMIDA PERSONAL | C24: =CATEGORIAS!$E$18 | D24: =SUMIFS(MOVIMIENTOS!$F:$F,MOVIMIENTOS!$A:$A,">="&DATE(PORTADA!$B$2,1,1),MOVIMIENTOS!$A:$A,"<="&EOMONTH(DATE(PORTADA!$B$2,1,1),0),MOVIMIENTOS!$D:$D,$B24) | E24: =C24-D24 | F24: =IFERROR(D24/C24,"") | S24: =IF(DAY(DATE(PORTADA!$B$2,1,20))<>20,"",20) | T24: =IF(DAY(DATE(PORTADA!$B$2,1,20))<>20,"",SUMIFS(MOVIMIENTOS!$F:$F,MOVIMIENTOS!$A:$A,DATE(PORTADA!$B$2,1,20),MOVIMIENTOS!$C:$C,T$4)) | U24: =IF(DAY(DATE(PORTADA!$B$2,1,20))<>20,"",SUMIFS(MOVIMIENTOS!$F:$F,MOVIMIENTOS!$A:$A,DATE(PORTADA!$B$2,1,20),MOVIMIENTOS!$C:$C,U$4)) | V24: =IF(DAY(DATE(PORTADA!$B$2,1,20))<>20,"",SUMIFS(MOVIMIENTOS!$F:$F,MOVIMIENTOS!$A:$A,DATE(PORTADA!$B$2,1,20),MOVIMIENTOS!$C:$C,V$4)) | W24: =IF(DAY(DATE(PORTADA!$B$2,1,20))<>20,"",SUMIFS(MOVIMIENTOS!$F:$F,MOVIMIENTOS!$A:$A,DATE(PORTADA!$B$2,1,20),MOVIMIENTOS!$C:$C,W$4)) | X24: =IF(DAY(DATE(PORTADA!$B$2,1,20))<>20,"",SUMIFS(MOVIMIENTOS!$F:$F,MOVIMIENTOS!$A:$A,DATE(PORTADA!$B$2,1,20),MOVIMIENTOS!$C:$C,X$4)) | Y24: =IF(DAY(DATE(PORTADA!$B$2,1,20))<>20,"",SUMIFS(MOVIMIENTOS!$F:$F,MOVIMIENTOS!$A:$A,DATE(PORTADA!$B$2,1,20),MOVIMIENTOS!$C:$C,Y$4)) | Z24: =IF(DAY(DATE(PORTADA!$B$2,1,20))<>20,"",SUMIFS(MOVIMIENTOS!$F:$F,MOVIMIENTOS!$A:$A,DATE(PORTADA!$B$2,1,20),MOVIMIENTOS!$C:$C,Z$4)) | AA24: =IF(DAY(DATE(PORTADA!$B$2,1,20))<>20,"",SUM(T24:Z24))
A25: CASA | B25: CUENTAS | C25: =CATEGORIAS!$E$19 | D25: =SUMIFS(MOVIMIENTOS!$F:$F,MOVIMIENTOS!$A:$A,">="&DATE(PORTADA!$B$2,1,1),MOVIMIENTOS!$A:$A,"<="&EOMONTH(DATE(PORTADA!$B$2,1,1),0),MOVIMIENTOS!$D:$D,$B25) | E25: =C25-D25 | F25: =IFERROR(D25/C25,"") | S25: =IF(DAY(DATE(PORTADA!$B$2,1,21))<>21,"",21) | T25: =IF(DAY(DATE(PORTADA!$B$2,1,21))<>21,"",SUMIFS(MOVIMIENTOS!$F:$F,MOVIMIENTOS!$A:$A,DATE(PORTADA!$B$2,1,21),MOVIMIENTOS!$C:$C,T$4)) | U25: =IF(DAY(DATE(PORTADA!$B$2,1,21))<>21,"",SUMIFS(MOVIMIENTOS!$F:$F,MOVIMIENTOS!$A:$A,DATE(PORTADA!$B$2,1,21),MOVIMIENTOS!$C:$C,U$4)) | V25: =IF(DAY(DATE(PORTADA!$B$2,1,21))<>21,"",SUMIFS(MOVIMIENTOS!$F:$F,MOVIMIENTOS!$A:$A,DATE(PORTADA!$B$2,1,21),MOVIMIENTOS!$C:$C,V$4)) | W25: =IF(DAY(DATE(PORTADA!$B$2,1,21))<>21,"",SUMIFS(MOVIMIENTOS!$F:$F,MOVIMIENTOS!$A:$A,DATE(PORTADA!$B$2,1,21),MOVIMIENTOS!$C:$C,W$4)) | X25: =IF(DAY(DATE(PORTADA!$B$2,1,21))<>21,"",SUMIFS(MOVIMIENTOS!$F:$F,MOVIMIENTOS!$A:$A,DATE(PORTADA!$B$2,1,21),MOVIMIENTOS!$C:$C,X$4)) | Y25: =IF(DAY(DATE(PORTADA!$B$2,1,21))<>21,"",SUMIFS(MOVIMIENTOS!$F:$F,MOVIMIENTOS!$A:$A,DATE(PORTADA!$B$2,1,21),MOVIMIENTOS!$C:$C,Y$4)) | Z25: =IF(DAY(DATE(PORTADA!$B$2,1,21))<>21,"",SUMIFS(MOVIMIENTOS!$F:$F,MOVIMIENTOS!$A:$A,DATE(PORTADA!$B$2,1,21),MOVIMIENTOS!$C:$C,Z$4)) | AA25: =IF(DAY(DATE(PORTADA!$B$2,1,21))<>21,"",SUM(T25:Z25))
A26: SALUD | B26: MEDICAMENTOS | C26: =CATEGORIAS!$E$20 | D26: =SUMIFS(MOVIMIENTOS!$F:$F,MOVIMIENTOS!$A:$A,">="&DATE(PORTADA!$B$2,1,1),MOVIMIENTOS!$A:$A,"<="&EOMONTH(DATE(PORTADA!$B$2,1,1),0),MOVIMIENTOS!$D:$D,$B26) | E26: =C26-D26 | F26: =IFERROR(D26/C26,"") | S26: =IF(DAY(DATE(PORTADA!$B$2,1,22))<>22,"",22) | T26: =IF(DAY(DATE(PORTADA!$B$2,1,22))<>22,"",SUMIFS(MOVIMIENTOS!$F:$F,MOVIMIENTOS!$A:$A,DATE(PORTADA!$B$2,1,22),MOVIMIENTOS!$C:$C,T$4)) | U26: =IF(DAY(DATE(PORTADA!$B$2,1,22))<>22,"",SUMIFS(MOVIMIENTOS!$F:$F,MOVIMIENTOS!$A:$A,DATE(PORTADA!$B$2,1,22),MOVIMIENTOS!$C:$C,U$4)) | V26: =IF(DAY(DATE(PORTADA!$B$2,1,22))<>22,"",SUMIFS(MOVIMIENTOS!$F:$F,MOVIMIENTOS!$A:$A,DATE(PORTADA!$B$2,1,22),MOVIMIENTOS!$C:$C,V$4)) | W26: =IF(DAY(DATE(PORTADA!$B$2,1,22))<>22,"",SUMIFS(MOVIMIENTOS!$F:$F,MOVIMIENTOS!$A:$A,DATE(PORTADA!$B$2,1,22),MOVIMIENTOS!$C:$C,W$4)) | X26: =IF(DAY(DATE(PORTADA!$B$2,1,22))<>22,"",SUMIFS(MOVIMIENTOS!$F:$F,MOVIMIENTOS!$A:$A,DATE(PORTADA!$B$2,1,22),MOVIMIENTOS!$C:$C,X$4)) | Y26: =IF(DAY(DATE(PORTADA!$B$2,1,22))<>22,"",SUMIFS(MOVIMIENTOS!$F:$F,MOVIMIENTOS!$A:$A,DATE(PORTADA!$B$2,1,22),MOVIMIENTOS!$C:$C,Y$4)) | Z26: =IF(DAY(DATE(PORTADA!$B$2,1,22))<>22,"",SUMIFS(MOVIMIENTOS!$F:$F,MOVIMIENTOS!$A:$A,DATE(PORTADA!$B$2,1,22),MOVIMIENTOS!$C:$C,Z$4)) | AA26: =IF(DAY(DATE(PORTADA!$B$2,1,22))<>22,"",SUM(T26:Z26))
A27: SALUD | B27: ROPA | C27: =CATEGORIAS!$E$21 | D27: =SUMIFS(MOVIMIENTOS!$F:$F,MOVIMIENTOS!$A:$A,">="&DATE(PORTADA!$B$2,1,1),MOVIMIENTOS!$A:$A,"<="&EOMONTH(DATE(PORTADA!$B$2,1,1),0),MOVIMIENTOS!$D:$D,$B27) | E27: =C27-D27 | F27: =IFERROR(D27/C27,"") | S27: =IF(DAY(DATE(PORTADA!$B$2,1,23))<>23,"",23) | T27: =IF(DAY(DATE(PORTADA!$B$2,1,23))<>23,"",SUMIFS(MOVIMIENTOS!$F:$F,MOVIMIENTOS!$A:$A,DATE(PORTADA!$B$2,1,23),MOVIMIENTOS!$C:$C,T$4)) | U27: =IF(DAY(DATE(PORTADA!$B$2,1,23))<>23,"",SUMIFS(MOVIMIENTOS!$F:$F,MOVIMIENTOS!$A:$A,DATE(PORTADA!$B$2,1,23),MOVIMIENTOS!$C:$C,U$4)) | V27: =IF(DAY(DATE(PORTADA!$B$2,1,23))<>23,"",SUMIFS(MOVIMIENTOS!$F:$F,MOVIMIENTOS!$A:$A,DATE(PORTADA!$B$2,1,23),MOVIMIENTOS!$C:$C,V$4)) | W27: =IF(DAY(DATE(PORTADA!$B$2,1,23))<>23,"",SUMIFS(MOVIMIENTOS!$F:$F,MOVIMIENTOS!$A:$A,DATE(PORTADA!$B$2,1,23),MOVIMIENTOS!$C:$C,W$4)) | X27: =IF(DAY(DATE(PORTADA!$B$2,1,23))<>23,"",SUMIFS(MOVIMIENTOS!$F:$F,MOVIMIENTOS!$A:$A,DATE(PORTADA!$B$2,1,23),MOVIMIENTOS!$C:$C,X$4)) | Y27: =IF(DAY(DATE(PORTADA!$B$2,1,23))<>23,"",SUMIFS(MOVIMIENTOS!$F:$F,MOVIMIENTOS!$A:$A,DATE(PORTADA!$B$2,1,23),MOVIMIENTOS!$C:$C,Y$4)) | Z27: =IF(DAY(DATE(PORTADA!$B$2,1,23))<>23,"",SUMIFS(MOVIMIENTOS!$F:$F,MOVIMIENTOS!$A:$A,DATE(PORTADA!$B$2,1,23),MOVIMIENTOS!$C:$C,Z$4)) | AA27: =IF(DAY(DATE(PORTADA!$B$2,1,23))<>23,"",SUM(T27:Z27))
A28: SALUD | B28: DEPORTE | C28: =CATEGORIAS!$E$22 | D28: =SUMIFS(MOVIMIENTOS!$F:$F,MOVIMIENTOS!$A:$A,">="&DATE(PORTADA!$B$2,1,1),MOVIMIENTOS!$A:$A,"<="&EOMONTH(DATE(PORTADA!$B$2,1,1),0),MOVIMIENTOS!$D:$D,$B28) | E28: =C28-D28 | F28: =IFERROR(D28/C28,"") | S28: =IF(DAY(DATE(PORTADA!$B$2,1,24))<>24,"",24) | T28: =IF(DAY(DATE(PORTADA!$B$2,1,24))<>24,"",SUMIFS(MOVIMIENTOS!$F:$F,MOVIMIENTOS!$A:$A,DATE(PORTADA!$B$2,1,24),MOVIMIENTOS!$C:$C,T$4)) | U28: =IF(DAY(DATE(PORTADA!$B$2,1,24))<>24,"",SUMIFS(MOVIMIENTOS!$F:$F,MOVIMIENTOS!$A:$A,DATE(PORTADA!$B$2,1,24),MOVIMIENTOS!$C:$C,U$4)) | V28: =IF(DAY(DATE(PORTADA!$B$2,1,24))<>24,"",SUMIFS(MOVIMIENTOS!$F:$F,MOVIMIENTOS!$A:$A,DATE(PORTADA!$B$2,1,24),MOVIMIENTOS!$C:$C,V$4)) | W28: =IF(DAY(DATE(PORTADA!$B$2,1,24))<>24,"",SUMIFS(MOVIMIENTOS!$F:$F,MOVIMIENTOS!$A:$A,DATE(PORTADA!$B$2,1,24),MOVIMIENTOS!$C:$C,W$4)) | X28: =IF(DAY(DATE(PORTADA!$B$2,1,24))<>24,"",SUMIFS(MOVIMIENTOS!$F:$F,MOVIMIENTOS!$A:$A,DATE(PORTADA!$B$2,1,24),MOVIMIENTOS!$C:$C,X$4)) | Y28: =IF(DAY(DATE(PORTADA!$B$2,1,24))<>24,"",SUMIFS(MOVIMIENTOS!$F:$F,MOVIMIENTOS!$A:$A,DATE(PORTADA!$B$2,1,24),MOVIMIENTOS!$C:$C,Y$4)) | Z28: =IF(DAY(DATE(PORTADA!$B$2,1,24))<>24,"",SUMIFS(MOVIMIENTOS!$F:$F,MOVIMIENTOS!$A:$A,DATE(PORTADA!$B$2,1,24),MOVIMIENTOS!$C:$C,Z$4)) | AA28: =IF(DAY(DATE(PORTADA!$B$2,1,24))<>24,"",SUM(T28:Z28))
A29: AUTO | B29: BENCINA | C29: =CATEGORIAS!$E$23 | D29: =SUMIFS(MOVIMIENTOS!$F:$F,MOVIMIENTOS!$A:$A,">="&DATE(PORTADA!$B$2,1,1),MOVIMIENTOS!$A:$A,"<="&EOMONTH(DATE(PORTADA!$B$2,1,1),0),MOVIMIENTOS!$D:$D,$B29) | E29: =C29-D29 | F29: =IFERROR(D29/C29,"") | S29: =IF(DAY(DATE(PORTADA!$B$2,1,25))<>25,"",25) | T29: =IF(DAY(DATE(PORTADA!$B$2,1,25))<>25,"",SUMIFS(MOVIMIENTOS!$F:$F,MOVIMIENTOS!$A:$A,DATE(PORTADA!$B$2,1,25),MOVIMIENTOS!$C:$C,T$4)) | U29: =IF(DAY(DATE(PORTADA!$B$2,1,25))<>25,"",SUMIFS(MOVIMIENTOS!$F:$F,MOVIMIENTOS!$A:$A,DATE(PORTADA!$B$2,1,25),MOVIMIENTOS!$C:$C,U$4)) | V29: =IF(DAY(DATE(PORTADA!$B$2,1,25))<>25,"",SUMIFS(MOVIMIENTOS!$F:$F,MOVIMIENTOS!$A:$A,DATE(PORTADA!$B$2,1,25),MOVIMIENTOS!$C:$C,V$4)) | W29: =IF(DAY(DATE(PORTADA!$B$2,1,25))<>25,"",SUMIFS(MOVIMIENTOS!$F:$F,MOVIMIENTOS!$A:$A,DATE(PORTADA!$B$2,1,25),MOVIMIENTOS!$C:$C,W$4)) | X29: =IF(DAY(DATE(PORTADA!$B$2,1,25))<>25,"",SUMIFS(MOVIMIENTOS!$F:$F,MOVIMIENTOS!$A:$A,DATE(PORTADA!$B$2,1,25),MOVIMIENTOS!$C:$C,X$4)) | Y29: =IF(DAY(DATE(PORTADA!$B$2,1,25))<>25,"",SUMIFS(MOVIMIENTOS!$F:$F,MOVIMIENTOS!$A:$A,DATE(PORTADA!$B$2,1,25),MOVIMIENTOS!$C:$C,Y$4)) | Z29: =IF(DAY(DATE(PORTADA!$B$2,1,25))<>25,"",SUMIFS(MOVIMIENTOS!$F:$F,MOVIMIENTOS!$A:$A,DATE(PORTADA!$B$2,1,25),MOVIMIENTOS!$C:$C,Z$4)) | AA29: =IF(DAY(DATE(PORTADA!$B$2,1,25))<>25,"",SUM(T29:Z29))
A30: AUTO | B30: OTROS | C30: =CATEGORIAS!$E$24 | D30: =SUMIFS(MOVIMIENTOS!$F:$F,MOVIMIENTOS!$A:$A,">="&DATE(PORTADA!$B$2,1,1),MOVIMIENTOS!$A:$A,"<="&EOMONTH(DATE(PORTADA!$B$2,1,1),0),MOVIMIENTOS!$D:$D,$B30) | E30: =C30-D30 | F30: =IFERROR(D30/C30,"") | S30: =IF(DAY(DATE(PORTADA!$B$2,1,26))<>26,"",26) | T30: =IF(DAY(DATE(PORTADA!$B$2,1,26))<>26,"",SUMIFS(MOVIMIENTOS!$F:$F,MOVIMIENTOS!$A:$A,DATE(PORTADA!$B$2,1,26),MOVIMIENTOS!$C:$C,T$4)) | U30: =IF(DAY(DATE(PORTADA!$B$2,1,26))<>26,"",SUMIFS(MOVIMIENTOS!$F:$F,MOVIMIENTOS!$A:$A,DATE(PORTADA!$B$2,1,26),MOVIMIENTOS!$C:$C,U$4)) | V30: =IF(DAY(DATE(PORTADA!$B$2,1,26))<>26,"",SUMIFS(MOVIMIENTOS!$F:$F,MOVIMIENTOS!$A:$A,DATE(PORTADA!$B$2,1,26),MOVIMIENTOS!$C:$C,V$4)) | W30: =IF(DAY(DATE(PORTADA!$B$2,1,26))<>26,"",SUMIFS(MOVIMIENTOS!$F:$F,MOVIMIENTOS!$A:$A,DATE(PORTADA!$B$2,1,26),MOVIMIENTOS!$C:$C,W$4)) | X30: =IF(DAY(DATE(PORTADA!$B$2,1,26))<>26,"",SUMIFS(MOVIMIENTOS!$F:$F,MOVIMIENTOS!$A:$A,DATE(PORTADA!$B$2,1,26),MOVIMIENTOS!$C:$C,X$4)) | Y30: =IF(DAY(DATE(PORTADA!$B$2,1,26))<>26,"",SUMIFS(MOVIMIENTOS!$F:$F,MOVIMIENTOS!$A:$A,DATE(PORTADA!$B$2,1,26),MOVIMIENTOS!$C:$C,Y$4)) | Z30: =IF(DAY(DATE(PORTADA!$B$2,1,26))<>26,"",SUMIFS(MOVIMIENTOS!$F:$F,MOVIMIENTOS!$A:$A,DATE(PORTADA!$B$2,1,26),MOVIMIENTOS!$C:$C,Z$4)) | AA30: =IF(DAY(DATE(PORTADA!$B$2,1,26))<>26,"",SUM(T30:Z30))
A31: DIVERSION | B31: COPETE | C31: =CATEGORIAS!$E$25 | D31: =SUMIFS(MOVIMIENTOS!$F:$F,MOVIMIENTOS!$A:$A,">="&DATE(PORTADA!$B$2,1,1),MOVIMIENTOS!$A:$A,"<="&EOMONTH(DATE(PORTADA!$B$2,1,1),0),MOVIMIENTOS!$D:$D,$B31) | E31: =C31-D31 | F31: =IFERROR(D31/C31,"") | S31: =IF(DAY(DATE(PORTADA!$B$2,1,27))<>27,"",27) | T31: =IF(DAY(DATE(PORTADA!$B$2,1,27))<>27,"",SUMIFS(MOVIMIENTOS!$F:$F,MOVIMIENTOS!$A:$A,DATE(PORTADA!$B$2,1,27),MOVIMIENTOS!$C:$C,T$4)) | U31: =IF(DAY(DATE(PORTADA!$B$2,1,27))<>27,"",SUMIFS(MOVIMIENTOS!$F:$F,MOVIMIENTOS!$A:$A,DATE(PORTADA!$B$2,1,27),MOVIMIENTOS!$C:$C,U$4)) | V31: =IF(DAY(DATE(PORTADA!$B$2,1,27))<>27,"",SUMIFS(MOVIMIENTOS!$F:$F,MOVIMIENTOS!$A:$A,DATE(PORTADA!$B$2,1,27),MOVIMIENTOS!$C:$C,V$4)) | W31: =IF(DAY(DATE(PORTADA!$B$2,1,27))<>27,"",SUMIFS(MOVIMIENTOS!$F:$F,MOVIMIENTOS!$A:$A,DATE(PORTADA!$B$2,1,27),MOVIMIENTOS!$C:$C,W$4)) | X31: =IF(DAY(DATE(PORTADA!$B$2,1,27))<>27,"",SUMIFS(MOVIMIENTOS!$F:$F,MOVIMIENTOS!$A:$A,DATE(PORTADA!$B$2,1,27),MOVIMIENTOS!$C:$C,X$4)) | Y31: =IF(DAY(DATE(PORTADA!$B$2,1,27))<>27,"",SUMIFS(MOVIMIENTOS!$F:$F,MOVIMIENTOS!$A:$A,DATE(PORTADA!$B$2,1,27),MOVIMIENTOS!$C:$C,Y$4)) | Z31: =IF(DAY(DATE(PORTADA!$B$2,1,27))<>27,"",SUMIFS(MOVIMIENTOS!$F:$F,MOVIMIENTOS!$A:$A,DATE(PORTADA!$B$2,1,27),MOVIMIENTOS!$C:$C,Z$4)) | AA31: =IF(DAY(DATE(PORTADA!$B$2,1,27))<>27,"",SUM(T31:Z31))
A32: DIVERSION | B32: WEED | C32: =CATEGORIAS!$E$26 | D32: =SUMIFS(MOVIMIENTOS!$F:$F,MOVIMIENTOS!$A:$A,">="&DATE(PORTADA!$B$2,1,1),MOVIMIENTOS!$A:$A,"<="&EOMONTH(DATE(PORTADA!$B$2,1,1),0),MOVIMIENTOS!$D:$D,$B32) | E32: =C32-D32 | F32: =IFERROR(D32/C32,"") | S32: =IF(DAY(DATE(PORTADA!$B$2,1,28))<>28,"",28) | T32: =IF(DAY(DATE(PORTADA!$B$2,1,28))<>28,"",SUMIFS(MOVIMIENTOS!$F:$F,MOVIMIENTOS!$A:$A,DATE(PORTADA!$B$2,1,28),MOVIMIENTOS!$C:$C,T$4)) | U32: =IF(DAY(DATE(PORTADA!$B$2,1,28))<>28,"",SUMIFS(MOVIMIENTOS!$F:$F,MOVIMIENTOS!$A:$A,DATE(PORTADA!$B$2,1,28),MOVIMIENTOS!$C:$C,U$4)) | V32: =IF(DAY(DATE(PORTADA!$B$2,1,28))<>28,"",SUMIFS(MOVIMIENTOS!$F:$F,MOVIMIENTOS!$A:$A,DATE(PORTADA!$B$2,1,28),MOVIMIENTOS!$C:$C,V$4)) | W32: =IF(DAY(DATE(PORTADA!$B$2,1,28))<>28,"",SUMIFS(MOVIMIENTOS!$F:$F,MOVIMIENTOS!$A:$A,DATE(PORTADA!$B$2,1,28),MOVIMIENTOS!$C:$C,W$4)) | X32: =IF(DAY(DATE(PORTADA!$B$2,1,28))<>28,"",SUMIFS(MOVIMIENTOS!$F:$F,MOVIMIENTOS!$A:$A,DATE(PORTADA!$B$2,1,28),MOVIMIENTOS!$C:$C,X$4)) | Y32: =IF(DAY(DATE(PORTADA!$B$2,1,28))<>28,"",SUMIFS(MOVIMIENTOS!$F:$F,MOVIMIENTOS!$A:$A,DATE(PORTADA!$B$2,1,28),MOVIMIENTOS!$C:$C,Y$4)) | Z32: =IF(DAY(DATE(PORTADA!$B$2,1,28))<>28,"",SUMIFS(MOVIMIENTOS!$F:$F,MOVIMIENTOS!$A:$A,DATE(PORTADA!$B$2,1,28),MOVIMIENTOS!$C:$C,Z$4)) | AA32: =IF(DAY(DATE(PORTADA!$B$2,1,28))<>28,"",SUM(T32:Z32))
A33: DIVERSION | B33: CARCASA CELULAR | C33: =CATEGORIAS!$E$27 | D33: =SUMIFS(MOVIMIENTOS!$F:$F,MOVIMIENTOS!$A:$A,">="&DATE(PORTADA!$B$2,1,1),MOVIMIENTOS!$A:$A,"<="&EOMONTH(DATE(PORTADA!$B$2,1,1),0),MOVIMIENTOS!$D:$D,$B33) | E33: =C33-D33 | F33: =IFERROR(D33/C33,"") | S33: =IF(DAY(DATE(PORTADA!$B$2,1,29))<>29,"",29) | T33: =IF(DAY(DATE(PORTADA!$B$2,1,29))<>29,"",SUMIFS(MOVIMIENTOS!$F:$F,MOVIMIENTOS!$A:$A,DATE(PORTADA!$B$2,1,29),MOVIMIENTOS!$C:$C,T$4)) | U33: =IF(DAY(DATE(PORTADA!$B$2,1,29))<>29,"",SUMIFS(MOVIMIENTOS!$F:$F,MOVIMIENTOS!$A:$A,DATE(PORTADA!$B$2,1,29),MOVIMIENTOS!$C:$C,U$4)) | V33: =IF(DAY(DATE(PORTADA!$B$2,1,29))<>29,"",SUMIFS(MOVIMIENTOS!$F:$F,MOVIMIENTOS!$A:$A,DATE(PORTADA!$B$2,1,29),MOVIMIENTOS!$C:$C,V$4)) | W33: =IF(DAY(DATE(PORTADA!$B$2,1,29))<>29,"",SUMIFS(MOVIMIENTOS!$F:$F,MOVIMIENTOS!$A:$A,DATE(PORTADA!$B$2,1,29),MOVIMIENTOS!$C:$C,W$4)) | X33: =IF(DAY(DATE(PORTADA!$B$2,1,29))<>29,"",SUMIFS(MOVIMIENTOS!$F:$F,MOVIMIENTOS!$A:$A,DATE(PORTADA!$B$2,1,29),MOVIMIENTOS!$C:$C,X$4)) | Y33: =IF(DAY(DATE(PORTADA!$B$2,1,29))<>29,"",SUMIFS(MOVIMIENTOS!$F:$F,MOVIMIENTOS!$A:$A,DATE(PORTADA!$B$2,1,29),MOVIMIENTOS!$C:$C,Y$4)) | Z33: =IF(DAY(DATE(PORTADA!$B$2,1,29))<>29,"",SUMIFS(MOVIMIENTOS!$F:$F,MOVIMIENTOS!$A:$A,DATE(PORTADA!$B$2,1,29),MOVIMIENTOS!$C:$C,Z$4)) | AA33: =IF(DAY(DATE(PORTADA!$B$2,1,29))<>29,"",SUM(T33:Z33))
A34: DIVERSION | B34: SALIDA CON AMIGOS | C34: =CATEGORIAS!$E$28 | D34: =SUMIFS(MOVIMIENTOS!$F:$F,MOVIMIENTOS!$A:$A,">="&DATE(PORTADA!$B$2,1,1),MOVIMIENTOS!$A:$A,"<="&EOMONTH(DATE(PORTADA!$B$2,1,1),0),MOVIMIENTOS!$D:$D,$B34) | E34: =C34-D34 | F34: =IFERROR(D34/C34,"") | S34: =IF(DAY(DATE(PORTADA!$B$2,1,30))<>30,"",30) | T34: =IF(DAY(DATE(PORTADA!$B$2,1,30))<>30,"",SUMIFS(MOVIMIENTOS!$F:$F,MOVIMIENTOS!$A:$A,DATE(PORTADA!$B$2,1,30),MOVIMIENTOS!$C:$C,T$4)) | U34: =IF(DAY(DATE(PORTADA!$B$2,1,30))<>30,"",SUMIFS(MOVIMIENTOS!$F:$F,MOVIMIENTOS!$A:$A,DATE(PORTADA!$B$2,1,30),MOVIMIENTOS!$C:$C,U$4)) | V34: =IF(DAY(DATE(PORTADA!$B$2,1,30))<>30,"",SUMIFS(MOVIMIENTOS!$F:$F,MOVIMIENTOS!$A:$A,DATE(PORTADA!$B$2,1,30),MOVIMIENTOS!$C:$C,V$4)) | W34: =IF(DAY(DATE(PORTADA!$B$2,1,30))<>30,"",SUMIFS(MOVIMIENTOS!$F:$F,MOVIMIENTOS!$A:$A,DATE(PORTADA!$B$2,1,30),MOVIMIENTOS!$C:$C,W$4)) | X34: =IF(DAY(DATE(PORTADA!$B$2,1,30))<>30,"",SUMIFS(MOVIMIENTOS!$F:$F,MOVIMIENTOS!$A:$A,DATE(PORTADA!$B$2,1,30),MOVIMIENTOS!$C:$C,X$4)) | Y34: =IF(DAY(DATE(PORTADA!$B$2,1,30))<>30,"",SUMIFS(MOVIMIENTOS!$F:$F,MOVIMIENTOS!$A:$A,DATE(PORTADA!$B$2,1,30),MOVIMIENTOS!$C:$C,Y$4)) | Z34: =IF(DAY(DATE(PORTADA!$B$2,1,30))<>30,"",SUMIFS(MOVIMIENTOS!$F:$F,MOVIMIENTOS!$A:$A,DATE(PORTADA!$B$2,1,30),MOVIMIENTOS!$C:$C,Z$4)) | AA34: =IF(DAY(DATE(PORTADA!$B$2,1,30))<>30,"",SUM(T34:Z34))
A35: OTROS | B35: CHICHES | C35: =CATEGORIAS!$E$29 | D35: =SUMIFS(MOVIMIENTOS!$F:$F,MOVIMIENTOS!$A:$A,">="&DATE(PORTADA!$B$2,1,1),MOVIMIENTOS!$A:$A,"<="&EOMONTH(DATE(PORTADA!$B$2,1,1),0),MOVIMIENTOS!$D:$D,$B35) | E35: =C35-D35 | F35: =IFERROR(D35/C35,"") | S35: =IF(DAY(DATE(PORTADA!$B$2,1,31))<>31,"",31) | T35: =IF(DAY(DATE(PORTADA!$B$2,1,31))<>31,"",SUMIFS(MOVIMIENTOS!$F:$F,MOVIMIENTOS!$A:$A,DATE(PORTADA!$B$2,1,31),MOVIMIENTOS!$C:$C,T$4)) | U35: =IF(DAY(DATE(PORTADA!$B$2,1,31))<>31,"",SUMIFS(MOVIMIENTOS!$F:$F,MOVIMIENTOS!$A:$A,DATE(PORTADA!$B$2,1,31),MOVIMIENTOS!$C:$C,U$4)) | V35: =IF(DAY(DATE(PORTADA!$B$2,1,31))<>31,"",SUMIFS(MOVIMIENTOS!$F:$F,MOVIMIENTOS!$A:$A,DATE(PORTADA!$B$2,1,31),MOVIMIENTOS!$C:$C,V$4)) | W35: =IF(DAY(DATE(PORTADA!$B$2,1,31))<>31,"",SUMIFS(MOVIMIENTOS!$F:$F,MOVIMIENTOS!$A:$A,DATE(PORTADA!$B$2,1,31),MOVIMIENTOS!$C:$C,W$4)) | X35: =IF(DAY(DATE(PORTADA!$B$2,1,31))<>31,"",SUMIFS(MOVIMIENTOS!$F:$F,MOVIMIENTOS!$A:$A,DATE(PORTADA!$B$2,1,31),MOVIMIENTOS!$C:$C,X$4)) | Y35: =IF(DAY(DATE(PORTADA!$B$2,1,31))<>31,"",SUMIFS(MOVIMIENTOS!$F:$F,MOVIMIENTOS!$A:$A,DATE(PORTADA!$B$2,1,31),MOVIMIENTOS!$C:$C,Y$4)) | Z35: =IF(DAY(DATE(PORTADA!$B$2,1,31))<>31,"",SUMIFS(MOVIMIENTOS!$F:$F,MOVIMIENTOS!$A:$A,DATE(PORTADA!$B$2,1,31),MOVIMIENTOS!$C:$C,Z$4)) | AA35: =IF(DAY(DATE(PORTADA!$B$2,1,31))<>31,"",SUM(T35:Z35))
A36: OTROS | B36: DONACIONES | C36: =CATEGORIAS!$E$30 | D36: =SUMIFS(MOVIMIENTOS!$F:$F,MOVIMIENTOS!$A:$A,">="&DATE(PORTADA!$B$2,1,1),MOVIMIENTOS!$A:$A,"<="&EOMONTH(DATE(PORTADA!$B$2,1,1),0),MOVIMIENTOS!$D:$D,$B36) | E36: =C36-D36 | F36: =IFERROR(D36/C36,"") | S36: MES | T36: =SUM(T5:T35) | U36: =SUM(U5:U35) | V36: =SUM(V5:V35) | W36: =SUM(W5:W35) | X36: =SUM(X5:X35) | Y36: =SUM(Y5:Y35) | Z36: =SUM(Z5:Z35) | AA36: =SUM(AA5:AA35)
A37: OTROS | B37: PRESTAMOS | C37: =CATEGORIAS!$E$31 | D37: =SUMIFS(MOVIMIENTOS!$F:$F,MOVIMIENTOS!$A:$A,">="&DATE(PORTADA!$B$2,1,1),MOVIMIENTOS!$A:$A,"<="&EOMONTH(DATE(PORTADA!$B$2,1,1),0),MOVIMIENTOS!$D:$D,$B37) | E37: =C37-D37 | F37: =IFERROR(D37/C37,"")
A38: OTROS | B38: LOCOMOCION | C38: =CATEGORIAS!$E$32 | D38: =SUMIFS(MOVIMIENTOS!$F:$F,MOVIMIENTOS!$A:$A,">="&DATE(PORTADA!$B$2,1,1),MOVIMIENTOS!$A:$A,"<="&EOMONTH(DATE(PORTADA!$B$2,1,1),0),MOVIMIENTOS!$D:$D,$B38) | E38: =C38-D38 | F38: =IFERROR(D38/C38,"")
A39: OTROS | B39: OTROS GASTOS | C39: =CATEGORIAS!$E$33 | D39: =SUMIFS(MOVIMIENTOS!$F:$F,MOVIMIENTOS!$A:$A,">="&DATE(PORTADA!$B$2,1,1),MOVIMIENTOS!$A:$A,"<="&EOMONTH(DATE(PORTADA!$B$2,1,1),0),MOVIMIENTOS!$D:$D,$B39) | E39: =C39-D39 | F39: =IFERROR(D39/C39,"")
B40: TOTAL EGRESOS | C40: =SUM(C17:C39) | D40: =SUM(D17:D39) | E40: =SUM(E17:E39)
A42: POR GRUPO
A43: GRUPO | C43: PRESUPUESTO | D43: REAL | E43: DIFERENCIA | F43: % USADO
A44: CUENTAS PERSONALES | C44: =SUMIFS($C$17:$C$39,$A$17:$A$39,$A44) | D44: =SUMIFS($D$17:$D$39,$A$17:$A$39,$A44) | E44: =C44-D44 | F44: =IFERROR(D44/C44,"")
A45: HIJOS | C45: =SUMIFS($C$17:$C$39,$A$17:$A$39,$A45) | D45: =SUMIFS($D$17:$D$39,$A$17:$A$39,$A45) | E45: =C45-D45 | F45: =IFERROR(D45/C45,"")
A46: CASA | C46: =SUMIFS($C$17:$C$39,$A$17:$A$39,$A46) | D46: =SUMIFS($D$17:$D$39,$A$17:$A$39,$A46) | E46: =C46-D46 | F46: =IFERROR(D46/C46,"")
A47: SALUD | C47: =SUMIFS($C$17:$C$39,$A$17:$A$39,$A47) | D47: =SUMIFS($D$17:$D$39,$A$17:$A$39,$A47) | E47: =C47-D47 | F47: =IFERROR(D47/C47,"")
A48: AUTO | C48: =SUMIFS($C$17:$C$39,$A$17:$A$39,$A48) | D48: =SUMIFS($D$17:$D$39,$A$17:$A$39,$A48) | E48: =C48-D48 | F48: =IFERROR(D48/C48,"")
A49: DIVERSION | C49: =SUMIFS($C$17:$C$39,$A$17:$A$39,$A49) | D49: =SUMIFS($D$17:$D$39,$A$17:$A$39,$A49) | E49: =C49-D49 | F49: =IFERROR(D49/C49,"")
A50: OTROS | C50: =SUMIFS($C$17:$C$39,$A$17:$A$39,$A50) | D50: =SUMIFS($D$17:$D$39,$A$17:$A$39,$A50) | E50: =C50-D50 | F50: =IFERROR(D50/C50,"")
A52: SALDO DEL MES
B53: Ingresos menos egresos | C53: =C13-C40 | D53: =D13-D40
B54: Solo gasto | C54: =SUMIFS(CATEGORIAS!$E:$E,CATEGORIAS!$D:$D,"GASTO") | D54: =SUMIFS(MOVIMIENTOS!$F:$F,MOVIMIENTOS!$A:$A,">="&DATE(PORTADA!$B$2,1,1),MOVIMIENTOS!$A:$A,"<="&EOMONTH(DATE(PORTADA!$B$2,1,1),0),MOVIMIENTOS!$E:$E,"GASTO")
B55: Ahorro | C55: =SUMIFS(CATEGORIAS!$E:$E,CATEGORIAS!$D:$D,"AHORRO") | D55: =SUMIFS(MOVIMIENTOS!$F:$F,MOVIMIENTOS!$A:$A,">="&DATE(PORTADA!$B$2,1,1),MOVIMIENTOS!$A:$A,"<="&EOMONTH(DATE(PORTADA!$B$2,1,1),0),MOVIMIENTOS!$E:$E,"AHORRO")
B56: Deuda | C56: =SUMIFS(CATEGORIAS!$E:$E,CATEGORIAS!$D:$D,"DEUDA") | D56: =SUMIFS(MOVIMIENTOS!$F:$F,MOVIMIENTOS!$A:$A,">="&DATE(PORTADA!$B$2,1,1),MOVIMIENTOS!$A:$A,"<="&EOMONTH(DATE(PORTADA!$B$2,1,1),0),MOVIMIENTOS!$E:$E,"DEUDA")

Sheet FEBRERO
A1: FEBRERO · ingresos y egresos
A2: =CONCATENATE("Año ",PORTADA!$B$2," · verde = lo escribes tú · azul = se calcula solo")
S3: DÍA A DÍA
A4: INGRESOS | S4: DÍA | T4: CUENTAS PERSONALES | U4: HIJOS | V4: CASA | W4: SALUD | X4: AUTO | Y4: DIVERSION | Z4: OTROS | AA4: TOTAL
A5: GRUPO | B5: CATEGORÍA | C5: PRESUPUESTO | D5: REAL | E5: DIFERENCIA | F5: % LOGRO | S5: =IF(DAY(DATE(PORTADA!$B$2,2,1))<>1,"",1) | T5: =IF(DAY(DATE(PORTADA!$B$2,2,1))<>1,"",SUMIFS(MOVIMIENTOS!$F:$F,MOVIMIENTOS!$A:$A,DATE(PORTADA!$B$2,2,1),MOVIMIENTOS!$C:$C,T$4)) | U5: =IF(DAY(DATE(PORTADA!$B$2,2,1))<>1,"",SUMIFS(MOVIMIENTOS!$F:$F,MOVIMIENTOS!$A:$A,DATE(PORTADA!$B$2,2,1),MOVIMIENTOS!$C:$C,U$4)) | V5: =IF(DAY(DATE(PORTADA!$B$2,2,1))<>1,"",SUMIFS(MOVIMIENTOS!$F:$F,MOVIMIENTOS!$A:$A,DATE(PORTADA!$B$2,2,1),MOVIMIENTOS!$C:$C,V$4)) | W5: =IF(DAY(DATE(PORTADA!$B$2,2,1))<>1,"",SUMIFS(MOVIMIENTOS!$F:$F,MOVIMIENTOS!$A:$A,DATE(PORTADA!$B$2,2,1),MOVIMIENTOS!$C:$C,W$4)) | X5: =IF(DAY(DATE(PORTADA!$B$2,2,1))<>1,"",SUMIFS(MOVIMIENTOS!$F:$F,MOVIMIENTOS!$A:$A,DATE(PORTADA!$B$2,2,1),MOVIMIENTOS!$C:$C,X$4)) | Y5: =IF(DAY(DATE(PORTADA!$B$2,2,1))<>1,"",SUMIFS(MOVIMIENTOS!$F:$F,MOVIMIENTOS!$A:$A,DATE(PORTADA!$B$2,2,1),MOVIMIENTOS!$C:$C,Y$4)) | Z5: =IF(DAY(DATE(PORTADA!$B$2,2,1))<>1,"",SUMIFS(MOVIMIENTOS!$F:$F,MOVIMIENTOS!$A:$A,DATE(PORTADA!$B$2,2,1),MOVIMIENTOS!$C:$C,Z$4)) | AA5: =IF(DAY(DATE(PORTADA!$B$2,2,1))<>1,"",SUM(T5:Z5))
A6: SUELDO | B6: QUINCENA | C6: =CATEGORIAS!$E$4 | D6: =SUMIFS(MOVIMIENTOS!$F:$F,MOVIMIENTOS!$A:$A,">="&DATE(PORTADA!$B$2,2,1),MOVIMIENTOS!$A:$A,"<="&EOMONTH(DATE(PORTADA!$B$2,2,1),0),MOVIMIENTOS!$D:$D,$B6) | E6: =D6-C6 | F6: =IFERROR(D6/C6,"") | S6: =IF(DAY(DATE(PORTADA!$B$2,2,2))<>2,"",2) | T6: =IF(DAY(DATE(PORTADA!$B$2,2,2))<>2,"",SUMIFS(MOVIMIENTOS!$F:$F,MOVIMIENTOS!$A:$A,DATE(PORTADA!$B$2,2,2),MOVIMIENTOS!$C:$C,T$4)) | U6: =IF(DAY(DATE(PORTADA!$B$2,2,2))<>2,"",SUMIFS(MOVIMIENTOS!$F:$F,MOVIMIENTOS!$A:$A,DATE(PORTADA!$B$2,2,2),MOVIMIENTOS!$C:$C,U$4)) | V6: =IF(DAY(DATE(PORTADA!$B$2,2,2))<>2,"",SUMIFS(MOVIMIENTOS!$F:$F,MOVIMIENTOS!$A:$A,DATE(PORTADA!$B$2,2,2),MOVIMIENTOS!$C:$C,V$4)) | W6: =IF(DAY(DATE(PORTADA!$B$2,2,2))<>2,"",SUMIFS(MOVIMIENTOS!$F:$F,MOVIMIENTOS!$A:$A,DATE(PORTADA!$B$2,2,2),MOVIMIENTOS!$C:$C,W$4)) | X6: =IF(DAY(DATE(PORTADA!$B$2,2,2))<>2,"",SUMIFS(MOVIMIENTOS!$F:$F,MOVIMIENTOS!$A:$A,DATE(PORTADA!$B$2,2,2),MOVIMIENTOS!$C:$C,X$4)) | Y6: =IF(DAY(DATE(PORTADA!$B$2,2,2))<>2,"",SUMIFS(MOVIMIENTOS!$F:$F,MOVIMIENTOS!$A:$A,DATE(PORTADA!$B$2,2,2),MOVIMIENTOS!$C:$C,Y$4)) | Z6: =IF(DAY(DATE(PORTADA!$B$2,2,2))<>2,"",SUMIFS(MOVIMIENTOS!$F:$F,MOVIMIENTOS!$A:$A,DATE(PORTADA!$B$2,2,2),MOVIMIENTOS!$C:$C,Z$4)) | AA6: =IF(DAY(DATE(PORTADA!$B$2,2,2))<>2,"",SUM(T6:Z6))
A7: SUELDO | B7: PAGO FIN DE MES | C7: =CATEGORIAS!$E$5 | D7: =SUMIFS(MOVIMIENTOS!$F:$F,MOVIMIENTOS!$A:$A,">="&DATE(PORTADA!$B$2,2,1),MOVIMIENTOS!$A:$A,"<="&EOMONTH(DATE(PORTADA!$B$2,2,1),0),MOVIMIENTOS!$D:$D,$B7) | E7: =D7-C7 | F7: =IFERROR(D7/C7,"") | S7: =IF(DAY(DATE(PORTADA!$B$2,2,3))<>3,"",3) | T7: =IF(DAY(DATE(PORTADA!$B$2,2,3))<>3,"",SUMIFS(MOVIMIENTOS!$F:$F,MOVIMIENTOS!$A:$A,DATE(PORTADA!$B$2,2,3),MOVIMIENTOS!$C:$C,T$4)) | U7: =IF(DAY(DATE(PORTADA!$B$2,2,3))<>3,"",SUMIFS(MOVIMIENTOS!$F:$F,MOVIMIENTOS!$A:$A,DATE(PORTADA!$B$2,2,3),MOVIMIENTOS!$C:$C,U$4)) | V7: =IF(DAY(DATE(PORTADA!$B$2,2,3))<>3,"",SUMIFS(MOVIMIENTOS!$F:$F,MOVIMIENTOS!$A:$A,DATE(PORTADA!$B$2,2,3),MOVIMIENTOS!$C:$C,V$4)) | W7: =IF(DAY(DATE(PORTADA!$B$2,2,3))<>3,"",SUMIFS(MOVIMIENTOS!$F:$F,MOVIMIENTOS!$A:$A,DATE(PORTADA!$B$2,2,3),MOVIMIENTOS!$C:$C,W$4)) | X7: =IF(DAY(DATE(PORTADA!$B$2,2,3))<>3,"",SUMIFS(MOVIMIENTOS!$F:$F,MOVIMIENTOS!$A:$A,DATE(PORTADA!$B$2,2,3),MOVIMIENTOS!$C:$C,X$4)) | Y7: =IF(DAY(DATE(PORTADA!$B$2,2,3))<>3,"",SUMIFS(MOVIMIENTOS!$F:$F,MOVIMIENTOS!$A:$A,DATE(PORTADA!$B$2,2,3),MOVIMIENTOS!$C:$C,Y$4)) | Z7: =IF(DAY(DATE(PORTADA!$B$2,2,3))<>3,"",SUMIFS(MOVIMIENTOS!$F:$F,MOVIMIENTOS!$A:$A,DATE(PORTADA!$B$2,2,3),MOVIMIENTOS!$C:$C,Z$4)) | AA7: =IF(DAY(DATE(PORTADA!$B$2,2,3))<>3,"",SUM(T7:Z7))
A8: NEGOCIO | B8: EFFICIENTCHILE | C8: =CATEGORIAS!$E$6 | D8: =SUMIFS(MOVIMIENTOS!$F:$F,MOVIMIENTOS!$A:$A,">="&DATE(PORTADA!$B$2,2,1),MOVIMIENTOS!$A:$A,"<="&EOMONTH(DATE(PORTADA!$B$2,2,1),0),MOVIMIENTOS!$D:$D,$B8) | E8: =D8-C8 | F8: =IFERROR(D8/C8,"") | S8: =IF(DAY(DATE(PORTADA!$B$2,2,4))<>4,"",4) | T8: =IF(DAY(DATE(PORTADA!$B$2,2,4))<>4,"",SUMIFS(MOVIMIENTOS!$F:$F,MOVIMIENTOS!$A:$A,DATE(PORTADA!$B$2,2,4),MOVIMIENTOS!$C:$C,T$4)) | U8: =IF(DAY(DATE(PORTADA!$B$2,2,4))<>4,"",SUMIFS(MOVIMIENTOS!$F:$F,MOVIMIENTOS!$A:$A,DATE(PORTADA!$B$2,2,4),MOVIMIENTOS!$C:$C,U$4)) | V8: =IF(DAY(DATE(PORTADA!$B$2,2,4))<>4,"",SUMIFS(MOVIMIENTOS!$F:$F,MOVIMIENTOS!$A:$A,DATE(PORTADA!$B$2,2,4),MOVIMIENTOS!$C:$C,V$4)) | W8: =IF(DAY(DATE(PORTADA!$B$2,2,4))<>4,"",SUMIFS(MOVIMIENTOS!$F:$F,MOVIMIENTOS!$A:$A,DATE(PORTADA!$B$2,2,4),MOVIMIENTOS!$C:$C,W$4)) | X8: =IF(DAY(DATE(PORTADA!$B$2,2,4))<>4,"",SUMIFS(MOVIMIENTOS!$F:$F,MOVIMIENTOS!$A:$A,DATE(PORTADA!$B$2,2,4),MOVIMIENTOS!$C:$C,X$4)) | Y8: =IF(DAY(DATE(PORTADA!$B$2,2,4))<>4,"",SUMIFS(MOVIMIENTOS!$F:$F,MOVIMIENTOS!$A:$A,DATE(PORTADA!$B$2,2,4),MOVIMIENTOS!$C:$C,Y$4)) | Z8: =IF(DAY(DATE(PORTADA!$B$2,2,4))<>4,"",SUMIFS(MOVIMIENTOS!$F:$F,MOVIMIENTOS!$A:$A,DATE(PORTADA!$B$2,2,4),MOVIMIENTOS!$C:$C,Z$4)) | AA8: =IF(DAY(DATE(PORTADA!$B$2,2,4))<>4,"",SUM(T8:Z8))
A9: NEGOCIO | B9: VENTA DE ARTICULO | C9: =CATEGORIAS!$E$7 | D9: =SUMIFS(MOVIMIENTOS!$F:$F,MOVIMIENTOS!$A:$A,">="&DATE(PORTADA!$B$2,2,1),MOVIMIENTOS!$A:$A,"<="&EOMONTH(DATE(PORTADA!$B$2,2,1),0),MOVIMIENTOS!$D:$D,$B9) | E9: =D9-C9 | F9: =IFERROR(D9/C9,"") | S9: =IF(DAY(DATE(PORTADA!$B$2,2,5))<>5,"",5) | T9: =IF(DAY(DATE(PORTADA!$B$2,2,5))<>5,"",SUMIFS(MOVIMIENTOS!$F:$F,MOVIMIENTOS!$A:$A,DATE(PORTADA!$B$2,2,5),MOVIMIENTOS!$C:$C,T$4)) | U9: =IF(DAY(DATE(PORTADA!$B$2,2,5))<>5,"",SUMIFS(MOVIMIENTOS!$F:$F,MOVIMIENTOS!$A:$A,DATE(PORTADA!$B$2,2,5),MOVIMIENTOS!$C:$C,U$4)) | V9: =IF(DAY(DATE(PORTADA!$B$2,2,5))<>5,"",SUMIFS(MOVIMIENTOS!$F:$F,MOVIMIENTOS!$A:$A,DATE(PORTADA!$B$2,2,5),MOVIMIENTOS!$C:$C,V$4)) | W9: =IF(DAY(DATE(PORTADA!$B$2,2,5))<>5,"",SUMIFS(MOVIMIENTOS!$F:$F,MOVIMIENTOS!$A:$A,DATE(PORTADA!$B$2,2,5),MOVIMIENTOS!$C:$C,W$4)) | X9: =IF(DAY(DATE(PORTADA!$B$2,2,5))<>5,"",SUMIFS(MOVIMIENTOS!$F:$F,MOVIMIENTOS!$A:$A,DATE(PORTADA!$B$2,2,5),MOVIMIENTOS!$C:$C,X$4)) | Y9: =IF(DAY(DATE(PORTADA!$B$2,2,5))<>5,"",SUMIFS(MOVIMIENTOS!$F:$F,MOVIMIENTOS!$A:$A,DATE(PORTADA!$B$2,2,5),MOVIMIENTOS!$C:$C,Y$4)) | Z9: =IF(DAY(DATE(PORTADA!$B$2,2,5))<>5,"",SUMIFS(MOVIMIENTOS!$F:$F,MOVIMIENTOS!$A:$A,DATE(PORTADA!$B$2,2,5),MOVIMIENTOS!$C:$C,Z$4)) | AA9: =IF(DAY(DATE(PORTADA!$B$2,2,5))<>5,"",SUM(T9:Z9))
A10: NEGOCIO | B10: VENTA DE SERVICIO | C10: =CATEGORIAS!$E$8 | D10: =SUMIFS(MOVIMIENTOS!$F:$F,MOVIMIENTOS!$A:$A,">="&DATE(PORTADA!$B$2,2,1),MOVIMIENTOS!$A:$A,"<="&EOMONTH(DATE(PORTADA!$B$2,2,1),0),MOVIMIENTOS!$D:$D,$B10) | E10: =D10-C10 | F10: =IFERROR(D10/C10,"") | S10: =IF(DAY(DATE(PORTADA!$B$2,2,6))<>6,"",6) | T10: =IF(DAY(DATE(PORTADA!$B$2,2,6))<>6,"",SUMIFS(MOVIMIENTOS!$F:$F,MOVIMIENTOS!$A:$A,DATE(PORTADA!$B$2,2,6),MOVIMIENTOS!$C:$C,T$4)) | U10: =IF(DAY(DATE(PORTADA!$B$2,2,6))<>6,"",SUMIFS(MOVIMIENTOS!$F:$F,MOVIMIENTOS!$A:$A,DATE(PORTADA!$B$2,2,6),MOVIMIENTOS!$C:$C,U$4)) | V10: =IF(DAY(DATE(PORTADA!$B$2,2,6))<>6,"",SUMIFS(MOVIMIENTOS!$F:$F,MOVIMIENTOS!$A:$A,DATE(PORTADA!$B$2,2,6),MOVIMIENTOS!$C:$C,V$4)) | W10: =IF(DAY(DATE(PORTADA!$B$2,2,6))<>6,"",SUMIFS(MOVIMIENTOS!$F:$F,MOVIMIENTOS!$A:$A,DATE(PORTADA!$B$2,2,6),MOVIMIENTOS!$C:$C,W$4)) | X10: =IF(DAY(DATE(PORTADA!$B$2,2,6))<>6,"",SUMIFS(MOVIMIENTOS!$F:$F,MOVIMIENTOS!$A:$A,DATE(PORTADA!$B$2,2,6),MOVIMIENTOS!$C:$C,X$4)) | Y10: =IF(DAY(DATE(PORTADA!$B$2,2,6))<>6,"",SUMIFS(MOVIMIENTOS!$F:$F,MOVIMIENTOS!$A:$A,DATE(PORTADA!$B$2,2,6),MOVIMIENTOS!$C:$C,Y$4)) | Z10: =IF(DAY(DATE(PORTADA!$B$2,2,6))<>6,"",SUMIFS(MOVIMIENTOS!$F:$F,MOVIMIENTOS!$A:$A,DATE(PORTADA!$B$2,2,6),MOVIMIENTOS!$C:$C,Z$4)) | AA10: =IF(DAY(DATE(PORTADA!$B$2,2,6))<>6,"",SUM(T10:Z10))
A11: OTROS | B11: COBROS PENDIENTES | C11: =CATEGORIAS!$E$9 | D11: =SUMIFS(MOVIMIENTOS!$F:$F,MOVIMIENTOS!$A:$A,">="&DATE(PORTADA!$B$2,2,1),MOVIMIENTOS!$A:$A,"<="&EOMONTH(DATE(PORTADA!$B$2,2,1),0),MOVIMIENTOS!$D:$D,$B11) | E11: =D11-C11 | F11: =IFERROR(D11/C11,"") | S11: =IF(DAY(DATE(PORTADA!$B$2,2,7))<>7,"",7) | T11: =IF(DAY(DATE(PORTADA!$B$2,2,7))<>7,"",SUMIFS(MOVIMIENTOS!$F:$F,MOVIMIENTOS!$A:$A,DATE(PORTADA!$B$2,2,7),MOVIMIENTOS!$C:$C,T$4)) | U11: =IF(DAY(DATE(PORTADA!$B$2,2,7))<>7,"",SUMIFS(MOVIMIENTOS!$F:$F,MOVIMIENTOS!$A:$A,DATE(PORTADA!$B$2,2,7),MOVIMIENTOS!$C:$C,U$4)) | V11: =IF(DAY(DATE(PORTADA!$B$2,2,7))<>7,"",SUMIFS(MOVIMIENTOS!$F:$F,MOVIMIENTOS!$A:$A,DATE(PORTADA!$B$2,2,7),MOVIMIENTOS!$C:$C,V$4)) | W11: =IF(DAY(DATE(PORTADA!$B$2,2,7))<>7,"",SUMIFS(MOVIMIENTOS!$F:$F,MOVIMIENTOS!$A:$A,DATE(PORTADA!$B$2,2,7),MOVIMIENTOS!$C:$C,W$4)) | X11: =IF(DAY(DATE(PORTADA!$B$2,2,7))<>7,"",SUMIFS(MOVIMIENTOS!$F:$F,MOVIMIENTOS!$A:$A,DATE(PORTADA!$B$2,2,7),MOVIMIENTOS!$C:$C,X$4)) | Y11: =IF(DAY(DATE(PORTADA!$B$2,2,7))<>7,"",SUMIFS(MOVIMIENTOS!$F:$F,MOVIMIENTOS!$A:$A,DATE(PORTADA!$B$2,2,7),MOVIMIENTOS!$C:$C,Y$4)) | Z11: =IF(DAY(DATE(PORTADA!$B$2,2,7))<>7,"",SUMIFS(MOVIMIENTOS!$F:$F,MOVIMIENTOS!$A:$A,DATE(PORTADA!$B$2,2,7),MOVIMIENTOS!$C:$C,Z$4)) | AA11: =IF(DAY(DATE(PORTADA!$B$2,2,7))<>7,"",SUM(T11:Z11))
A12: OTROS | B12: OTROS INGRESOS | C12: =CATEGORIAS!$E$10 | D12: =SUMIFS(MOVIMIENTOS!$F:$F,MOVIMIENTOS!$A:$A,">="&DATE(PORTADA!$B$2,2,1),MOVIMIENTOS!$A:$A,"<="&EOMONTH(DATE(PORTADA!$B$2,2,1),0),MOVIMIENTOS!$D:$D,$B12) | E12: =D12-C12 | F12: =IFERROR(D12/C12,"") | S12: =IF(DAY(DATE(PORTADA!$B$2,2,8))<>8,"",8) | T12: =IF(DAY(DATE(PORTADA!$B$2,2,8))<>8,"",SUMIFS(MOVIMIENTOS!$F:$F,MOVIMIENTOS!$A:$A,DATE(PORTADA!$B$2,2,8),MOVIMIENTOS!$C:$C,T$4)) | U12: =IF(DAY(DATE(PORTADA!$B$2,2,8))<>8,"",SUMIFS(MOVIMIENTOS!$F:$F,MOVIMIENTOS!$A:$A,DATE(PORTADA!$B$2,2,8),MOVIMIENTOS!$C:$C,U$4)) | V12: =IF(DAY(DATE(PORTADA!$B$2,2,8))<>8,"",SUMIFS(MOVIMIENTOS!$F:$F,MOVIMIENTOS!$A:$A,DATE(PORTADA!$B$2,2,8),MOVIMIENTOS!$C:$C,V$4)) | W12: =IF(DAY(DATE(PORTADA!$B$2,2,8))<>8,"",SUMIFS(MOVIMIENTOS!$F:$F,MOVIMIENTOS!$A:$A,DATE(PORTADA!$B$2,2,8),MOVIMIENTOS!$C:$C,W$4)) | X12: =IF(DAY(DATE(PORTADA!$B$2,2,8))<>8,"",SUMIFS(MOVIMIENTOS!$F:$F,MOVIMIENTOS!$A:$A,DATE(PORTADA!$B$2,2,8),MOVIMIENTOS!$C:$C,X$4)) | Y12: =IF(DAY(DATE(PORTADA!$B$2,2,8))<>8,"",SUMIFS(MOVIMIENTOS!$F:$F,MOVIMIENTOS!$A:$A,DATE(PORTADA!$B$2,2,8),MOVIMIENTOS!$C:$C,Y$4)) | Z12: =IF(DAY(DATE(PORTADA!$B$2,2,8))<>8,"",SUMIFS(MOVIMIENTOS!$F:$F,MOVIMIENTOS!$A:$A,DATE(PORTADA!$B$2,2,8),MOVIMIENTOS!$C:$C,Z$4)) | AA12: =IF(DAY(DATE(PORTADA!$B$2,2,8))<>8,"",SUM(T12:Z12))
B13: TOTAL INGRESOS | C13: =SUM(C6:C12) | D13: =SUM(D6:D12) | E13: =SUM(E6:E12) | S13: =IF(DAY(DATE(PORTADA!$B$2,2,9))<>9,"",9) | T13: =IF(DAY(DATE(PORTADA!$B$2,2,9))<>9,"",SUMIFS(MOVIMIENTOS!$F:$F,MOVIMIENTOS!$A:$A,DATE(PORTADA!$B$2,2,9),MOVIMIENTOS!$C:$C,T$4)) | U13: =IF(DAY(DATE(PORTADA!$B$2,2,9))<>9,"",SUMIFS(MOVIMIENTOS!$F:$F,MOVIMIENTOS!$A:$A,DATE(PORTADA!$B$2,2,9),MOVIMIENTOS!$C:$C,U$4)) | V13: =IF(DAY(DATE(PORTADA!$B$2,2,9))<>9,"",SUMIFS(MOVIMIENTOS!$F:$F,MOVIMIENTOS!$A:$A,DATE(PORTADA!$B$2,2,9),MOVIMIENTOS!$C:$C,V$4)) | W13: =IF(DAY(DATE(PORTADA!$B$2,2,9))<>9,"",SUMIFS(MOVIMIENTOS!$F:$F,MOVIMIENTOS!$A:$A,DATE(PORTADA!$B$2,2,9),MOVIMIENTOS!$C:$C,W$4)) | X13: =IF(DAY(DATE(PORTADA!$B$2,2,9))<>9,"",SUMIFS(MOVIMIENTOS!$F:$F,MOVIMIENTOS!$A:$A,DATE(PORTADA!$B$2,2,9),MOVIMIENTOS!$C:$C,X$4)) | Y13: =IF(DAY(DATE(PORTADA!$B$2,2,9))<>9,"",SUMIFS(MOVIMIENTOS!$F:$F,MOVIMIENTOS!$A:$A,DATE(PORTADA!$B$2,2,9),MOVIMIENTOS!$C:$C,Y$4)) | Z13: =IF(DAY(DATE(PORTADA!$B$2,2,9))<>9,"",SUMIFS(MOVIMIENTOS!$F:$F,MOVIMIENTOS!$A:$A,DATE(PORTADA!$B$2,2,9),MOVIMIENTOS!$C:$C,Z$4)) | AA13: =IF(DAY(DATE(PORTADA!$B$2,2,9))<>9,"",SUM(T13:Z13))
S14: =IF(DAY(DATE(PORTADA!$B$2,2,10))<>10,"",10) | T14: =IF(DAY(DATE(PORTADA!$B$2,2,10))<>10,"",SUMIFS(MOVIMIENTOS!$F:$F,MOVIMIENTOS!$A:$A,DATE(PORTADA!$B$2,2,10),MOVIMIENTOS!$C:$C,T$4)) | U14: =IF(DAY(DATE(PORTADA!$B$2,2,10))<>10,"",SUMIFS(MOVIMIENTOS!$F:$F,MOVIMIENTOS!$A:$A,DATE(PORTADA!$B$2,2,10),MOVIMIENTOS!$C:$C,U$4)) | V14: =IF(DAY(DATE(PORTADA!$B$2,2,10))<>10,"",SUMIFS(MOVIMIENTOS!$F:$F,MOVIMIENTOS!$A:$A,DATE(PORTADA!$B$2,2,10),MOVIMIENTOS!$C:$C,V$4)) | W14: =IF(DAY(DATE(PORTADA!$B$2,2,10))<>10,"",SUMIFS(MOVIMIENTOS!$F:$F,MOVIMIENTOS!$A:$A,DATE(PORTADA!$B$2,2,10),MOVIMIENTOS!$C:$C,W$4)) | X14: =IF(DAY(DATE(PORTADA!$B$2,2,10))<>10,"",SUMIFS(MOVIMIENTOS!$F:$F,MOVIMIENTOS!$A:$A,DATE(PORTADA!$B$2,2,10),MOVIMIENTOS!$C:$C,X$4)) | Y14: =IF(DAY(DATE(PORTADA!$B$2,2,10))<>10,"",SUMIFS(MOVIMIENTOS!$F:$F,MOVIMIENTOS!$A:$A,DATE(PORTADA!$B$2,2,10),MOVIMIENTOS!$C:$C,Y$4)) | Z14: =IF(DAY(DATE(PORTADA!$B$2,2,10))<>10,"",SUMIFS(MOVIMIENTOS!$F:$F,MOVIMIENTOS!$A:$A,DATE(PORTADA!$B$2,2,10),MOVIMIENTOS!$C:$C,Z$4)) | AA14: =IF(DAY(DATE(PORTADA!$B$2,2,10))<>10,"",SUM(T14:Z14))
A15: EGRESOS | S15: =IF(DAY(DATE(PORTADA!$B$2,2,11))<>11,"",11) | T15: =IF(DAY(DATE(PORTADA!$B$2,2,11))<>11,"",SUMIFS(MOVIMIENTOS!$F:$F,MOVIMIENTOS!$A:$A,DATE(PORTADA!$B$2,2,11),MOVIMIENTOS!$C:$C,T$4)) | U15: =IF(DAY(DATE(PORTADA!$B$2,2,11))<>11,"",SUMIFS(MOVIMIENTOS!$F:$F,MOVIMIENTOS!$A:$A,DATE(PORTADA!$B$2,2,11),MOVIMIENTOS!$C:$C,U$4)) | V15: =IF(DAY(DATE(PORTADA!$B$2,2,11))<>11,"",SUMIFS(MOVIMIENTOS!$F:$F,MOVIMIENTOS!$A:$A,DATE(PORTADA!$B$2,2,11),MOVIMIENTOS!$C:$C,V$4)) | W15: =IF(DAY(DATE(PORTADA!$B$2,2,11))<>11,"",SUMIFS(MOVIMIENTOS!$F:$F,MOVIMIENTOS!$A:$A,DATE(PORTADA!$B$2,2,11),MOVIMIENTOS!$C:$C,W$4)) | X15: =IF(DAY(DATE(PORTADA!$B$2,2,11))<>11,"",SUMIFS(MOVIMIENTOS!$F:$F,MOVIMIENTOS!$A:$A,DATE(PORTADA!$B$2,2,11),MOVIMIENTOS!$C:$C,X$4)) | Y15: =IF(DAY(DATE(PORTADA!$B$2,2,11))<>11,"",SUMIFS(MOVIMIENTOS!$F:$F,MOVIMIENTOS!$A:$A,DATE(PORTADA!$B$2,2,11),MOVIMIENTOS!$C:$C,Y$4)) | Z15: =IF(DAY(DATE(PORTADA!$B$2,2,11))<>11,"",SUMIFS(MOVIMIENTOS!$F:$F,MOVIMIENTOS!$A:$A,DATE(PORTADA!$B$2,2,11),MOVIMIENTOS!$C:$C,Z$4)) | AA15: =IF(DAY(DATE(PORTADA!$B$2,2,11))<>11,"",SUM(T15:Z15))
A16: GRUPO | B16: CATEGORÍA | C16: PRESUPUESTO | D16: REAL | E16: DIFERENCIA | F16: % USADO | S16: =IF(DAY(DATE(PORTADA!$B$2,2,12))<>12,"",12) | T16: =IF(DAY(DATE(PORTADA!$B$2,2,12))<>12,"",SUMIFS(MOVIMIENTOS!$F:$F,MOVIMIENTOS!$A:$A,DATE(PORTADA!$B$2,2,12),MOVIMIENTOS!$C:$C,T$4)) | U16: =IF(DAY(DATE(PORTADA!$B$2,2,12))<>12,"",SUMIFS(MOVIMIENTOS!$F:$F,MOVIMIENTOS!$A:$A,DATE(PORTADA!$B$2,2,12),MOVIMIENTOS!$C:$C,U$4)) | V16: =IF(DAY(DATE(PORTADA!$B$2,2,12))<>12,"",SUMIFS(MOVIMIENTOS!$F:$F,MOVIMIENTOS!$A:$A,DATE(PORTADA!$B$2,2,12),MOVIMIENTOS!$C:$C,V$4)) | W16: =IF(DAY(DATE(PORTADA!$B$2,2,12))<>12,"",SUMIFS(MOVIMIENTOS!$F:$F,MOVIMIENTOS!$A:$A,DATE(PORTADA!$B$2,2,12),MOVIMIENTOS!$C:$C,W$4)) | X16: =IF(DAY(DATE(PORTADA!$B$2,2,12))<>12,"",SUMIFS(MOVIMIENTOS!$F:$F,MOVIMIENTOS!$A:$A,DATE(PORTADA!$B$2,2,12),MOVIMIENTOS!$C:$C,X$4)) | Y16: =IF(DAY(DATE(PORTADA!$B$2,2,12))<>12,"",SUMIFS(MOVIMIENTOS!$F:$F,MOVIMIENTOS!$A:$A,DATE(PORTADA!$B$2,2,12),MOVIMIENTOS!$C:$C,Y$4)) | Z16: =IF(DAY(DATE(PORTADA!$B$2,2,12))<>12,"",SUMIFS(MOVIMIENTOS!$F:$F,MOVIMIENTOS!$A:$A,DATE(PORTADA!$B$2,2,12),MOVIMIENTOS!$C:$C,Z$4)) | AA16: =IF(DAY(DATE(PORTADA!$B$2,2,12))<>12,"",SUM(T16:Z16))
A17: CUENTAS PERSONALES | B17: PREST. AUTO | C17: =CATEGORIAS!$E$11 | D17: =SUMIFS(MOVIMIENTOS!$F:$F,MOVIMIENTOS!$A:$A,">="&DATE(PORTADA!$B$2,2,1),MOVIMIENTOS!$A:$A,"<="&EOMONTH(DATE(PORTADA!$B$2,2,1),0),MOVIMIENTOS!$D:$D,$B17) | E17: =C17-D17 | F17: =IFERROR(D17/C17,"") | S17: =IF(DAY(DATE(PORTADA!$B$2,2,13))<>13,"",13) | T17: =IF(DAY(DATE(PORTADA!$B$2,2,13))<>13,"",SUMIFS(MOVIMIENTOS!$F:$F,MOVIMIENTOS!$A:$A,DATE(PORTADA!$B$2,2,13),MOVIMIENTOS!$C:$C,T$4)) | U17: =IF(DAY(DATE(PORTADA!$B$2,2,13))<>13,"",SUMIFS(MOVIMIENTOS!$F:$F,MOVIMIENTOS!$A:$A,DATE(PORTADA!$B$2,2,13),MOVIMIENTOS!$C:$C,U$4)) | V17: =IF(DAY(DATE(PORTADA!$B$2,2,13))<>13,"",SUMIFS(MOVIMIENTOS!$F:$F,MOVIMIENTOS!$A:$A,DATE(PORTADA!$B$2,2,13),MOVIMIENTOS!$C:$C,V$4)) | W17: =IF(DAY(DATE(PORTADA!$B$2,2,13))<>13,"",SUMIFS(MOVIMIENTOS!$F:$F,MOVIMIENTOS!$A:$A,DATE(PORTADA!$B$2,2,13),MOVIMIENTOS!$C:$C,W$4)) | X17: =IF(DAY(DATE(PORTADA!$B$2,2,13))<>13,"",SUMIFS(MOVIMIENTOS!$F:$F,MOVIMIENTOS!$A:$A,DATE(PORTADA!$B$2,2,13),MOVIMIENTOS!$C:$C,X$4)) | Y17: =IF(DAY(DATE(PORTADA!$B$2,2,13))<>13,"",SUMIFS(MOVIMIENTOS!$F:$F,MOVIMIENTOS!$A:$A,DATE(PORTADA!$B$2,2,13),MOVIMIENTOS!$C:$C,Y$4)) | Z17: =IF(DAY(DATE(PORTADA!$B$2,2,13))<>13,"",SUMIFS(MOVIMIENTOS!$F:$F,MOVIMIENTOS!$A:$A,DATE(PORTADA!$B$2,2,13),MOVIMIENTOS!$C:$C,Z$4)) | AA17: =IF(DAY(DATE(PORTADA!$B$2,2,13))<>13,"",SUM(T17:Z17))
A18: CUENTAS PERSONALES | B18: AHORRO CASA | C18: =CATEGORIAS!$E$12 | D18: =SUMIFS(MOVIMIENTOS!$F:$F,MOVIMIENTOS!$A:$A,">="&DATE(PORTADA!$B$2,2,1),MOVIMIENTOS!$A:$A,"<="&EOMONTH(DATE(PORTADA!$B$2,2,1),0),MOVIMIENTOS!$D:$D,$B18) | E18: =C18-D18 | F18: =IFERROR(D18/C18,"") | S18: =IF(DAY(DATE(PORTADA!$B$2,2,14))<>14,"",14) | T18: =IF(DAY(DATE(PORTADA!$B$2,2,14))<>14,"",SUMIFS(MOVIMIENTOS!$F:$F,MOVIMIENTOS!$A:$A,DATE(PORTADA!$B$2,2,14),MOVIMIENTOS!$C:$C,T$4)) | U18: =IF(DAY(DATE(PORTADA!$B$2,2,14))<>14,"",SUMIFS(MOVIMIENTOS!$F:$F,MOVIMIENTOS!$A:$A,DATE(PORTADA!$B$2,2,14),MOVIMIENTOS!$C:$C,U$4)) | V18: =IF(DAY(DATE(PORTADA!$B$2,2,14))<>14,"",SUMIFS(MOVIMIENTOS!$F:$F,MOVIMIENTOS!$A:$A,DATE(PORTADA!$B$2,2,14),MOVIMIENTOS!$C:$C,V$4)) | W18: =IF(DAY(DATE(PORTADA!$B$2,2,14))<>14,"",SUMIFS(MOVIMIENTOS!$F:$F,MOVIMIENTOS!$A:$A,DATE(PORTADA!$B$2,2,14),MOVIMIENTOS!$C:$C,W$4)) | X18: =IF(DAY(DATE(PORTADA!$B$2,2,14))<>14,"",SUMIFS(MOVIMIENTOS!$F:$F,MOVIMIENTOS!$A:$A,DATE(PORTADA!$B$2,2,14),MOVIMIENTOS!$C:$C,X$4)) | Y18: =IF(DAY(DATE(PORTADA!$B$2,2,14))<>14,"",SUMIFS(MOVIMIENTOS!$F:$F,MOVIMIENTOS!$A:$A,DATE(PORTADA!$B$2,2,14),MOVIMIENTOS!$C:$C,Y$4)) | Z18: =IF(DAY(DATE(PORTADA!$B$2,2,14))<>14,"",SUMIFS(MOVIMIENTOS!$F:$F,MOVIMIENTOS!$A:$A,DATE(PORTADA!$B$2,2,14),MOVIMIENTOS!$C:$C,Z$4)) | AA18: =IF(DAY(DATE(PORTADA!$B$2,2,14))<>14,"",SUM(T18:Z18))
A19: HIJOS | B19: PENSIONES | C19: =CATEGORIAS!$E$13 | D19: =SUMIFS(MOVIMIENTOS!$F:$F,MOVIMIENTOS!$A:$A,">="&DATE(PORTADA!$B$2,2,1),MOVIMIENTOS!$A:$A,"<="&EOMONTH(DATE(PORTADA!$B$2,2,1),0),MOVIMIENTOS!$D:$D,$B19) | E19: =C19-D19 | F19: =IFERROR(D19/C19,"") | S19: =IF(DAY(DATE(PORTADA!$B$2,2,15))<>15,"",15) | T19: =IF(DAY(DATE(PORTADA!$B$2,2,15))<>15,"",SUMIFS(MOVIMIENTOS!$F:$F,MOVIMIENTOS!$A:$A,DATE(PORTADA!$B$2,2,15),MOVIMIENTOS!$C:$C,T$4)) | U19: =IF(DAY(DATE(PORTADA!$B$2,2,15))<>15,"",SUMIFS(MOVIMIENTOS!$F:$F,MOVIMIENTOS!$A:$A,DATE(PORTADA!$B$2,2,15),MOVIMIENTOS!$C:$C,U$4)) | V19: =IF(DAY(DATE(PORTADA!$B$2,2,15))<>15,"",SUMIFS(MOVIMIENTOS!$F:$F,MOVIMIENTOS!$A:$A,DATE(PORTADA!$B$2,2,15),MOVIMIENTOS!$C:$C,V$4)) | W19: =IF(DAY(DATE(PORTADA!$B$2,2,15))<>15,"",SUMIFS(MOVIMIENTOS!$F:$F,MOVIMIENTOS!$A:$A,DATE(PORTADA!$B$2,2,15),MOVIMIENTOS!$C:$C,W$4)) | X19: =IF(DAY(DATE(PORTADA!$B$2,2,15))<>15,"",SUMIFS(MOVIMIENTOS!$F:$F,MOVIMIENTOS!$A:$A,DATE(PORTADA!$B$2,2,15),MOVIMIENTOS!$C:$C,X$4)) | Y19: =IF(DAY(DATE(PORTADA!$B$2,2,15))<>15,"",SUMIFS(MOVIMIENTOS!$F:$F,MOVIMIENTOS!$A:$A,DATE(PORTADA!$B$2,2,15),MOVIMIENTOS!$C:$C,Y$4)) | Z19: =IF(DAY(DATE(PORTADA!$B$2,2,15))<>15,"",SUMIFS(MOVIMIENTOS!$F:$F,MOVIMIENTOS!$A:$A,DATE(PORTADA!$B$2,2,15),MOVIMIENTOS!$C:$C,Z$4)) | AA19: =IF(DAY(DATE(PORTADA!$B$2,2,15))<>15,"",SUM(T19:Z19))
A20: HIJOS | B20: ROPA Y REGALOS | C20: =CATEGORIAS!$E$14 | D20: =SUMIFS(MOVIMIENTOS!$F:$F,MOVIMIENTOS!$A:$A,">="&DATE(PORTADA!$B$2,2,1),MOVIMIENTOS!$A:$A,"<="&EOMONTH(DATE(PORTADA!$B$2,2,1),0),MOVIMIENTOS!$D:$D,$B20) | E20: =C20-D20 | F20: =IFERROR(D20/C20,"") | S20: =IF(DAY(DATE(PORTADA!$B$2,2,16))<>16,"",16) | T20: =IF(DAY(DATE(PORTADA!$B$2,2,16))<>16,"",SUMIFS(MOVIMIENTOS!$F:$F,MOVIMIENTOS!$A:$A,DATE(PORTADA!$B$2,2,16),MOVIMIENTOS!$C:$C,T$4)) | U20: =IF(DAY(DATE(PORTADA!$B$2,2,16))<>16,"",SUMIFS(MOVIMIENTOS!$F:$F,MOVIMIENTOS!$A:$A,DATE(PORTADA!$B$2,2,16),MOVIMIENTOS!$C:$C,U$4)) | V20: =IF(DAY(DATE(PORTADA!$B$2,2,16))<>16,"",SUMIFS(MOVIMIENTOS!$F:$F,MOVIMIENTOS!$A:$A,DATE(PORTADA!$B$2,2,16),MOVIMIENTOS!$C:$C,V$4)) | W20: =IF(DAY(DATE(PORTADA!$B$2,2,16))<>16,"",SUMIFS(MOVIMIENTOS!$F:$F,MOVIMIENTOS!$A:$A,DATE(PORTADA!$B$2,2,16),MOVIMIENTOS!$C:$C,W$4)) | X20: =IF(DAY(DATE(PORTADA!$B$2,2,16))<>16,"",SUMIFS(MOVIMIENTOS!$F:$F,MOVIMIENTOS!$A:$A,DATE(PORTADA!$B$2,2,16),MOVIMIENTOS!$C:$C,X$4)) | Y20: =IF(DAY(DATE(PORTADA!$B$2,2,16))<>16,"",SUMIFS(MOVIMIENTOS!$F:$F,MOVIMIENTOS!$A:$A,DATE(PORTADA!$B$2,2,16),MOVIMIENTOS!$C:$C,Y$4)) | Z20: =IF(DAY(DATE(PORTADA!$B$2,2,16))<>16,"",SUMIFS(MOVIMIENTOS!$F:$F,MOVIMIENTOS!$A:$A,DATE(PORTADA!$B$2,2,16),MOVIMIENTOS!$C:$C,Z$4)) | AA20: =IF(DAY(DATE(PORTADA!$B$2,2,16))<>16,"",SUM(T20:Z20))
A21: HIJOS | B21: AHORRO EMERGENCIAS | C21: =CATEGORIAS!$E$15 | D21: =SUMIFS(MOVIMIENTOS!$F:$F,MOVIMIENTOS!$A:$A,">="&DATE(PORTADA!$B$2,2,1),MOVIMIENTOS!$A:$A,"<="&EOMONTH(DATE(PORTADA!$B$2,2,1),0),MOVIMIENTOS!$D:$D,$B21) | E21: =C21-D21 | F21: =IFERROR(D21/C21,"") | S21: =IF(DAY(DATE(PORTADA!$B$2,2,17))<>17,"",17) | T21: =IF(DAY(DATE(PORTADA!$B$2,2,17))<>17,"",SUMIFS(MOVIMIENTOS!$F:$F,MOVIMIENTOS!$A:$A,DATE(PORTADA!$B$2,2,17),MOVIMIENTOS!$C:$C,T$4)) | U21: =IF(DAY(DATE(PORTADA!$B$2,2,17))<>17,"",SUMIFS(MOVIMIENTOS!$F:$F,MOVIMIENTOS!$A:$A,DATE(PORTADA!$B$2,2,17),MOVIMIENTOS!$C:$C,U$4)) | V21: =IF(DAY(DATE(PORTADA!$B$2,2,17))<>17,"",SUMIFS(MOVIMIENTOS!$F:$F,MOVIMIENTOS!$A:$A,DATE(PORTADA!$B$2,2,17),MOVIMIENTOS!$C:$C,V$4)) | W21: =IF(DAY(DATE(PORTADA!$B$2,2,17))<>17,"",SUMIFS(MOVIMIENTOS!$F:$F,MOVIMIENTOS!$A:$A,DATE(PORTADA!$B$2,2,17),MOVIMIENTOS!$C:$C,W$4)) | X21: =IF(DAY(DATE(PORTADA!$B$2,2,17))<>17,"",SUMIFS(MOVIMIENTOS!$F:$F,MOVIMIENTOS!$A:$A,DATE(PORTADA!$B$2,2,17),MOVIMIENTOS!$C:$C,X$4)) | Y21: =IF(DAY(DATE(PORTADA!$B$2,2,17))<>17,"",SUMIFS(MOVIMIENTOS!$F:$F,MOVIMIENTOS!$A:$A,DATE(PORTADA!$B$2,2,17),MOVIMIENTOS!$C:$C,Y$4)) | Z21: =IF(DAY(DATE(PORTADA!$B$2,2,17))<>17,"",SUMIFS(MOVIMIENTOS!$F:$F,MOVIMIENTOS!$A:$A,DATE(PORTADA!$B$2,2,17),MOVIMIENTOS!$C:$C,Z$4)) | AA21: =IF(DAY(DATE(PORTADA!$B$2,2,17))<>17,"",SUM(T21:Z21))
A22: HIJOS | B22: SALIDAS CON FAMILIA | C22: =CATEGORIAS!$E$16 | D22: =SUMIFS(MOVIMIENTOS!$F:$F,MOVIMIENTOS!$A:$A,">="&DATE(PORTADA!$B$2,2,1),MOVIMIENTOS!$A:$A,"<="&EOMONTH(DATE(PORTADA!$B$2,2,1),0),MOVIMIENTOS!$D:$D,$B22) | E22: =C22-D22 | F22: =IFERROR(D22/C22,"") | S22: =IF(DAY(DATE(PORTADA!$B$2,2,18))<>18,"",18) | T22: =IF(DAY(DATE(PORTADA!$B$2,2,18))<>18,"",SUMIFS(MOVIMIENTOS!$F:$F,MOVIMIENTOS!$A:$A,DATE(PORTADA!$B$2,2,18),MOVIMIENTOS!$C:$C,T$4)) | U22: =IF(DAY(DATE(PORTADA!$B$2,2,18))<>18,"",SUMIFS(MOVIMIENTOS!$F:$F,MOVIMIENTOS!$A:$A,DATE(PORTADA!$B$2,2,18),MOVIMIENTOS!$C:$C,U$4)) | V22: =IF(DAY(DATE(PORTADA!$B$2,2,18))<>18,"",SUMIFS(MOVIMIENTOS!$F:$F,MOVIMIENTOS!$A:$A,DATE(PORTADA!$B$2,2,18),MOVIMIENTOS!$C:$C,V$4)) | W22: =IF(DAY(DATE(PORTADA!$B$2,2,18))<>18,"",SUMIFS(MOVIMIENTOS!$F:$F,MOVIMIENTOS!$A:$A,DATE(PORTADA!$B$2,2,18),MOVIMIENTOS!$C:$C,W$4)) | X22: =IF(DAY(DATE(PORTADA!$B$2,2,18))<>18,"",SUMIFS(MOVIMIENTOS!$F:$F,MOVIMIENTOS!$A:$A,DATE(PORTADA!$B$2,2,18),MOVIMIENTOS!$C:$C,X$4)) | Y22: =IF(DAY(DATE(PORTADA!$B$2,2,18))<>18,"",SUMIFS(MOVIMIENTOS!$F:$F,MOVIMIENTOS!$A:$A,DATE(PORTADA!$B$2,2,18),MOVIMIENTOS!$C:$C,Y$4)) | Z22: =IF(DAY(DATE(PORTADA!$B$2,2,18))<>18,"",SUMIFS(MOVIMIENTOS!$F:$F,MOVIMIENTOS!$A:$A,DATE(PORTADA!$B$2,2,18),MOVIMIENTOS!$C:$C,Z$4)) | AA22: =IF(DAY(DATE(PORTADA!$B$2,2,18))<>18,"",SUM(T22:Z22))
A23: CASA | B23: COMIDA CASA | C23: =CATEGORIAS!$E$17 | D23: =SUMIFS(MOVIMIENTOS!$F:$F,MOVIMIENTOS!$A:$A,">="&DATE(PORTADA!$B$2,2,1),MOVIMIENTOS!$A:$A,"<="&EOMONTH(DATE(PORTADA!$B$2,2,1),0),MOVIMIENTOS!$D:$D,$B23) | E23: =C23-D23 | F23: =IFERROR(D23/C23,"") | S23: =IF(DAY(DATE(PORTADA!$B$2,2,19))<>19,"",19) | T23: =IF(DAY(DATE(PORTADA!$B$2,2,19))<>19,"",SUMIFS(MOVIMIENTOS!$F:$F,MOVIMIENTOS!$A:$A,DATE(PORTADA!$B$2,2,19),MOVIMIENTOS!$C:$C,T$4)) | U23: =IF(DAY(DATE(PORTADA!$B$2,2,19))<>19,"",SUMIFS(MOVIMIENTOS!$F:$F,MOVIMIENTOS!$A:$A,DATE(PORTADA!$B$2,2,19),MOVIMIENTOS!$C:$C,U$4)) | V23: =IF(DAY(DATE(PORTADA!$B$2,2,19))<>19,"",SUMIFS(MOVIMIENTOS!$F:$F,MOVIMIENTOS!$A:$A,DATE(PORTADA!$B$2,2,19),MOVIMIENTOS!$C:$C,V$4)) | W23: =IF(DAY(DATE(PORTADA!$B$2,2,19))<>19,"",SUMIFS(MOVIMIENTOS!$F:$F,MOVIMIENTOS!$A:$A,DATE(PORTADA!$B$2,2,19),MOVIMIENTOS!$C:$C,W$4)) | X23: =IF(DAY(DATE(PORTADA!$B$2,2,19))<>19,"",SUMIFS(MOVIMIENTOS!$F:$F,MOVIMIENTOS!$A:$A,DATE(PORTADA!$B$2,2,19),MOVIMIENTOS!$C:$C,X$4)) | Y23: =IF(DAY(DATE(PORTADA!$B$2,2,19))<>19,"",SUMIFS(MOVIMIENTOS!$F:$F,MOVIMIENTOS!$A:$A,DATE(PORTADA!$B$2,2,19),MOVIMIENTOS!$C:$C,Y$4)) | Z23: =IF(DAY(DATE(PORTADA!$B$2,2,19))<>19,"",SUMIFS(MOVIMIENTOS!$F:$F,MOVIMIENTOS!$A:$A,DATE(PORTADA!$B$2,2,19),MOVIMIENTOS!$C:$C,Z$4)) | AA23: =IF(DAY(DATE(PORTADA!$B$2,2,19))<>19,"",SUM(T23:Z23))
A24: CASA | B24: COMIDA PERSONAL | C24: =CATEGORIAS!$E$18 | D24: =SUMIFS(MOVIMIENTOS!$F:$F,MOVIMIENTOS!$A:$A,">="&DATE(PORTADA!$B$2,2,1),MOVIMIENTOS!$A:$A,"<="&EOMONTH(DATE(PORTADA!$B$2,2,1),0),MOVIMIENTOS!$D:$D,$B24) | E24: =C24-D24 | F24: =IFERROR(D24/C24,"") | S24: =IF(DAY(DATE(PORTADA!$B$2,2,20))<>20,"",20) | T24: =IF(DAY(DATE(PORTADA!$B$2,2,20))<>20,"",SUMIFS(MOVIMIENTOS!$F:$F,MOVIMIENTOS!$A:$A,DATE(PORTADA!$B$2,2,20),MOVIMIENTOS!$C:$C,T$4)) | U24: =IF(DAY(DATE(PORTADA!$B$2,2,20))<>20,"",SUMIFS(MOVIMIENTOS!$F:$F,MOVIMIENTOS!$A:$A,DATE(PORTADA!$B$2,2,20),MOVIMIENTOS!$C:$C,U$4)) | V24: =IF(DAY(DATE(PORTADA!$B$2,2,20))<>20,"",SUMIFS(MOVIMIENTOS!$F:$F,MOVIMIENTOS!$A:$A,DATE(PORTADA!$B$2,2,20),MOVIMIENTOS!$C:$C,V$4)) | W24: =IF(DAY(DATE(PORTADA!$B$2,2,20))<>20,"",SUMIFS(MOVIMIENTOS!$F:$F,MOVIMIENTOS!$A:$A,DATE(PORTADA!$B$2,2,20),MOVIMIENTOS!$C:$C,W$4)) | X24: =IF(DAY(DATE(PORTADA!$B$2,2,20))<>20,"",SUMIFS(MOVIMIENTOS!$F:$F,MOVIMIENTOS!$A:$A,DATE(PORTADA!$B$2,2,20),MOVIMIENTOS!$C:$C,X$4)) | Y24: =IF(DAY(DATE(PORTADA!$B$2,2,20))<>20,"",SUMIFS(MOVIMIENTOS!$F:$F,MOVIMIENTOS!$A:$A,DATE(PORTADA!$B$2,2,20),MOVIMIENTOS!$C:$C,Y$4)) | Z24: =IF(DAY(DATE(PORTADA!$B$2,2,20))<>20,"",SUMIFS(MOVIMIENTOS!$F:$F,MOVIMIENTOS!$A:$A,DATE(PORTADA!$B$2,2,20),MOVIMIENTOS!$C:$C,Z$4)) | AA24: =IF(DAY(DATE(PORTADA!$B$2,2,20))<>20,"",SUM(T24:Z24))
A25: CASA | B25: CUENTAS | C25: =CATEGORIAS!$E$19 | D25: =SUMIFS(MOVIMIENTOS!$F:$F,MOVIMIENTOS!$A:$A,">="&DATE(PORTADA!$B$2,2,1),MOVIMIENTOS!$A:$A,"<="&EOMONTH(DATE(PORTADA!$B$2,2,1),0),MOVIMIENTOS!$D:$D,$B25) | E25: =C25-D25 | F25: =IFERROR(D25/C25,"") | S25: =IF(DAY(DATE(PORTADA!$B$2,2,21))<>21,"",21) | T25: =IF(DAY(DATE(PORTADA!$B$2,2,21))<>21,"",SUMIFS(MOVIMIENTOS!$F:$F,MOVIMIENTOS!$A:$A,DATE(PORTADA!$B$2,2,21),MOVIMIENTOS!$C:$C,T$4)) | U25: =IF(DAY(DATE(PORTADA!$B$2,2,21))<>21,"",SUMIFS(MOVIMIENTOS!$F:$F,MOVIMIENTOS!$A:$A,DATE(PORTADA!$B$2,2,21),MOVIMIENTOS!$C:$C,U$4)) | V25: =IF(DAY(DATE(PORTADA!$B$2,2,21))<>21,"",SUMIFS(MOVIMIENTOS!$F:$F,MOVIMIENTOS!$A:$A,DATE(PORTADA!$B$2,2,21),MOVIMIENTOS!$C:$C,V$4)) | W25: =IF(DAY(DATE(PORTADA!$B$2,2,21))<>21,"",SUMIFS(MOVIMIENTOS!$F:$F,MOVIMIENTOS!$A:$A,DATE(PORTADA!$B$2,2,21),MOVIMIENTOS!$C:$C,W$4)) | X25: =IF(DAY(DATE(PORTADA!$B$2,2,21))<>21,"",SUMIFS(MOVIMIENTOS!$F:$F,MOVIMIENTOS!$A:$A,DATE(PORTADA!$B$2,2,21),MOVIMIENTOS!$C:$C,X$4)) | Y25: =IF(DAY(DATE(PORTADA!$B$2,2,21))<>21,"",SUMIFS(MOVIMIENTOS!$F:$F,MOVIMIENTOS!$A:$A,DATE(PORTADA!$B$2,2,21),MOVIMIENTOS!$C:$C,Y$4)) | Z25: =IF(DAY(DATE(PORTADA!$B$2,2,21))<>21,"",SUMIFS(MOVIMIENTOS!$F:$F,MOVIMIENTOS!$A:$A,DATE(PORTADA!$B$2,2,21),MOVIMIENTOS!$C:$C,Z$4)) | AA25: =IF(DAY(DATE(PORTADA!$B$2,2,21))<>21,"",SUM(T25:Z25))
A26: SALUD | B26: MEDICAMENTOS | C26: =CATEGORIAS!$E$20 | D26: =SUMIFS(MOVIMIENTOS!$F:$F,MOVIMIENTOS!$A:$A,">="&DATE(PORTADA!$B$2,2,1),MOVIMIENTOS!$A:$A,"<="&EOMONTH(DATE(PORTADA!$B$2,2,1),0),MOVIMIENTOS!$D:$D,$B26) | E26: =C26-D26 | F26: =IFERROR(D26/C26,"") | S26: =IF(DAY(DATE(PORTADA!$B$2,2,22))<>22,"",22) | T26: =IF(DAY(DATE(PORTADA!$B$2,2,22))<>22,"",SUMIFS(MOVIMIENTOS!$F:$F,MOVIMIENTOS!$A:$A,DATE(PORTADA!$B$2,2,22),MOVIMIENTOS!$C:$C,T$4)) | U26: =IF(DAY(DATE(PORTADA!$B$2,2,22))<>22,"",SUMIFS(MOVIMIENTOS!$F:$F,MOVIMIENTOS!$A:$A,DATE(PORTADA!$B$2,2,22),MOVIMIENTOS!$C:$C,U$4)) | V26: =IF(DAY(DATE(PORTADA!$B$2,2,22))<>22,"",SUMIFS(MOVIMIENTOS!$F:$F,MOVIMIENTOS!$A:$A,DATE(PORTADA!$B$2,2,22),MOVIMIENTOS!$C:$C,V$4)) | W26: =IF(DAY(DATE(PORTADA!$B$2,2,22))<>22,"",SUMIFS(MOVIMIENTOS!$F:$F,MOVIMIENTOS!$A:$A,DATE(PORTADA!$B$2,2,22),MOVIMIENTOS!$C:$C,W$4)) | X26: =IF(DAY(DATE(PORTADA!$B$2,2,22))<>22,"",SUMIFS(MOVIMIENTOS!$F:$F,MOVIMIENTOS!$A:$A,DATE(PORTADA!$B$2,2,22),MOVIMIENTOS!$C:$C,X$4)) | Y26: =IF(DAY(DATE(PORTADA!$B$2,2,22))<>22,"",SUMIFS(MOVIMIENTOS!$F:$F,MOVIMIENTOS!$A:$A,DATE(PORTADA!$B$2,2,22),MOVIMIENTOS!$C:$C,Y$4)) | Z26: =IF(DAY(DATE(PORTADA!$B$2,2,22))<>22,"",SUMIFS(MOVIMIENTOS!$F:$F,MOVIMIENTOS!$A:$A,DATE(PORTADA!$B$2,2,22),MOVIMIENTOS!$C:$C,Z$4)) | AA26: =IF(DAY(DATE(PORTADA!$B$2,2,22))<>22,"",SUM(T26:Z26))
A27: SALUD | B27: ROPA | C27: =CATEGORIAS!$E$21 | D27: =SUMIFS(MOVIMIENTOS!$F:$F,MOVIMIENTOS!$A:$A,">="&DATE(PORTADA!$B$2,2,1),MOVIMIENTOS!$A:$A,"<="&EOMONTH(DATE(PORTADA!$B$2,2,1),0),MOVIMIENTOS!$D:$D,$B27) | E27: =C27-D27 | F27: =IFERROR(D27/C27,"") | S27: =IF(DAY(DATE(PORTADA!$B$2,2,23))<>23,"",23) | T27: =IF(DAY(DATE(PORTADA!$B$2,2,23))<>23,"",SUMIFS(MOVIMIENTOS!$F:$F,MOVIMIENTOS!$A:$A,DATE(PORTADA!$B$2,2,23),MOVIMIENTOS!$C:$C,T$4)) | U27: =IF(DAY(DATE(PORTADA!$B$2,2,23))<>23,"",SUMIFS(MOVIMIENTOS!$F:$F,MOVIMIENTOS!$A:$A,DATE(PORTADA!$B$2,2,23),MOVIMIENTOS!$C:$C,U$4)) | V27: =IF(DAY(DATE(PORTADA!$B$2,2,23))<>23,"",SUMIFS(MOVIMIENTOS!$F:$F,MOVIMIENTOS!$A:$A,DATE(PORTADA!$B$2,2,23),MOVIMIENTOS!$C:$C,V$4)) | W27: =IF(DAY(DATE(PORTADA!$B$2,2,23))<>23,"",SUMIFS(MOVIMIENTOS!$F:$F,MOVIMIENTOS!$A:$A,DATE(PORTADA!$B$2,2,23),MOVIMIENTOS!$C:$C,W$4)) | X27: =IF(DAY(DATE(PORTADA!$B$2,2,23))<>23,"",SUMIFS(MOVIMIENTOS!$F:$F,MOVIMIENTOS!$A:$A,DATE(PORTADA!$B$2,2,23),MOVIMIENTOS!$C:$C,X$4)) | Y27: =IF(DAY(DATE(PORTADA!$B$2,2,23))<>23,"",SUMIFS(MOVIMIENTOS!$F:$F,MOVIMIENTOS!$A:$A,DATE(PORTADA!$B$2,2,23),MOVIMIENTOS!$C:$C,Y$4)) | Z27: =IF(DAY(DATE(PORTADA!$B$2,2,23))<>23,"",SUMIFS(MOVIMIENTOS!$F:$F,MOVIMIENTOS!$A:$A,DATE(PORTADA!$B$2,2,23),MOVIMIENTOS!$C:$C,Z$4)) | AA27: =IF(DAY(DATE(PORTADA!$B$2,2,23))<>23,"",SUM(T27:Z27))
A28: SALUD | B28: DEPORTE | C28: =CATEGORIAS!$E$22 | D28: =SUMIFS(MOVIMIENTOS!$F:$F,MOVIMIENTOS!$A:$A,">="&DATE(PORTADA!$B$2,2,1),MOVIMIENTOS!$A:$A,"<="&EOMONTH(DATE(PORTADA!$B$2,2,1),0),MOVIMIENTOS!$D:$D,$B28) | E28: =C28-D28 | F28: =IFERROR(D28/C28,"") | S28: =IF(DAY(DATE(PORTADA!$B$2,2,24))<>24,"",24) | T28: =IF(DAY(DATE(PORTADA!$B$2,2,24))<>24,"",SUMIFS(MOVIMIENTOS!$F:$F,MOVIMIENTOS!$A:$A,DATE(PORTADA!$B$2,2,24),MOVIMIENTOS!$C:$C,T$4)) | U28: =IF(DAY(DATE(PORTADA!$B$2,2,24))<>24,"",SUMIFS(MOVIMIENTOS!$F:$F,MOVIMIENTOS!$A:$A,DATE(PORTADA!$B$2,2,24),MOVIMIENTOS!$C:$C,U$4)) | V28: =IF(DAY(DATE(PORTADA!$B$2,2,24))<>24,"",SUMIFS(MOVIMIENTOS!$F:$F,MOVIMIENTOS!$A:$A,DATE(PORTADA!$B$2,2,24),MOVIMIENTOS!$C:$C,V$4)) | W28: =IF(DAY(DATE(PORTADA!$B$2,2,24))<>24,"",SUMIFS(MOVIMIENTOS!$F:$F,MOVIMIENTOS!$A:$A,DATE(PORTADA!$B$2,2,24),MOVIMIENTOS!$C:$C,W$4)) | X28: =IF(DAY(DATE(PORTADA!$B$2,2,24))<>24,"",SUMIFS(MOVIMIENTOS!$F:$F,MOVIMIENTOS!$A:$A,DATE(PORTADA!$B$2,2,24),MOVIMIENTOS!$C:$C,X$4)) | Y28: =IF(DAY(DATE(PORTADA!$B$2,2,24))<>24,"",SUMIFS(MOVIMIENTOS!$F:$F,MOVIMIENTOS!$A:$A,DATE(PORTADA!$B$2,2,24),MOVIMIENTOS!$C:$C,Y$4)) | Z28: =IF(DAY(DATE(PORTADA!$B$2,2,24))<>24,"",SUMIFS(MOVIMIENTOS!$F:$F,MOVIMIENTOS!$A:$A,DATE(PORTADA!$B$2,2,24),MOVIMIENTOS!$C:$C,Z$4)) | AA28: =IF(DAY(DATE(PORTADA!$B$2,2,24))<>24,"",SUM(T28:Z28))
A29: AUTO | B29: BENCINA | C29: =CATEGORIAS!$E$23 | D29: =SUMIFS(MOVIMIENTOS!$F:$F,MOVIMIENTOS!$A:$A,">="&DATE(PORTADA!$B$2,2,1),MOVIMIENTOS!$A:$A,"<="&EOMONTH(DATE(PORTADA!$B$2,2,1),0),MOVIMIENTOS!$D:$D,$B29) | E29: =C29-D29 | F29: =IFERROR(D29/C29,"") | S29: =IF(DAY(DATE(PORTADA!$B$2,2,25))<>25,"",25) | T29: =IF(DAY(DATE(PORTADA!$B$2,2,25))<>25,"",SUMIFS(MOVIMIENTOS!$F:$F,MOVIMIENTOS!$A:$A,DATE(PORTADA!$B$2,2,25),MOVIMIENTOS!$C:$C,T$4)) | U29: =IF(DAY(DATE(PORTADA!$B$2,2,25))<>25,"",SUMIFS(MOVIMIENTOS!$F:$F,MOVIMIENTOS!$A:$A,DATE(PORTADA!$B$2,2,25),MOVIMIENTOS!$C:$C,U$4)) | V29: =IF(DAY(DATE(PORTADA!$B$2,2,25))<>25,"",SUMIFS(MOVIMIENTOS!$F:$F,MOVIMIENTOS!$A:$A,DATE(PORTADA!$B$2,2,25),MOVIMIENTOS!$C:$C,V$4)) | W29: =IF(DAY(DATE(PORTADA!$B$2,2,25))<>25,"",SUMIFS(MOVIMIENTOS!$F:$F,MOVIMIENTOS!$A:$A,DATE(PORTADA!$B$2,2,25),MOVIMIENTOS!$C:$C,W$4)) | X29: =IF(DAY(DATE(PORTADA!$B$2,2,25))<>25,"",SUMIFS(MOVIMIENTOS!$F:$F,MOVIMIENTOS!$A:$A,DATE(PORTADA!$B$2,2,25),MOVIMIENTOS!$C:$C,X$4)) | Y29: =IF(DAY(DATE(PORTADA!$B$2,2,25))<>25,"",SUMIFS(MOVIMIENTOS!$F:$F,MOVIMIENTOS!$A:$A,DATE(PORTADA!$B$2,2,25),MOVIMIENTOS!$C:$C,Y$4)) | Z29: =IF(DAY(DATE(PORTADA!$B$2,2,25))<>25,"",SUMIFS(MOVIMIENTOS!$F:$F,MOVIMIENTOS!$A:$A,DATE(PORTADA!$B$2,2,25),MOVIMIENTOS!$C:$C,Z$4)) | AA29: =IF(DAY(DATE(PORTADA!$B$2,2,25))<>25,"",SUM(T29:Z29))
A30: AUTO | B30: OTROS | C30: =CATEGORIAS!$E$24 | D30: =SUMIFS(MOVIMIENTOS!$F:$F,MOVIMIENTOS!$A:$A,">="&DATE(PORTADA!$B$2,2,1),MOVIMIENTOS!$A:$A,"<="&EOMONTH(DATE(PORTADA!$B$2,2,1),0),MOVIMIENTOS!$D:$D,$B30) | E30: =C30-D30 | F30: =IFERROR(D30/C30,"") | S30: =IF(DAY(DATE(PORTADA!$B$2,2,26))<>26,"",26) | T30: =IF(DAY(DATE(PORTADA!$B$2,2,26))<>26,"",SUMIFS(MOVIMIENTOS!$F:$F,MOVIMIENTOS!$A:$A,DATE(PORTADA!$B$2,2,26),MOVIMIENTOS!$C:$C,T$4)) | U30: =IF(DAY(DATE(PORTADA!$B$2,2,26))<>26,"",SUMIFS(MOVIMIENTOS!$F:$F,MOVIMIENTOS!$A:$A,DATE(PORTADA!$B$2,2,26),MOVIMIENTOS!$C:$C,U$4)) | V30: =IF(DAY(DATE(PORTADA!$B$2,2,26))<>26,"",SUMIFS(MOVIMIENTOS!$F:$F,MOVIMIENTOS!$A:$A,DATE(PORTADA!$B$2,2,26),MOVIMIENTOS!$C:$C,V$4)) | W30: =IF(DAY(DATE(PORTADA!$B$2,2,26))<>26,"",SUMIFS(MOVIMIENTOS!$F:$F,MOVIMIENTOS!$A:$A,DATE(PORTADA!$B$2,2,26),MOVIMIENTOS!$C:$C,W$4)) | X30: =IF(DAY(DATE(PORTADA!$B$2,2,26))<>26,"",SUMIFS(MOVIMIENTOS!$F:$F,MOVIMIENTOS!$A:$A,DATE(PORTADA!$B$2,2,26),MOVIMIENTOS!$C:$C,X$4)) | Y30: =IF(DAY(DATE(PORTADA!$B$2,2,26))<>26,"",SUMIFS(MOVIMIENTOS!$F:$F,MOVIMIENTOS!$A:$A,DATE(PORTADA!$B$2,2,26),MOVIMIENTOS!$C:$C,Y$4)) | Z30: =IF(DAY(DATE(PORTADA!$B$2,2,26))<>26,"",SUMIFS(MOVIMIENTOS!$F:$F,MOVIMIENTOS!$A:$A,DATE(PORTADA!$B$2,2,26),MOVIMIENTOS!$C:$C,Z$4)) | AA30: =IF(DAY(DATE(PORTADA!$B$2,2,26))<>26,"",SUM(T30:Z30))
A31: DIVERSION | B31: COPETE | C31: =CATEGORIAS!$E$25 | D31: =SUMIFS(MOVIMIENTOS!$F:$F,MOVIMIENTOS!$A:$A,">="&DATE(PORTADA!$B$2,2,1),MOVIMIENTOS!$A:$A,"<="&EOMONTH(DATE(PORTADA!$B$2,2,1),0),MOVIMIENTOS!$D:$D,$B31) | E31: =C31-D31 | F31: =IFERROR(D31/C31,"") | S31: =IF(DAY(DATE(PORTADA!$B$2,2,27))<>27,"",27) | T31: =IF(DAY(DATE(PORTADA!$B$2,2,27))<>27,"",SUMIFS(MOVIMIENTOS!$F:$F,MOVIMIENTOS!$A:$A,DATE(PORTADA!$B$2,2,27),MOVIMIENTOS!$C:$C,T$4)) | U31: =IF(DAY(DATE(PORTADA!$B$2,2,27))<>27,"",SUMIFS(MOVIMIENTOS!$F:$F,MOVIMIENTOS!$A:$A,DATE(PORTADA!$B$2,2,27),MOVIMIENTOS!$C:$C,U$4)) | V31: =IF(DAY(DATE(PORTADA!$B$2,2,27))<>27,"",SUMIFS(MOVIMIENTOS!$F:$F,MOVIMIENTOS!$A:$A,DATE(PORTADA!$B$2,2,27),MOVIMIENTOS!$C:$C,V$4)) | W31: =IF(DAY(DATE(PORTADA!$B$2,2,27))<>27,"",SUMIFS(MOVIMIENTOS!$F:$F,MOVIMIENTOS!$A:$A,DATE(PORTADA!$B$2,2,27),MOVIMIENTOS!$C:$C,W$4)) | X31: =IF(DAY(DATE(PORTADA!$B$2,2,27))<>27,"",SUMIFS(MOVIMIENTOS!$F:$F,MOVIMIENTOS!$A:$A,DATE(PORTADA!$B$2,2,27),MOVIMIENTOS!$C:$C,X$4)) | Y31: =IF(DAY(DATE(PORTADA!$B$2,2,27))<>27,"",SUMIFS(MOVIMIENTOS!$F:$F,MOVIMIENTOS!$A:$A,DATE(PORTADA!$B$2,2,27),MOVIMIENTOS!$C:$C,Y$4)) | Z31: =IF(DAY(DATE(PORTADA!$B$2,2,27))<>27,"",SUMIFS(MOVIMIENTOS!$F:$F,MOVIMIENTOS!$A:$A,DATE(PORTADA!$B$2,2,27),MOVIMIENTOS!$C:$C,Z$4)) | AA31: =IF(DAY(DATE(PORTADA!$B$2,2,27))<>27,"",SUM(T31:Z31))
A32: DIVERSION | B32: WEED | C32: =CATEGORIAS!$E$26 | D32: =SUMIFS(MOVIMIENTOS!$F:$F,MOVIMIENTOS!$A:$A,">="&DATE(PORTADA!$B$2,2,1),MOVIMIENTOS!$A:$A,"<="&EOMONTH(DATE(PORTADA!$B$2,2,1),0),MOVIMIENTOS!$D:$D,$B32) | E32: =C32-D32 | F32: =IFERROR(D32/C32,"") | S32: =IF(DAY(DATE(PORTADA!$B$2,2,28))<>28,"",28) | T32: =IF(DAY(DATE(PORTADA!$B$2,2,28))<>28,"",SUMIFS(MOVIMIENTOS!$F:$F,MOVIMIENTOS!$A:$A,DATE(PORTADA!$B$2,2,28),MOVIMIENTOS!$C:$C,T$4)) | U32: =IF(DAY(DATE(PORTADA!$B$2,2,28))<>28,"",SUMIFS(MOVIMIENTOS!$F:$F,MOVIMIENTOS!$A:$A,DATE(PORTADA!$B$2,2,28),MOVIMIENTOS!$C:$C,U$4)) | V32: =IF(DAY(DATE(PORTADA!$B$2,2,28))<>28,"",SUMIFS(MOVIMIENTOS!$F:$F,MOVIMIENTOS!$A:$A,DATE(PORTADA!$B$2,2,28),MOVIMIENTOS!$C:$C,V$4)) | W32: =IF(DAY(DATE(PORTADA!$B$2,2,28))<>28,"",SUMIFS(MOVIMIENTOS!$F:$F,MOVIMIENTOS!$A:$A,DATE(PORTADA!$B$2,2,28),MOVIMIENTOS!$C:$C,W$4)) | X32: =IF(DAY(DATE(PORTADA!$B$2,2,28))<>28,"",SUMIFS(MOVIMIENTOS!$F:$F,MOVIMIENTOS!$A:$A,DATE(PORTADA!$B$2,2,28),MOVIMIENTOS!$C:$C,X$4)) | Y32: =IF(DAY(DATE(PORTADA!$B$2,2,28))<>28,"",SUMIFS(MOVIMIENTOS!$F:$F,MOVIMIENTOS!$A:$A,DATE(PORTADA!$B$2,2,28),MOVIMIENTOS!$C:$C,Y$4)) | Z32: =IF(DAY(DATE(PORTADA!$B$2,2,28))<>28,"",SUMIFS(MOVIMIENTOS!$F:$F,MOVIMIENTOS!$A:$A,DATE(PORTADA!$B$2,2,28),MOVIMIENTOS!$C:$C,Z$4)) | AA32: =IF(DAY(DATE(PORTADA!$B$2,2,28))<>28,"",SUM(T32:Z32))
A33: DIVERSION | B33: CARCASA CELULAR | C33: =CATEGORIAS!$E$27 | D33: =SUMIFS(MOVIMIENTOS!$F:$F,MOVIMIENTOS!$A:$A,">="&DATE(PORTADA!$B$2,2,1),MOVIMIENTOS!$A:$A,"<="&EOMONTH(DATE(PORTADA!$B$2,2,1),0),MOVIMIENTOS!$D:$D,$B33) | E33: =C33-D33 | F33: =IFERROR(D33/C33,"") | S33: =IF(DAY(DATE(PORTADA!$B$2,2,29))<>29,"",29) | T33: =IF(DAY(DATE(PORTADA!$B$2,2,29))<>29,"",SUMIFS(MOVIMIENTOS!$F:$F,MOVIMIENTOS!$A:$A,DATE(PORTADA!$B$2,2,29),MOVIMIENTOS!$C:$C,T$4)) | U33: =IF(DAY(DATE(PORTADA!$B$2,2,29))<>29,"",SUMIFS(MOVIMIENTOS!$F:$F,MOVIMIENTOS!$A:$A,DATE(PORTADA!$B$2,2,29),MOVIMIENTOS!$C:$C,U$4)) | V33: =IF(DAY(DATE(PORTADA!$B$2,2,29))<>29,"",SUMIFS(MOVIMIENTOS!$F:$F,MOVIMIENTOS!$A:$A,DATE(PORTADA!$B$2,2,29),MOVIMIENTOS!$C:$C,V$4)) | W33: =IF(DAY(DATE(PORTADA!$B$2,2,29))<>29,"",SUMIFS(MOVIMIENTOS!$F:$F,MOVIMIENTOS!$A:$A,DATE(PORTADA!$B$2,2,29),MOVIMIENTOS!$C:$C,W$4)) | X33: =IF(DAY(DATE(PORTADA!$B$2,2,29))<>29,"",SUMIFS(MOVIMIENTOS!$F:$F,MOVIMIENTOS!$A:$A,DATE(PORTADA!$B$2,2,29),MOVIMIENTOS!$C:$C,X$4)) | Y33: =IF(DAY(DATE(PORTADA!$B$2,2,29))<>29,"",SUMIFS(MOVIMIENTOS!$F:$F,MOVIMIENTOS!$A:$A,DATE(PORTADA!$B$2,2,29),MOVIMIENTOS!$C:$C,Y$4)) | Z33: =IF(DAY(DATE(PORTADA!$B$2,2,29))<>29,"",SUMIFS(MOVIMIENTOS!$F:$F,MOVIMIENTOS!$A:$A,DATE(PORTADA!$B$2,2,29),MOVIMIENTOS!$C:$C,Z$4)) | AA33: =IF(DAY(DATE(PORTADA!$B$2,2,29))<>29,"",SUM(T33:Z33))
A34: DIVERSION | B34: SALIDA CON AMIGOS | C34: =CATEGORIAS!$E$28 | D34: =SUMIFS(MOVIMIENTOS!$F:$F,MOVIMIENTOS!$A:$A,">="&DATE(PORTADA!$B$2,2,1),MOVIMIENTOS!$A:$A,"<="&EOMONTH(DATE(PORTADA!$B$2,2,1),0),MOVIMIENTOS!$D:$D,$B34) | E34: =C34-D34 | F34: =IFERROR(D34/C34,"") | S34: =IF(DAY(DATE(PORTADA!$B$2,2,30))<>30,"",30) | T34: =IF(DAY(DATE(PORTADA!$B$2,2,30))<>30,"",SUMIFS(MOVIMIENTOS!$F:$F,MOVIMIENTOS!$A:$A,DATE(PORTADA!$B$2,2,30),MOVIMIENTOS!$C:$C,T$4)) | U34: =IF(DAY(DATE(PORTADA!$B$2,2,30))<>30,"",SUMIFS(MOVIMIENTOS!$F:$F,MOVIMIENTOS!$A:$A,DATE(PORTADA!$B$2,2,30),MOVIMIENTOS!$C:$C,U$4)) | V34: =IF(DAY(DATE(PORTADA!$B$2,2,30))<>30,"",SUMIFS(MOVIMIENTOS!$F:$F,MOVIMIENTOS!$A:$A,DATE(PORTADA!$B$2,2,30),MOVIMIENTOS!$C:$C,V$4)) | W34: =IF(DAY(DATE(PORTADA!$B$2,2,30))<>30,"",SUMIFS(MOVIMIENTOS!$F:$F,MOVIMIENTOS!$A:$A,DATE(PORTADA!$B$2,2,30),MOVIMIENTOS!$C:$C,W$4)) | X34: =IF(DAY(DATE(PORTADA!$B$2,2,30))<>30,"",SUMIFS(MOVIMIENTOS!$F:$F,MOVIMIENTOS!$A:$A,DATE(PORTADA!$B$2,2,30),MOVIMIENTOS!$C:$C,X$4)) | Y34: =IF(DAY(DATE(PORTADA!$B$2,2,30))<>30,"",SUMIFS(MOVIMIENTOS!$F:$F,MOVIMIENTOS!$A:$A,DATE(PORTADA!$B$2,2,30),MOVIMIENTOS!$C:$C,Y$4)) | Z34: =IF(DAY(DATE(PORTADA!$B$2,2,30))<>30,"",SUMIFS(MOVIMIENTOS!$F:$F,MOVIMIENTOS!$A:$A,DATE(PORTADA!$B$2,2,30),MOVIMIENTOS!$C:$C,Z$4)) | AA34: =IF(DAY(DATE(PORTADA!$B$2,2,30))<>30,"",SUM(T34:Z34))
A35: OTROS | B35: CHICHES | C35: =CATEGORIAS!$E$29 | D35: =SUMIFS(MOVIMIENTOS!$F:$F,MOVIMIENTOS!$A:$A,">="&DATE(PORTADA!$B$2,2,1),MOVIMIENTOS!$A:$A,"<="&EOMONTH(DATE(PORTADA!$B$2,2,1),0),MOVIMIENTOS!$D:$D,$B35) | E35: =C35-D35 | F35: =IFERROR(D35/C35,"") | S35: =IF(DAY(DATE(PORTADA!$B$2,2,31))<>31,"",31) | T35: =IF(DAY(DATE(PORTADA!$B$2,2,31))<>31,"",SUMIFS(MOVIMIENTOS!$F:$F,MOVIMIENTOS!$A:$A,DATE(PORTADA!$B$2,2,31),MOVIMIENTOS!$C:$C,T$4)) | U35: =IF(DAY(DATE(PORTADA!$B$2,2,31))<>31,"",SUMIFS(MOVIMIENTOS!$F:$F,MOVIMIENTOS!$A:$A,DATE(PORTADA!$B$2,2,31),MOVIMIENTOS!$C:$C,U$4)) | V35: =IF(DAY(DATE(PORTADA!$B$2,2,31))<>31,"",SUMIFS(MOVIMIENTOS!$F:$F,MOVIMIENTOS!$A:$A,DATE(PORTADA!$B$2,2,31),MOVIMIENTOS!$C:$C,V$4)) | W35: =IF(DAY(DATE(PORTADA!$B$2,2,31))<>31,"",SUMIFS(MOVIMIENTOS!$F:$F,MOVIMIENTOS!$A:$A,DATE(PORTADA!$B$2,2,31),MOVIMIENTOS!$C:$C,W$4)) | X35: =IF(DAY(DATE(PORTADA!$B$2,2,31))<>31,"",SUMIFS(MOVIMIENTOS!$F:$F,MOVIMIENTOS!$A:$A,DATE(PORTADA!$B$2,2,31),MOVIMIENTOS!$C:$C,X$4)) | Y35: =IF(DAY(DATE(PORTADA!$B$2,2,31))<>31,"",SUMIFS(MOVIMIENTOS!$F:$F,MOVIMIENTOS!$A:$A,DATE(PORTADA!$B$2,2,31),MOVIMIENTOS!$C:$C,Y$4)) | Z35: =IF(DAY(DATE(PORTADA!$B$2,2,31))<>31,"",SUMIFS(MOVIMIENTOS!$F:$F,MOVIMIENTOS!$A:$A,DATE(PORTADA!$B$2,2,31),MOVIMIENTOS!$C:$C,Z$4)) | AA35: =IF(DAY(DATE(PORTADA!$B$2,2,31))<>31,"",SUM(T35:Z35))
A36: OTROS | B36: DONACIONES | C36: =CATEGORIAS!$E$30 | D36: =SUMIFS(MOVIMIENTOS!$F:$F,MOVIMIENTOS!$A:$A,">="&DATE(PORTADA!$B$2,2,1),MOVIMIENTOS!$A:$A,"<="&EOMONTH(DATE(PORTADA!$B$2,2,1),0),MOVIMIENTOS!$D:$D,$B36) | E36: =C36-D36 | F36: =IFERROR(D36/C36,"") | S36: MES | T36: =SUM(T5:T35) | U36: =SUM(U5:U35) | V36: =SUM(V5:V35) | W36: =SUM(W5:W35) | X36: =SUM(X5:X35) | Y36: =SUM(Y5:Y35) | Z36: =SUM(Z5:Z35) | AA36: =SUM(AA5:AA35)
A37: OTROS | B37: PRESTAMOS | C37: =CATEGORIAS!$E$31 | D37: =SUMIFS(MOVIMIENTOS!$F:$F,MOVIMIENTOS!$A:$A,">="&DATE(PORTADA!$B$2,2,1),MOVIMIENTOS!$A:$A,"<="&EOMONTH(DATE(PORTADA!$B$2,2,1),0),MOVIMIENTOS!$D:$D,$B37) | E37: =C37-D37 | F37: =IFERROR(D37/C37,"")
A38: OTROS | B38: LOCOMOCION | C38: =CATEGORIAS!$E$32 | D38: =SUMIFS(MOVIMIENTOS!$F:$F,MOVIMIENTOS!$A:$A,">="&DATE(PORTADA!$B$2,2,1),MOVIMIENTOS!$A:$A,"<="&EOMONTH(DATE(PORTADA!$B$2,2,1),0),MOVIMIENTOS!$D:$D,$B38) | E38: =C38-D38 | F38: =IFERROR(D38/C38,"")
A39: OTROS | B39: OTROS GASTOS | C39: =CATEGORIAS!$E$33 | D39: =SUMIFS(MOVIMIENTOS!$F:$F,MOVIMIENTOS!$A:$A,">="&DATE(PORTADA!$B$2,2,1),MOVIMIENTOS!$A:$A,"<="&EOMONTH(DATE(PORTADA!$B$2,2,1),0),MOVIMIENTOS!$D:$D,$B39) | E39: =C39-D39 | F39: =IFERROR(D39/C39,"")
B40: TOTAL EGRESOS | C40: =SUM(C17:C39) | D40: =SUM(D17:D39) | E40: =SUM(E17:E39)
A42: POR GRUPO
A43: GRUPO | C43: PRESUPUESTO | D43: REAL | E43: DIFERENCIA | F43: % USADO
A44: CUENTAS PERSONALES | C44: =SUMIFS($C$17:$C$39,$A$17:$A$39,$A44) | D44: =SUMIFS($D$17:$D$39,$A$17:$A$39,$A44) | E44: =C44-D44 | F44: =IFERROR(D44/C44,"")
A45: HIJOS | C45: =SUMIFS($C$17:$C$39,$A$17:$A$39,$A45) | D45: =SUMIFS($D$17:$D$39,$A$17:$A$39,$A45) | E45: =C45-D45 | F45: =IFERROR(D45/C45,"")
A46: CASA | C46: =SUMIFS($C$17:$C$39,$A$17:$A$39,$A46) | D46: =SUMIFS($D$17:$D$39,$A$17:$A$39,$A46) | E46: =C46-D46 | F46: =IFERROR(D46/C46,"")
A47: SALUD | C47: =SUMIFS($C$17:$C$39,$A$17:$A$39,$A47) | D47: =SUMIFS($D$17:$D$39,$A$17:$A$39,$A47) | E47: =C47-D47 | F47: =IFERROR(D47/C47,"")
A48: AUTO | C48: =SUMIFS($C$17:$C$39,$A$17:$A$39,$A48) | D48: =SUMIFS($D$17:$D$39,$A$17:$A$39,$A48) | E48: =C48-D48 | F48: =IFERROR(D48/C48,"")
A49: DIVERSION | C49: =SUMIFS($C$17:$C$39,$A$17:$A$39,$A49) | D49: =SUMIFS($D$17:$D$39,$A$17:$A$39,$A49) | E49: =C49-D49 | F49: =IFERROR(D49/C49,"")
A50: OTROS | C50: =SUMIFS($C$17:$C$39,$A$17:$A$39,$A50) | D50: =SUMIFS($D$17:$D$39,$A$17:$A$39,$A50) | E50: =C50-D50 | F50: =IFERROR(D50/C50,"")
A52: SALDO DEL MES
B53: Ingresos menos egresos | C53: =C13-C40 | D53: =D13-D40
B54: Solo gasto | C54: =SUMIFS(CATEGORIAS!$E:$E,CATEGORIAS!$D:$D,"GASTO") | D54: =SUMIFS(MOVIMIENTOS!$F:$F,MOVIMIENTOS!$A:$A,">="&DATE(PORTADA!$B$2,2,1),MOVIMIENTOS!$A:$A,"<="&EOMONTH(DATE(PORTADA!$B$2,2,1),0),MOVIMIENTOS!$E:$E,"GASTO")
B55: Ahorro | C55: =SUMIFS(CATEGORIAS!$E:$E,CATEGORIAS!$D:$D,"AHORRO") | D55: =SUMIFS(MOVIMIENTOS!$F:$F,MOVIMIENTOS!$A:$A,">="&DATE(PORTADA!$B$2,2,1),MOVIMIENTOS!$A:$A,"<="&EOMONTH(DATE(PORTADA!$B$2,2,1),0),MOVIMIENTOS!$E:$E,"AHORRO")
B56: Deuda | C56: =SUMIFS(CATEGORIAS!$E:$E,CATEGORIAS!$D:$D,"DEUDA") | D56: =SUMIFS(MOVIMIENTOS!$F:$F,MOVIMIENTOS!$A:$A,">="&DATE(PORTADA!$B$2,2,1),MOVIMIENTOS!$A:$A,"<="&EOMONTH(DATE(PORTADA!$B$2,2,1),0),MOVIMIENTOS!$E:$E,"DEUDA")

Sheet MARZO
A1: MARZO · ingresos y egresos
A2: =CONCATENATE("Año ",PORTADA!$B$2," · verde = lo escribes tú · azul = se calcula solo")
S3: DÍA A DÍA
A4: INGRESOS | S4: DÍA | T4: CUENTAS PERSONALES | U4: HIJOS | V4: CASA | W4: SALUD | X4: AUTO | Y4: DIVERSION | Z4: OTROS | AA4: TOTAL
A5: GRUPO | B5: CATEGORÍA | C5: PRESUPUESTO | D5: REAL | E5: DIFERENCIA | F5: % LOGRO | S5: =IF(DAY(DATE(PORTADA!$B$2,3,1))<>1,"",1) | T5: =IF(DAY(DATE(PORTADA!$B$2,3,1))<>1,"",SUMIFS(MOVIMIENTOS!$F:$F,MOVIMIENTOS!$A:$A,DATE(PORTADA!$B$2,3,1),MOVIMIENTOS!$C:$C,T$4)) | U5: =IF(DAY(DATE(PORTADA!$B$2,3,1))<>1,"",SUMIFS(MOVIMIENTOS!$F:$F,MOVIMIENTOS!$A:$A,DATE(PORTADA!$B$2,3,1),MOVIMIENTOS!$C:$C,U$4)) | V5: =IF(DAY(DATE(PORTADA!$B$2,3,1))<>1,"",SUMIFS(MOVIMIENTOS!$F:$F,MOVIMIENTOS!$A:$A,DATE(PORTADA!$B$2,3,1),MOVIMIENTOS!$C:$C,V$4)) | W5: =IF(DAY(DATE(PORTADA!$B$2,3,1))<>1,"",SUMIFS(MOVIMIENTOS!$F:$F,MOVIMIENTOS!$A:$A,DATE(PORTADA!$B$2,3,1),MOVIMIENTOS!$C:$C,W$4)) | X5: =IF(DAY(DATE(PORTADA!$B$2,3,1))<>1,"",SUMIFS(MOVIMIENTOS!$F:$F,MOVIMIENTOS!$A:$A,DATE(PORTADA!$B$2,3,1),MOVIMIENTOS!$C:$C,X$4)) | Y5: =IF(DAY(DATE(PORTADA!$B$2,3,1))<>1,"",SUMIFS(MOVIMIENTOS!$F:$F,MOVIMIENTOS!$A:$A,DATE(PORTADA!$B$2,3,1),MOVIMIENTOS!$C:$C,Y$4)) | Z5: =IF(DAY(DATE(PORTADA!$B$2,3,1))<>1,"",SUMIFS(MOVIMIENTOS!$F:$F,MOVIMIENTOS!$A:$A,DATE(PORTADA!$B$2,3,1),MOVIMIENTOS!$C:$C,Z$4)) | AA5: =IF(DAY(DATE(PORTADA!$B$2,3,1))<>1,"",SUM(T5:Z5))
A6: SUELDO | B6: QUINCENA | C6: =CATEGORIAS!$E$4 | D6: =SUMIFS(MOVIMIENTOS!$F:$F,MOVIMIENTOS!$A:$A,">="&DATE(PORTADA!$B$2,3,1),MOVIMIENTOS!$A:$A,"<="&EOMONTH(DATE(PORTADA!$B$2,3,1),0),MOVIMIENTOS!$D:$D,$B6) | E6: =D6-C6 | F6: =IFERROR(D6/C6,"") | S6: =IF(DAY(DATE(PORTADA!$B$2,3,2))<>2,"",2) | T6: =IF(DAY(DATE(PORTADA!$B$2,3,2))<>2,"",SUMIFS(MOVIMIENTOS!$F:$F,MOVIMIENTOS!$A:$A,DATE(PORTADA!$B$2,3,2),MOVIMIENTOS!$C:$C,T$4)) | U6: =IF(DAY(DATE(PORTADA!$B$2,3,2))<>2,"",SUMIFS(MOVIMIENTOS!$F:$F,MOVIMIENTOS!$A:$A,DATE(PORTADA!$B$2,3,2),MOVIMIENTOS!$C:$C,U$4)) | V6: =IF(DAY(DATE(PORTADA!$B$2,3,2))<>2,"",SUMIFS(MOVIMIENTOS!$F:$F,MOVIMIENTOS!$A:$A,DATE(PORTADA!$B$2,3,2),MOVIMIENTOS!$C:$C,V$4)) | W6: =IF(DAY(DATE(PORTADA!$B$2,3,2))<>2,"",SUMIFS(MOVIMIENTOS!$F:$F,MOVIMIENTOS!$A:$A,DATE(PORTADA!$B$2,3,2),MOVIMIENTOS!$C:$C,W$4)) | X6: =IF(DAY(DATE(PORTADA!$B$2,3,2))<>2,"",SUMIFS(MOVIMIENTOS!$F:$F,MOVIMIENTOS!$A:$A,DATE(PORTADA!$B$2,3,2),MOVIMIENTOS!$C:$C,X$4)) | Y6: =IF(DAY(DATE(PORTADA!$B$2,3,2))<>2,"",SUMIFS(MOVIMIENTOS!$F:$F,MOVIMIENTOS!$A:$A,DATE(PORTADA!$B$2,3,2),MOVIMIENTOS!$C:$C,Y$4)) | Z6: =IF(DAY(DATE(PORTADA!$B$2,3,2))<>2,"",SUMIFS(MOVIMIENTOS!$F:$F,MOVIMIENTOS!$A:$A,DATE(PORTADA!$B$2,3,2),MOVIMIENTOS!$C:$C,Z$4)) | AA6: =IF(DAY(DATE(PORTADA!$B$2,3,2))<>2,"",SUM(T6:Z6))
A7: SUELDO | B7: PAGO FIN DE MES | C7: =CATEGORIAS!$E$5 | D7: =SUMIFS(MOVIMIENTOS!$F:$F,MOVIMIENTOS!$A:$A,">="&DATE(PORTADA!$B$2,3,1),MOVIMIENTOS!$A:$A,"<="&EOMONTH(DATE(PORTADA!$B$2,3,1),0),MOVIMIENTOS!$D:$D,$B7) | E7: =D7-C7 | F7: =IFERROR(D7/C7,"") | S7: =IF(DAY(DATE(PORTADA!$B$2,3,3))<>3,"",3) | T7: =IF(DAY(DATE(PORTADA!$B$2,3,3))<>3,"",SUMIFS(MOVIMIENTOS!$F:$F,MOVIMIENTOS!$A:$A,DATE(PORTADA!$B$2,3,3),MOVIMIENTOS!$C:$C,T$4)) | U7: =IF(DAY(DATE(PORTADA!$B$2,3,3))<>3,"",SUMIFS(MOVIMIENTOS!$F:$F,MOVIMIENTOS!$A:$A,DATE(PORTADA!$B$2,3,3),MOVIMIENTOS!$C:$C,U$4)) | V7: =IF(DAY(DATE(PORTADA!$B$2,3,3))<>3,"",SUMIFS(MOVIMIENTOS!$F:$F,MOVIMIENTOS!$A:$A,DATE(PORTADA!$B$2,3,3),MOVIMIENTOS!$C:$C,V$4)) | W7: =IF(DAY(DATE(PORTADA!$B$2,3,3))<>3,"",SUMIFS(MOVIMIENTOS!$F:$F,MOVIMIENTOS!$A:$A,DATE(PORTADA!$B$2,3,3),MOVIMIENTOS!$C:$C,W$4)) | X7: =IF(DAY(DATE(PORTADA!$B$2,3,3))<>3,"",SUMIFS(MOVIMIENTOS!$F:$F,MOVIMIENTOS!$A:$A,DATE(PORTADA!$B$2,3,3),MOVIMIENTOS!$C:$C,X$4)) | Y7: =IF(DAY(DATE(PORTADA!$B$2,3,3))<>3,"",SUMIFS(MOVIMIENTOS!$F:$F,MOVIMIENTOS!$A:$A,DATE(PORTADA!$B$2,3,3),MOVIMIENTOS!$C:$C,Y$4)) | Z7: =IF(DAY(DATE(PORTADA!$B$2,3,3))<>3,"",SUMIFS(MOVIMIENTOS!$F:$F,MOVIMIENTOS!$A:$A,DATE(PORTADA!$B$2,3,3),MOVIMIENTOS!$C:$C,Z$4)) | AA7: =IF(DAY(DATE(PORTADA!$B$2,3,3))<>3,"",SUM(T7:Z7))
A8: NEGOCIO | B8: EFFICIENTCHILE | C8: =CATEGORIAS!$E$6 | D8: =SUMIFS(MOVIMIENTOS!$F:$F,MOVIMIENTOS!$A:$A,">="&DATE(PORTADA!$B$2,3,1),MOVIMIENTOS!$A:$A,"<="&EOMONTH(DATE(PORTADA!$B$2,3,1),0),MOVIMIENTOS!$D:$D,$B8) | E8: =D8-C8 | F8: =IFERROR(D8/C8,"") | S8: =IF(DAY(DATE(PORTADA!$B$2,3,4))<>4,"",4) | T8: =IF(DAY(DATE(PORTADA!$B$2,3,4))<>4,"",SUMIFS(MOVIMIENTOS!$F:$F,MOVIMIENTOS!$A:$A,DATE(PORTADA!$B$2,3,4),MOVIMIENTOS!$C:$C,T$4)) | U8: =IF(DAY(DATE(PORTADA!$B$2,3,4))<>4,"",SUMIFS(MOVIMIENTOS!$F:$F,MOVIMIENTOS!$A:$A,DATE(PORTADA!$B$2,3,4),MOVIMIENTOS!$C:$C,U$4)) | V8: =IF(DAY(DATE(PORTADA!$B$2,3,4))<>4,"",SUMIFS(MOVIMIENTOS!$F:$F,MOVIMIENTOS!$A:$A,DATE(PORTADA!$B$2,3,4),MOVIMIENTOS!$C:$C,V$4)) | W8: =IF(DAY(DATE(PORTADA!$B$2,3,4))<>4,"",SUMIFS(MOVIMIENTOS!$F:$F,MOVIMIENTOS!$A:$A,DATE(PORTADA!$B$2,3,4),MOVIMIENTOS!$C:$C,W$4)) | X8: =IF(DAY(DATE(PORTADA!$B$2,3,4))<>4,"",SUMIFS(MOVIMIENTOS!$F:$F,MOVIMIENTOS!$A:$A,DATE(PORTADA!$B$2,3,4),MOVIMIENTOS!$C:$C,X$4)) | Y8: =IF(DAY(DATE(PORTADA!$B$2,3,4))<>4,"",SUMIFS(MOVIMIENTOS!$F:$F,MOVIMIENTOS!$A:$A,DATE(PORTADA!$B$2,3,4),MOVIMIENTOS!$C:$C,Y$4)) | Z8: =IF(DAY(DATE(PORTADA!$B$2,3,4))<>4,"",SUMIFS(MOVIMIENTOS!$F:$F,MOVIMIENTOS!$A:$A,DATE(PORTADA!$B$2,3,4),MOVIMIENTOS!$C:$C,Z$4)) | AA8: =IF(DAY(DATE(PORTADA!$B$2,3,4))<>4,"",SUM(T8:Z8))
A9: NEGOCIO | B9: VENTA DE ARTICULO | C9: =CATEGORIAS!$E$7 | D9: =SUMIFS(MOVIMIENTOS!$F:$F,MOVIMIENTOS!$A:$A,">="&DATE(PORTADA!$B$2,3,1),MOVIMIENTOS!$A:$A,"<="&EOMONTH(DATE(PORTADA!$B$2,3,1),0),MOVIMIENTOS!$D:$D,$B9) | E9: =D9-C9 | F9: =IFERROR(D9/C9,"") | S9: =IF(DAY(DATE(PORTADA!$B$2,3,5))<>5,"",5) | T9: =IF(DAY(DATE(PORTADA!$B$2,3,5))<>5,"",SUMIFS(MOVIMIENTOS!$F:$F,MOVIMIENTOS!$A:$A,DATE(PORTADA!$B$2,3,5),MOVIMIENTOS!$C:$C,T$4)) | U9: =IF(DAY(DATE(PORTADA!$B$2,3,5))<>5,"",SUMIFS(MOVIMIENTOS!$F:$F,MOVIMIENTOS!$A:$A,DATE(PORTADA!$B$2,3,5),MOVIMIENTOS!$C:$C,U$4)) | V9: =IF(DAY(DATE(PORTADA!$B$2,3,5))<>5,"",SUMIFS(MOVIMIENTOS!$F:$F,MOVIMIENTOS!$A:$A,DATE(PORTADA!$B$2,3,5),MOVIMIENTOS!$C:$C,V$4)) | W9: =IF(DAY(DATE(PORTADA!$B$2,3,5))<>5,"",SUMIFS(MOVIMIENTOS!$F:$F,MOVIMIENTOS!$A:$A,DATE(PORTADA!$B$2,3,5),MOVIMIENTOS!$C:$C,W$4)) | X9: =IF(DAY(DATE(PORTADA!$B$2,3,5))<>5,"",SUMIFS(MOVIMIENTOS!$F:$F,MOVIMIENTOS!$A:$A,DATE(PORTADA!$B$2,3,5),MOVIMIENTOS!$C:$C,X$4)) | Y9: =IF(DAY(DATE(PORTADA!$B$2,3,5))<>5,"",SUMIFS(MOVIMIENTOS!$F:$F,MOVIMIENTOS!$A:$A,DATE(PORTADA!$B$2,3,5),MOVIMIENTOS!$C:$C,Y$4)) | Z9: =IF(DAY(DATE(PORTADA!$B$2,3,5))<>5,"",SUMIFS(MOVIMIENTOS!$F:$F,MOVIMIENTOS!$A:$A,DATE(PORTADA!$B$2,3,5),MOVIMIENTOS!$C:$C,Z$4)) | AA9: =IF(DAY(DATE(PORTADA!$B$2,3,5))<>5,"",SUM(T9:Z9))
A10: NEGOCIO | B10: VENTA DE SERVICIO | C10: =CATEGORIAS!$E$8 | D10: =SUMIFS(MOVIMIENTOS!$F:$F,MOVIMIENTOS!$A:$A,">="&DATE(PORTADA!$B$2,3,1),MOVIMIENTOS!$A:$A,"<="&EOMONTH(DATE(PORTADA!$B$2,3,1),0),MOVIMIENTOS!$D:$D,$B10) | E10: =D10-C10 | F10: =IFERROR(D10/C10,"") | S10: =IF(DAY(DATE(PORTADA!$B$2,3,6))<>6,"",6) | T10: =IF(DAY(DATE(PORTADA!$B$2,3,6))<>6,"",SUMIFS(MOVIMIENTOS!$F:$F,MOVIMIENTOS!$A:$A,DATE(PORTADA!$B$2,3,6),MOVIMIENTOS!$C:$C,T$4)) | U10: =IF(DAY(DATE(PORTADA!$B$2,3,6))<>6,"",SUMIFS(MOVIMIENTOS!$F:$F,MOVIMIENTOS!$A:$A,DATE(PORTADA!$B$2,3,6),MOVIMIENTOS!$C:$C,U$4)) | V10: =IF(DAY(DATE(PORTADA!$B$2,3,6))<>6,"",SUMIFS(MOVIMIENTOS!$F:$F,MOVIMIENTOS!$A:$A,DATE(PORTADA!$B$2,3,6),MOVIMIENTOS!$C:$C,V$4)) | W10: =IF(DAY(DATE(PORTADA!$B$2,3,6))<>6,"",SUMIFS(MOVIMIENTOS!$F:$F,MOVIMIENTOS!$A:$A,DATE(PORTADA!$B$2,3,6),MOVIMIENTOS!$C:$C,W$4)) | X10: =IF(DAY(DATE(PORTADA!$B$2,3,6))<>6,"",SUMIFS(MOVIMIENTOS!$F:$F,MOVIMIENTOS!$A:$A,DATE(PORTADA!$B$2,3,6),MOVIMIENTOS!$C:$C,X$4)) | Y10: =IF(DAY(DATE(PORTADA!$B$2,3,6))<>6,"",SUMIFS(MOVIMIENTOS!$F:$F,MOVIMIENTOS!$A:$A,DATE(PORTADA!$B$2,3,6),MOVIMIENTOS!$C:$C,Y$4)) | Z10: =IF(DAY(DATE(PORTADA!$B$2,3,6))<>6,"",SUMIFS(MOVIMIENTOS!$F:$F,MOVIMIENTOS!$A:$A,DATE(PORTADA!$B$2,3,6),MOVIMIENTOS!$C:$C,Z$4)) | AA10: =IF(DAY(DATE(PORTADA!$B$2,3,6))<>6,"",SUM(T10:Z10))
A11: OTROS | B11: COBROS PENDIENTES | C11: =CATEGORIAS!$E$9 | D11: =SUMIFS(MOVIMIENTOS!$F:$F,MOVIMIENTOS!$A:$A,">="&DATE(PORTADA!$B$2,3,1),MOVIMIENTOS!$A:$A,"<="&EOMONTH(DATE(PORTADA!$B$2,3,1),0),MOVIMIENTOS!$D:$D,$B11) | E11: =D11-C11 | F11: =IFERROR(D11/C11,"") | S11: =IF(DAY(DATE(PORTADA!$B$2,3,7))<>7,"",7) | T11: =IF(DAY(DATE(PORTADA!$B$2,3,7))<>7,"",SUMIFS(MOVIMIENTOS!$F:$F,MOVIMIENTOS!$A:$A,DATE(PORTADA!$B$2,3,7),MOVIMIENTOS!$C:$C,T$4)) | U11: =IF(DAY(DATE(PORTADA!$B$2,3,7))<>7,"",SUMIFS(MOVIMIENTOS!$F:$F,MOVIMIENTOS!$A:$A,DATE(PORTADA!$B$2,3,7),MOVIMIENTOS!$C:$C,U$4)) | V11: =IF(DAY(DATE(PORTADA!$B$2,3,7))<>7,"",SUMIFS(MOVIMIENTOS!$F:$F,MOVIMIENTOS!$A:$A,DATE(PORTADA!$B$2,3,7),MOVIMIENTOS!$C:$C,V$4)) | W11: =IF(DAY(DATE(PORTADA!$B$2,3,7))<>7,"",SUMIFS(MOVIMIENTOS!$F:$F,MOVIMIENTOS!$A:$A,DATE(PORTADA!$B$2,3,7),MOVIMIENTOS!$C:$C,W$4)) | X11: =IF(DAY(DATE(PORTADA!$B$2,3,7))<>7,"",SUMIFS(MOVIMIENTOS!$F:$F,MOVIMIENTOS!$A:$A,DATE(PORTADA!$B$2,3,7),MOVIMIENTOS!$C:$C,X$4)) | Y11: =IF(DAY(DATE(PORTADA!$B$2,3,7))<>7,"",SUMIFS(MOVIMIENTOS!$F:$F,MOVIMIENTOS!$A:$A,DATE(PORTADA!$B$2,3,7),MOVIMIENTOS!$C:$C,Y$4)) | Z11: =IF(DAY(DATE(PORTADA!$B$2,3,7))<>7,"",SUMIFS(MOVIMIENTOS!$F:$F,MOVIMIENTOS!$A:$A,DATE(PORTADA!$B$2,3,7),MOVIMIENTOS!$C:$C,Z$4)) | AA11: =IF(DAY(DATE(PORTADA!$B$2,3,7))<>7,"",SUM(T11:Z11))
A12: OTROS | B12: OTROS INGRESOS | C12: =CATEGORIAS!$E$10 | D12: =SUMIFS(MOVIMIENTOS!$F:$F,MOVIMIENTOS!$A:$A,">="&DATE(PORTADA!$B$2,3,1),MOVIMIENTOS!$A:$A,"<="&EOMONTH(DATE(PORTADA!$B$2,3,1),0),MOVIMIENTOS!$D:$D,$B12) | E12: =D12-C12 | F12: =IFERROR(D12/C12,"") | S12: =IF(DAY(DATE(PORTADA!$B$2,3,8))<>8,"",8) | T12: =IF(DAY(DATE(PORTADA!$B$2,3,8))<>8,"",SUMIFS(MOVIMIENTOS!$F:$F,MOVIMIENTOS!$A:$A,DATE(PORTADA!$B$2,3,8),MOVIMIENTOS!$C:$C,T$4)) | U12: =IF(DAY(DATE(PORTADA!$B$2,3,8))<>8,"",SUMIFS(MOVIMIENTOS!$F:$F,MOVIMIENTOS!$A:$A,DATE(PORTADA!$B$2,3,8),MOVIMIENTOS!$C:$C,U$4)) | V12: =IF(DAY(DATE(PORTADA!$B$2,3,8))<>8,"",SUMIFS(MOVIMIENTOS!$F:$F,MOVIMIENTOS!$A:$A,DATE(PORTADA!$B$2,3,8),MOVIMIENTOS!$C:$C,V$4)) | W12: =IF(DAY(DATE(PORTADA!$B$2,3,8))<>8,"",SUMIFS(MOVIMIENTOS!$F:$F,MOVIMIENTOS!$A:$A,DATE(PORTADA!$B$2,3,8),MOVIMIENTOS!$C:$C,W$4)) | X12: =IF(DAY(DATE(PORTADA!$B$2,3,8))<>8,"",SUMIFS(MOVIMIENTOS!$F:$F,MOVIMIENTOS!$A:$A,DATE(PORTADA!$B$2,3,8),MOVIMIENTOS!$C:$C,X$4)) | Y12: =IF(DAY(DATE(PORTADA!$B$2,3,8))<>8,"",SUMIFS(MOVIMIENTOS!$F:$F,MOVIMIENTOS!$A:$A,DATE(PORTADA!$B$2,3,8),MOVIMIENTOS!$C:$C,Y$4)) | Z12: =IF(DAY(DATE(PORTADA!$B$2,3,8))<>8,"",SUMIFS(MOVIMIENTOS!$F:$F,MOVIMIENTOS!$A:$A,DATE(PORTADA!$B$2,3,8),MOVIMIENTOS!$C:$C,Z$4)) | AA12: =IF(DAY(DATE(PORTADA!$B$2,3,8))<>8,"",SUM(T12:Z12))
B13: TOTAL INGRESOS | C13: =SUM(C6:C12) | D13: =SUM(D6:D12) | E13: =SUM(E6:E12) | S13: =IF(DAY(DATE(PORTADA!$B$2,3,9))<>9,"",9) | T13: =IF(DAY(DATE(PORTADA!$B$2,3,9))<>9,"",SUMIFS(MOVIMIENTOS!$F:$F,MOVIMIENTOS!$A:$A,DATE(PORTADA!$B$2,3,9),MOVIMIENTOS!$C:$C,T$4)) | U13: =IF(DAY(DATE(PORTADA!$B$2,3,9))<>9,"",SUMIFS(MOVIMIENTOS!$F:$F,MOVIMIENTOS!$A:$A,DATE(PORTADA!$B$2,3,9),MOVIMIENTOS!$C:$C,U$4)) | V13: =IF(DAY(DATE(PORTADA!$B$2,3,9))<>9,"",SUMIFS(MOVIMIENTOS!$F:$F,MOVIMIENTOS!$A:$A,DATE(PORTADA!$B$2,3,9),MOVIMIENTOS!$C:$C,V$4)) | W13: =IF(DAY(DATE(PORTADA!$B$2,3,9))<>9,"",SUMIFS(MOVIMIENTOS!$F:$F,MOVIMIENTOS!$A:$A,DATE(PORTADA!$B$2,3,9),MOVIMIENTOS!$C:$C,W$4)) | X13: =IF(DAY(DATE(PORTADA!$B$2,3,9))<>9,"",SUMIFS(MOVIMIENTOS!$F:$F,MOVIMIENTOS!$A:$A,DATE(PORTADA!$B$2,3,9),MOVIMIENTOS!$C:$C,X$4)) | Y13: =IF(DAY(DATE(PORTADA!$B$2,3,9))<>9,"",SUMIFS(MOVIMIENTOS!$F:$F,MOVIMIENTOS!$A:$A,DATE(PORTADA!$B$2,3,9),MOVIMIENTOS!$C:$C,Y$4)) | Z13: =IF(DAY(DATE(PORTADA!$B$2,3,9))<>9,"",SUMIFS(MOVIMIENTOS!$F:$F,MOVIMIENTOS!$A:$A,DATE(PORTADA!$B$2,3,9),MOVIMIENTOS!$C:$C,Z$4)) | AA13: =IF(DAY(DATE(PORTADA!$B$2,3,9))<>9,"",SUM(T13:Z13))
S14: =IF(DAY(DATE(PORTADA!$B$2,3,10))<>10,"",10) | T14: =IF(DAY(DATE(PORTADA!$B$2,3,10))<>10,"",SUMIFS(MOVIMIENTOS!$F:$F,MOVIMIENTOS!$A:$A,DATE(PORTADA!$B$2,3,10),MOVIMIENTOS!$C:$C,T$4)) | U14: =IF(DAY(DATE(PORTADA!$B$2,3,10))<>10,"",SUMIFS(MOVIMIENTOS!$F:$F,MOVIMIENTOS!$A:$A,DATE(PORTADA!$B$2,3,10),MOVIMIENTOS!$C:$C,U$4)) | V14: =IF(DAY(DATE(PORTADA!$B$2,3,10))<>10,"",SUMIFS(MOVIMIENTOS!$F:$F,MOVIMIENTOS!$A:$A,DATE(PORTADA!$B$2,3,10),MOVIMIENTOS!$C:$C,V$4)) | W14: =IF(DAY(DATE(PORTADA!$B$2,3,10))<>10,"",SUMIFS(MOVIMIENTOS!$F:$F,MOVIMIENTOS!$A:$A,DATE(PORTADA!$B$2,3,10),MOVIMIENTOS!$C:$C,W$4)) | X14: =IF(DAY(DATE(PORTADA!$B$2,3,10))<>10,"",SUMIFS(MOVIMIENTOS!$F:$F,MOVIMIENTOS!$A:$A,DATE(PORTADA!$B$2,3,10),MOVIMIENTOS!$C:$C,X$4)) | Y14: =IF(DAY(DATE(PORTADA!$B$2,3,10))<>10,"",SUMIFS(MOVIMIENTOS!$F:$F,MOVIMIENTOS!$A:$A,DATE(PORTADA!$B$2,3,10),MOVIMIENTOS!$C:$C,Y$4)) | Z14: =IF(DAY(DATE(PORTADA!$B$2,3,10))<>10,"",SUMIFS(MOVIMIENTOS!$F:$F,MOVIMIENTOS!$A:$A,DATE(PORTADA!$B$2,3,10),MOVIMIENTOS!$C:$C,Z$4)) | AA14: =IF(DAY(DATE(PORTADA!$B$2,3,10))<>10,"",SUM(T14:Z14))
A15: EGRESOS | S15: =IF(DAY(DATE(PORTADA!$B$2,3,11))<>11,"",11) | T15: =IF(DAY(DATE(PORTADA!$B$2,3,11))<>11,"",SUMIFS(MOVIMIENTOS!$F:$F,MOVIMIENTOS!$A:$A,DATE(PORTADA!$B$2,3,11),MOVIMIENTOS!$C:$C,T$4)) | U15: =IF(DAY(DATE(PORTADA!$B$2,3,11))<>11,"",SUMIFS(MOVIMIENTOS!$F:$F,MOVIMIENTOS!$A:$A,DATE(PORTADA!$B$2,3,11),MOVIMIENTOS!$C:$C,U$4)) | V15: =IF(DAY(DATE(PORTADA!$B$2,3,11))<>11,"",SUMIFS(MOVIMIENTOS!$F:$F,MOVIMIENTOS!$A:$A,DATE(PORTADA!$B$2,3,11),MOVIMIENTOS!$C:$C,V$4)) | W15: =IF(DAY(DATE(PORTADA!$B$2,3,11))<>11,"",SUMIFS(MOVIMIENTOS!$F:$F,MOVIMIENTOS!$A:$A,DATE(PORTADA!$B$2,3,11),MOVIMIENTOS!$C:$C,W$4)) | X15: =IF(DAY(DATE(PORTADA!$B$2,3,11))<>11,"",SUMIFS(MOVIMIENTOS!$F:$F,MOVIMIENTOS!$A:$A,DATE(PORTADA!$B$2,3,11),MOVIMIENTOS!$C:$C,X$4)) | Y15: =IF(DAY(DATE(PORTADA!$B$2,3,11))<>11,"",SUMIFS(MOVIMIENTOS!$F:$F,MOVIMIENTOS!$A:$A,DATE(PORTADA!$B$2,3,11),MOVIMIENTOS!$C:$C,Y$4)) | Z15: =IF(DAY(DATE(PORTADA!$B$2,3,11))<>11,"",SUMIFS(MOVIMIENTOS!$F:$F,MOVIMIENTOS!$A:$A,DATE(PORTADA!$B$2,3,11),MOVIMIENTOS!$C:$C,Z$4)) | AA15: =IF(DAY(DATE(PORTADA!$B$2,3,11))<>11,"",SUM(T15:Z15))
A16: GRUPO | B16: CATEGORÍA | C16: PRESUPUESTO | D16: REAL | E16: DIFERENCIA | F16: % USADO | S16: =IF(DAY(DATE(PORTADA!$B$2,3,12))<>12,"",12) | T16: =IF(DAY(DATE(PORTADA!$B$2,3,12))<>12,"",SUMIFS(MOVIMIENTOS!$F:$F,MOVIMIENTOS!$A:$A,DATE(PORTADA!$B$2,3,12),MOVIMIENTOS!$C:$C,T$4)) | U16: =IF(DAY(DATE(PORTADA!$B$2,3,12))<>12,"",SUMIFS(MOVIMIENTOS!$F:$F,MOVIMIENTOS!$A:$A,DATE(PORTADA!$B$2,3,12),MOVIMIENTOS!$C:$C,U$4)) | V16: =IF(DAY(DATE(PORTADA!$B$2,3,12))<>12,"",SUMIFS(MOVIMIENTOS!$F:$F,MOVIMIENTOS!$A:$A,DATE(PORTADA!$B$2,3,12),MOVIMIENTOS!$C:$C,V$4)) | W16: =IF(DAY(DATE(PORTADA!$B$2,3,12))<>12,"",SUMIFS(MOVIMIENTOS!$F:$F,MOVIMIENTOS!$A:$A,DATE(PORTADA!$B$2,3,12),MOVIMIENTOS!$C:$C,W$4)) | X16: =IF(DAY(DATE(PORTADA!$B$2,3,12))<>12,"",SUMIFS(MOVIMIENTOS!$F:$F,MOVIMIENTOS!$A:$A,DATE(PORTADA!$B$2,3,12),MOVIMIENTOS!$C:$C,X$4)) | Y16: =IF(DAY(DATE(PORTADA!$B$2,3,12))<>12,"",SUMIFS(MOVIMIENTOS!$F:$F,MOVIMIENTOS!$A:$A,DATE(PORTADA!$B$2,3,12),MOVIMIENTOS!$C:$C,Y$4)) | Z16: =IF(DAY(DATE(PORTADA!$B$2,3,12))<>12,"",SUMIFS(MOVIMIENTOS!$F:$F,MOVIMIENTOS!$A:$A,DATE(PORTADA!$B$2,3,12),MOVIMIENTOS!$C:$C,Z$4)) | AA16: =IF(DAY(DATE(PORTADA!$B$2,3,12))<>12,"",SUM(T16:Z16))
A17: CUENTAS PERSONALES | B17: PREST. AUTO | C17: =CATEGORIAS!$E$11 | D17: =SUMIFS(MOVIMIENTOS!$F:$F,MOVIMIENTOS!$A:$A,">="&DATE(PORTADA!$B$2,3,1),MOVIMIENTOS!$A:$A,"<="&EOMONTH(DATE(PORTADA!$B$2,3,1),0),MOVIMIENTOS!$D:$D,$B17) | E17: =C17-D17 | F17: =IFERROR(D17/C17,"") | S17: =IF(DAY(DATE(PORTADA!$B$2,3,13))<>13,"",13) | T17: =IF(DAY(DATE(PORTADA!$B$2,3,13))<>13,"",SUMIFS(MOVIMIENTOS!$F:$F,MOVIMIENTOS!$A:$A,DATE(PORTADA!$B$2,3,13),MOVIMIENTOS!$C:$C,T$4)) | U17: =IF(DAY(DATE(PORTADA!$B$2,3,13))<>13,"",SUMIFS(MOVIMIENTOS!$F:$F,MOVIMIENTOS!$A:$A,DATE(PORTADA!$B$2,3,13),MOVIMIENTOS!$C:$C,U$4)) | V17: =IF(DAY(DATE(PORTADA!$B$2,3,13))<>13,"",SUMIFS(MOVIMIENTOS!$F:$F,MOVIMIENTOS!$A:$A,DATE(PORTADA!$B$2,3,13),MOVIMIENTOS!$C:$C,V$4)) | W17: =IF(DAY(DATE(PORTADA!$B$2,3,13))<>13,"",SUMIFS(MOVIMIENTOS!$F:$F,MOVIMIENTOS!$A:$A,DATE(PORTADA!$B$2,3,13),MOVIMIENTOS!$C:$C,W$4)) | X17: =IF(DAY(DATE(PORTADA!$B$2,3,13))<>13,"",SUMIFS(MOVIMIENTOS!$F:$F,MOVIMIENTOS!$A:$A,DATE(PORTADA!$B$2,3,13),MOVIMIENTOS!$C:$C,X$4)) | Y17: =IF(DAY(DATE(PORTADA!$B$2,3,13))<>13,"",SUMIFS(MOVIMIENTOS!$F:$F,MOVIMIENTOS!$A:$A,DATE(PORTADA!$B$2,3,13),MOVIMIENTOS!$C:$C,Y$4)) | Z17: =IF(DAY(DATE(PORTADA!$B$2,3,13))<>13,"",SUMIFS(MOVIMIENTOS!$F:$F,MOVIMIENTOS!$A:$A,DATE(PORTADA!$B$2,3,13),MOVIMIENTOS!$C:$C,Z$4)) | AA17: =IF(DAY(DATE(PORTADA!$B$2,3,13))<>13,"",SUM(T17:Z17))
A18: CUENTAS PERSONALES | B18: AHORRO CASA | C18: =CATEGORIAS!$E$12 | D18: =SUMIFS(MOVIMIENTOS!$F:$F,MOVIMIENTOS!$A:$A,">="&DATE(PORTADA!$B$2,3,1),MOVIMIENTOS!$A:$A,"<="&EOMONTH(DATE(PORTADA!$B$2,3,1),0),MOVIMIENTOS!$D:$D,$B18) | E18: =C18-D18 | F18: =IFERROR(D18/C18,"") | S18: =IF(DAY(DATE(PORTADA!$B$2,3,14))<>14,"",14) | T18: =IF(DAY(DATE(PORTADA!$B$2,3,14))<>14,"",SUMIFS(MOVIMIENTOS!$F:$F,MOVIMIENTOS!$A:$A,DATE(PORTADA!$B$2,3,14),MOVIMIENTOS!$C:$C,T$4)) | U18: =IF(DAY(DATE(PORTADA!$B$2,3,14))<>14,"",SUMIFS(MOVIMIENTOS!$F:$F,MOVIMIENTOS!$A:$A,DATE(PORTADA!$B$2,3,14),MOVIMIENTOS!$C:$C,U$4)) | V18: =IF(DAY(DATE(PORTADA!$B$2,3,14))<>14,"",SUMIFS(MOVIMIENTOS!$F:$F,MOVIMIENTOS!$A:$A,DATE(PORTADA!$B$2,3,14),MOVIMIENTOS!$C:$C,V$4)) | W18: =IF(DAY(DATE(PORTADA!$B$2,3,14))<>14,"",SUMIFS(MOVIMIENTOS!$F:$F,MOVIMIENTOS!$A:$A,DATE(PORTADA!$B$2,3,14),MOVIMIENTOS!$C:$C,W$4)) | X18: =IF(DAY(DATE(PORTADA!$B$2,3,14))<>14,"",SUMIFS(MOVIMIENTOS!$F:$F,MOVIMIENTOS!$A:$A,DATE(PORTADA!$B$2,3,14),MOVIMIENTOS!$C:$C,X$4)) | Y18: =IF(DAY(DATE(PORTADA!$B$2,3,14))<>14,"",SUMIFS(MOVIMIENTOS!$F:$F,MOVIMIENTOS!$A:$A,DATE(PORTADA!$B$2,3,14),MOVIMIENTOS!$C:$C,Y$4)) | Z18: =IF(DAY(DATE(PORTADA!$B$2,3,14))<>14,"",SUMIFS(MOVIMIENTOS!$F:$F,MOVIMIENTOS!$A:$A,DATE(PORTADA!$B$2,3,14),MOVIMIENTOS!$C:$C,Z$4)) | AA18: =IF(DAY(DATE(PORTADA!$B$2,3,14))<>14,"",SUM(T18:Z18))
A19: HIJOS | B19: PENSIONES | C19: =CATEGORIAS!$E$13 | D19: =SUMIFS(MOVIMIENTOS!$F:$F,MOVIMIENTOS!$A:$A,">="&DATE(PORTADA!$B$2,3,1),MOVIMIENTOS!$A:$A,"<="&EOMONTH(DATE(PORTADA!$B$2,3,1),0),MOVIMIENTOS!$D:$D,$B19) | E19: =C19-D19 | F19: =IFERROR(D19/C19,"") | S19: =IF(DAY(DATE(PORTADA!$B$2,3,15))<>15,"",15) | T19: =IF(DAY(DATE(PORTADA!$B$2,3,15))<>15,"",SUMIFS(MOVIMIENTOS!$F:$F,MOVIMIENTOS!$A:$A,DATE(PORTADA!$B$2,3,15),MOVIMIENTOS!$C:$C,T$4)) | U19: =IF(DAY(DATE(PORTADA!$B$2,3,15))<>15,"",SUMIFS(MOVIMIENTOS!$F:$F,MOVIMIENTOS!$A:$A,DATE(PORTADA!$B$2,3,15),MOVIMIENTOS!$C:$C,U$4)) | V19: =IF(DAY(DATE(PORTADA!$B$2,3,15))<>15,"",SUMIFS(MOVIMIENTOS!$F:$F,MOVIMIENTOS!$A:$A,DATE(PORTADA!$B$2,3,15),MOVIMIENTOS!$C:$C,V$4)) | W19: =IF(DAY(DATE(PORTADA!$B$2,3,15))<>15,"",SUMIFS(MOVIMIENTOS!$F:$F,MOVIMIENTOS!$A:$A,DATE(PORTADA!$B$2,3,15),MOVIMIENTOS!$C:$C,W$4)) | X19: =IF(DAY(DATE(PORTADA!$B$2,3,15))<>15,"",SUMIFS(MOVIMIENTOS!$F:$F,MOVIMIENTOS!$A:$A,DATE(PORTADA!$B$2,3,15),MOVIMIENTOS!$C:$C,X$4)) | Y19: =IF(DAY(DATE(PORTADA!$B$2,3,15))<>15,"",SUMIFS(MOVIMIENTOS!$F:$F,MOVIMIENTOS!$A:$A,DATE(PORTADA!$B$2,3,15),MOVIMIENTOS!$C:$C,Y$4)) | Z19: =IF(DAY(DATE(PORTADA!$B$2,3,15))<>15,"",SUMIFS(MOVIMIENTOS!$F:$F,MOVIMIENTOS!$A:$A,DATE(PORTADA!$B$2,3,15),MOVIMIENTOS!$C:$C,Z$4)) | AA19: =IF(DAY(DATE(PORTADA!$B$2,3,15))<>15,"",SUM(T19:Z19))
A20: HIJOS | B20: ROPA Y REGALOS | C20: =CATEGORIAS!$E$14 | D20: =SUMIFS(MOVIMIENTOS!$F:$F,MOVIMIENTOS!$A:$A,">="&DATE(PORTADA!$B$2,3,1),MOVIMIENTOS!$A:$A,"<="&EOMONTH(DATE(PORTADA!$B$2,3,1),0),MOVIMIENTOS!$D:$D,$B20) | E20: =C20-D20 | F20: =IFERROR(D20/C20,"") | S20: =IF(DAY(DATE(PORTADA!$B$2,3,16))<>16,"",16) | T20: =IF(DAY(DATE(PORTADA!$B$2,3,16))<>16,"",SUMIFS(MOVIMIENTOS!$F:$F,MOVIMIENTOS!$A:$A,DATE(PORTADA!$B$2,3,16),MOVIMIENTOS!$C:$C,T$4)) | U20: =IF(DAY(DATE(PORTADA!$B$2,3,16))<>16,"",SUMIFS(MOVIMIENTOS!$F:$F,MOVIMIENTOS!$A:$A,DATE(PORTADA!$B$2,3,16),MOVIMIENTOS!$C:$C,U$4)) | V20: =IF(DAY(DATE(PORTADA!$B$2,3,16))<>16,"",SUMIFS(MOVIMIENTOS!$F:$F,MOVIMIENTOS!$A:$A,DATE(PORTADA!$B$2,3,16),MOVIMIENTOS!$C:$C,V$4)) | W20: =IF(DAY(DATE(PORTADA!$B$2,3,16))<>16,"",SUMIFS(MOVIMIENTOS!$F:$F,MOVIMIENTOS!$A:$A,DATE(PORTADA!$B$2,3,16),MOVIMIENTOS!$C:$C,W$4)) | X20: =IF(DAY(DATE(PORTADA!$B$2,3,16))<>16,"",SUMIFS(MOVIMIENTOS!$F:$F,MOVIMIENTOS!$A:$A,DATE(PORTADA!$B$2,3,16),MOVIMIENTOS!$C:$C,X$4)) | Y20: =IF(DAY(DATE(PORTADA!$B$2,3,16))<>16,"",SUMIFS(MOVIMIENTOS!$F:$F,MOVIMIENTOS!$A:$A,DATE(PORTADA!$B$2,3,16),MOVIMIENTOS!$C:$C,Y$4)) | Z20: =IF(DAY(DATE(PORTADA!$B$2,3,16))<>16,"",SUMIFS(MOVIMIENTOS!$F:$F,MOVIMIENTOS!$A:$A,DATE(PORTADA!$B$2,3,16),MOVIMIENTOS!$C:$C,Z$4)) | AA20: =IF(DAY(DATE(PORTADA!$B$2,3,16))<>16,"",SUM(T20:Z20))
A21: HIJOS | B21: AHORRO EMERGENCIAS | C21: =CATEGORIAS!$E$15 | D21: =SUMIFS(MOVIMIENTOS!$F:$F,MOVIMIENTOS!$A:$A,">="&DATE(PORTADA!$B$2,3,1),MOVIMIENTOS!$A:$A,"<="&EOMONTH(DATE(PORTADA!$B$2,3,1),0),MOVIMIENTOS!$D:$D,$B21) | E21: =C21-D21 | F21: =IFERROR(D21/C21,"") | S21: =IF(DAY(DATE(PORTADA!$B$2,3,17))<>17,"",17) | T21: =IF(DAY(DATE(PORTADA!$B$2,3,17))<>17,"",SUMIFS(MOVIMIENTOS!$F:$F,MOVIMIENTOS!$A:$A,DATE(PORTADA!$B$2,3,17),MOVIMIENTOS!$C:$C,T$4)) | U21: =IF(DAY(DATE(PORTADA!$B$2,3,17))<>17,"",SUMIFS(MOVIMIENTOS!$F:$F,MOVIMIENTOS!$A:$A,DATE(PORTADA!$B$2,3,17),MOVIMIENTOS!$C:$C,U$4)) | V21: =IF(DAY(DATE(PORTADA!$B$2,3,17))<>17,"",SUMIFS(MOVIMIENTOS!$F:$F,MOVIMIENTOS!$A:$A,DATE(PORTADA!$B$2,3,17),MOVIMIENTOS!$C:$C,V$4)) | W21: =IF(DAY(DATE(PORTADA!$B$2,3,17))<>17,"",SUMIFS(MOVIMIENTOS!$F:$F,MOVIMIENTOS!$A:$A,DATE(PORTADA!$B$2,3,17),MOVIMIENTOS!$C:$C,W$4)) | X21: =IF(DAY(DATE(PORTADA!$B$2,3,17))<>17,"",SUMIFS(MOVIMIENTOS!$F:$F,MOVIMIENTOS!$A:$A,DATE(PORTADA!$B$2,3,17),MOVIMIENTOS!$C:$C,X$4)) | Y21: =IF(DAY(DATE(PORTADA!$B$2,3,17))<>17,"",SUMIFS(MOVIMIENTOS!$F:$F,MOVIMIENTOS!$A:$A,DATE(PORTADA!$B$2,3,17),MOVIMIENTOS!$C:$C,Y$4)) | Z21: =IF(DAY(DATE(PORTADA!$B$2,3,17))<>17,"",SUMIFS(MOVIMIENTOS!$F:$F,MOVIMIENTOS!$A:$A,DATE(PORTADA!$B$2,3,17),MOVIMIENTOS!$C:$C,Z$4)) | AA21: =IF(DAY(DATE(PORTADA!$B$2,3,17))<>17,"",SUM(T21:Z21))
A22: HIJOS | B22: SALIDAS CON FAMILIA | C22: =CATEGORIAS!$E$16 | D22: =SUMIFS(MOVIMIENTOS!$F:$F,MOVIMIENTOS!$A:$A,">="&DATE(PORTADA!$B$2,3,1),MOVIMIENTOS!$A:$A,"<="&EOMONTH(DATE(PORTADA!$B$2,3,1),0),MOVIMIENTOS!$D:$D,$B22) | E22: =C22-D22 | F22: =IFERROR(D22/C22,"") | S22: =IF(DAY(DATE(PORTADA!$B$2,3,18))<>18,"",18) | T22: =IF(DAY(DATE(PORTADA!$B$2,3,18))<>18,"",SUMIFS(MOVIMIENTOS!$F:$F,MOVIMIENTOS!$A:$A,DATE(PORTADA!$B$2,3,18),MOVIMIENTOS!$C:$C,T$4)) | U22: =IF(DAY(DATE(PORTADA!$B$2,3,18))<>18,"",SUMIFS(MOVIMIENTOS!$F:$F,MOVIMIENTOS!$A:$A,DATE(PORTADA!$B$2,3,18),MOVIMIENTOS!$C:$C,U$4)) | V22: =IF(DAY(DATE(PORTADA!$B$2,3,18))<>18,"",SUMIFS(MOVIMIENTOS!$F:$F,MOVIMIENTOS!$A:$A,DATE(PORTADA!$B$2,3,18),MOVIMIENTOS!$C:$C,V$4)) | W22: =IF(DAY(DATE(PORTADA!$B$2,3,18))<>18,"",SUMIFS(MOVIMIENTOS!$F:$F,MOVIMIENTOS!$A:$A,DATE(PORTADA!$B$2,3,18),MOVIMIENTOS!$C:$C,W$4)) | X22: =IF(DAY(DATE(PORTADA!$B$2,3,18))<>18,"",SUMIFS(MOVIMIENTOS!$F:$F,MOVIMIENTOS!$A:$A,DATE(PORTADA!$B$2,3,18),MOVIMIENTOS!$C:$C,X$4)) | Y22: =IF(DAY(DATE(PORTADA!$B$2,3,18))<>18,"",SUMIFS(MOVIMIENTOS!$F:$F,MOVIMIENTOS!$A:$A,DATE(PORTADA!$B$2,3,18),MOVIMIENTOS!$C:$C,Y$4)) | Z22: =IF(DAY(DATE(PORTADA!$B$2,3,18))<>18,"",SUMIFS(MOVIMIENTOS!$F:$F,MOVIMIENTOS!$A:$A,DATE(PORTADA!$B$2,3,18),MOVIMIENTOS!$C:$C,Z$4)) | AA22: =IF(DAY(DATE(PORTADA!$B$2,3,18))<>18,"",SUM(T22:Z22))
A23: CASA | B23: COMIDA CASA | C23: =CATEGORIAS!$E$17 | D23: =SUMIFS(MOVIMIENTOS!$F:$F,MOVIMIENTOS!$A:$A,">="&DATE(PORTADA!$B$2,3,1),MOVIMIENTOS!$A:$A,"<="&EOMONTH(DATE(PORTADA!$B$2,3,1),0),MOVIMIENTOS!$D:$D,$B23) | E23: =C23-D23 | F23: =IFERROR(D23/C23,"") | S23: =IF(DAY(DATE(PORTADA!$B$2,3,19))<>19,"",19) | T23: =IF(DAY(DATE(PORTADA!$B$2,3,19))<>19,"",SUMIFS(MOVIMIENTOS!$F:$F,MOVIMIENTOS!$A:$A,DATE(PORTADA!$B$2,3,19),MOVIMIENTOS!$C:$C,T$4)) | U23: =IF(DAY(DATE(PORTADA!$B$2,3,19))<>19,"",SUMIFS(MOVIMIENTOS!$F:$F,MOVIMIENTOS!$A:$A,DATE(PORTADA!$B$2,3,19),MOVIMIENTOS!$C:$C,U$4)) | V23: =IF(DAY(DATE(PORTADA!$B$2,3,19))<>19,"",SUMIFS(MOVIMIENTOS!$F:$F,MOVIMIENTOS!$A:$A,DATE(PORTADA!$B$2,3,19),MOVIMIENTOS!$C:$C,V$4)) | W23: =IF(DAY(DATE(PORTADA!$B$2,3,19))<>19,"",SUMIFS(MOVIMIENTOS!$F:$F,MOVIMIENTOS!$A:$A,DATE(PORTADA!$B$2,3,19),MOVIMIENTOS!$C:$C,W$4)) | X23: =IF(DAY(DATE(PORTADA!$B$2,3,19))<>19,"",SUMIFS(MOVIMIENTOS!$F:$F,MOVIMIENTOS!$A:$A,DATE(PORTADA!$B$2,3,19),MOVIMIENTOS!$C:$C,X$4)) | Y23: =IF(DAY(DATE(PORTADA!$B$2,3,19))<>19,"",SUMIFS(MOVIMIENTOS!$F:$F,MOVIMIENTOS!$A:$A,DATE(PORTADA!$B$2,3,19),MOVIMIENTOS!$C:$C,Y$4)) | Z23: =IF(DAY(DATE(PORTADA!$B$2,3,19))<>19,"",SUMIFS(MOVIMIENTOS!$F:$F,MOVIMIENTOS!$A:$A,DATE(PORTADA!$B$2,3,19),MOVIMIENTOS!$C:$C,Z$4)) | AA23: =IF(DAY(DATE(PORTADA!$B$2,3,19))<>19,"",SUM(T23:Z23))
A24: CASA | B24: COMIDA PERSONAL | C24: =CATEGORIAS!$E$18 | D24: =SUMIFS(MOVIMIENTOS!$F:$F,MOVIMIENTOS!$A:$A,">="&DATE(PORTADA!$B$2,3,1),MOVIMIENTOS!$A:$A,"<="&EOMONTH(DATE(PORTADA!$B$2,3,1),0),MOVIMIENTOS!$D:$D,$B24) | E24: =C24-D24 | F24: =IFERROR(D24/C24,"") | S24: =IF(DAY(DATE(PORTADA!$B$2,3,20))<>20,"",20) | T24: =IF(DAY(DATE(PORTADA!$B$2,3,20))<>20,"",SUMIFS(MOVIMIENTOS!$F:$F,MOVIMIENTOS!$A:$A,DATE(PORTADA!$B$2,3,20),MOVIMIENTOS!$C:$C,T$4)) | U24: =IF(DAY(DATE(PORTADA!$B$2,3,20))<>20,"",SUMIFS(MOVIMIENTOS!$F:$F,MOVIMIENTOS!$A:$A,DATE(PORTADA!$B$2,3,20),MOVIMIENTOS!$C:$C,U$4)) | V24: =IF(DAY(DATE(PORTADA!$B$2,3,20))<>20,"",SUMIFS(MOVIMIENTOS!$F:$F,MOVIMIENTOS!$A:$A,DATE(PORTADA!$B$2,3,20),MOVIMIENTOS!$C:$C,V$4)) | W24: =IF(DAY(DATE(PORTADA!$B$2,3,20))<>20,"",SUMIFS(MOVIMIENTOS!$F:$F,MOVIMIENTOS!$A:$A,DATE(PORTADA!$B$2,3,20),MOVIMIENTOS!$C:$C,W$4)) | X24: =IF(DAY(DATE(PORTADA!$B$2,3,20))<>20,"",SUMIFS(MOVIMIENTOS!$F:$F,MOVIMIENTOS!$A:$A,DATE(PORTADA!$B$2,3,20),MOVIMIENTOS!$C:$C,X$4)) | Y24: =IF(DAY(DATE(PORTADA!$B$2,3,20))<>20,"",SUMIFS(MOVIMIENTOS!$F:$F,MOVIMIENTOS!$A:$A,DATE(PORTADA!$B$2,3,20),MOVIMIENTOS!$C:$C,Y$4)) | Z24: =IF(DAY(DATE(PORTADA!$B$2,3,20))<>20,"",SUMIFS(MOVIMIENTOS!$F:$F,MOVIMIENTOS!$A:$A,DATE(PORTADA!$B$2,3,20),MOVIMIENTOS!$C:$C,Z$4)) | AA24: =IF(DAY(DATE(PORTADA!$B$2,3,20))<>20,"",SUM(T24:Z24))
A25: CASA | B25: CUENTAS | C25: =CATEGORIAS!$E$19 | D25: =SUMIFS(MOVIMIENTOS!$F:$F,MOVIMIENTOS!$A:$A,">="&DATE(PORTADA!$B$2,3,1),MOVIMIENTOS!$A:$A,"<="&EOMONTH(DATE(PORTADA!$B$2,3,1),0),MOVIMIENTOS!$D:$D,$B25) | E25: =C25-D25 | F25: =IFERROR(D25/C25,"") | S25: =IF(DAY(DATE(PORTADA!$B$2,3,21))<>21,"",21) | T25: =IF(DAY(DATE(PORTADA!$B$2,3,21))<>21,"",SUMIFS(MOVIMIENTOS!$F:$F,MOVIMIENTOS!$A:$A,DATE(PORTADA!$B$2,3,21),MOVIMIENTOS!$C:$C,T$4)) | U25: =IF(DAY(DATE(PORTADA!$B$2,3,21))<>21,"",SUMIFS(MOVIMIENTOS!$F:$F,MOVIMIENTOS!$A:$A,DATE(PORTADA!$B$2,3,21),MOVIMIENTOS!$C:$C,U$4)) | V25: =IF(DAY(DATE(PORTADA!$B$2,3,21))<>21,"",SUMIFS(MOVIMIENTOS!$F:$F,MOVIMIENTOS!$A:$A,DATE(PORTADA!$B$2,3,21),MOVIMIENTOS!$C:$C,V$4)) | W25: =IF(DAY(DATE(PORTADA!$B$2,3,21))<>21,"",SUMIFS(MOVIMIENTOS!$F:$F,MOVIMIENTOS!$A:$A,DATE(PORTADA!$B$2,3,21),MOVIMIENTOS!$C:$C,W$4)) | X25: =IF(DAY(DATE(PORTADA!$B$2,3,21))<>21,"",SUMIFS(MOVIMIENTOS!$F:$F,MOVIMIENTOS!$A:$A,DATE(PORTADA!$B$2,3,21),MOVIMIENTOS!$C:$C,X$4)) | Y25: =IF(DAY(DATE(PORTADA!$B$2,3,21))<>21,"",SUMIFS(MOVIMIENTOS!$F:$F,MOVIMIENTOS!$A:$A,DATE(PORTADA!$B$2,3,21),MOVIMIENTOS!$C:$C,Y$4)) | Z25: =IF(DAY(DATE(PORTADA!$B$2,3,21))<>21,"",SUMIFS(MOVIMIENTOS!$F:$F,MOVIMIENTOS!$A:$A,DATE(PORTADA!$B$2,3,21),MOVIMIENTOS!$C:$C,Z$4)) | AA25: =IF(DAY(DATE(PORTADA!$B$2,3,21))<>21,"",SUM(T25:Z25))
A26: SALUD | B26: MEDICAMENTOS | C26: =CATEGORIAS!$E$20 | D26: =SUMIFS(MOVIMIENTOS!$F:$F,MOVIMIENTOS!$A:$A,">="&DATE(PORTADA!$B$2,3,1),MOVIMIENTOS!$A:$A,"<="&EOMONTH(DATE(PORTADA!$B$2,3,1),0),MOVIMIENTOS!$D:$D,$B26) | E26: =C26-D26 | F26: =IFERROR(D26/C26,"") | S26: =IF(DAY(DATE(PORTADA!$B$2,3,22))<>22,"",22) | T26: =IF(DAY(DATE(PORTADA!$B$2,3,22))<>22,"",SUMIFS(MOVIMIENTOS!$F:$F,MOVIMIENTOS!$A:$A,DATE(PORTADA!$B$2,3,22),MOVIMIENTOS!$C:$C,T$4)) | U26: =IF(DAY(DATE(PORTADA!$B$2,3,22))<>22,"",SUMIFS(MOVIMIENTOS!$F:$F,MOVIMIENTOS!$A:$A,DATE(PORTADA!$B$2,3,22),MOVIMIENTOS!$C:$C,U$4)) | V26: =IF(DAY(DATE(PORTADA!$B$2,3,22))<>22,"",SUMIFS(MOVIMIENTOS!$F:$F,MOVIMIENTOS!$A:$A,DATE(PORTADA!$B$2,3,22),MOVIMIENTOS!$C:$C,V$4)) | W26: =IF(DAY(DATE(PORTADA!$B$2,3,22))<>22,"",SUMIFS(MOVIMIENTOS!$F:$F,MOVIMIENTOS!$A:$A,DATE(PORTADA!$B$2,3,22),MOVIMIENTOS!$C:$C,W$4)) | X26: =IF(DAY(DATE(PORTADA!$B$2,3,22))<>22,"",SUMIFS(MOVIMIENTOS!$F:$F,MOVIMIENTOS!$A:$A,DATE(PORTADA!$B$2,3,22),MOVIMIENTOS!$C:$C,X$4)) | Y26: =IF(DAY(DATE(PORTADA!$B$2,3,22))<>22,"",SUMIFS(MOVIMIENTOS!$F:$F,MOVIMIENTOS!$A:$A,DATE(PORTADA!$B$2,3,22),MOVIMIENTOS!$C:$C,Y$4)) | Z26: =IF(DAY(DATE(PORTADA!$B$2,3,22))<>22,"",SUMIFS(MOVIMIENTOS!$F:$F,MOVIMIENTOS!$A:$A,DATE(PORTADA!$B$2,3,22),MOVIMIENTOS!$C:$C,Z$4)) | AA26: =IF(DAY(DATE(PORTADA!$B$2,3,22))<>22,"",SUM(T26:Z26))
A27: SALUD | B27: ROPA | C27: =CATEGORIAS!$E$21 | D27: =SUMIFS(MOVIMIENTOS!$F:$F,MOVIMIENTOS!$A:$A,">="&DATE(PORTADA!$B$2,3,1),MOVIMIENTOS!$A:$A,"<="&EOMONTH(DATE(PORTADA!$B$2,3,1),0),MOVIMIENTOS!$D:$D,$B27) | E27: =C27-D27 | F27: =IFERROR(D27/C27,"") | S27: =IF(DAY(DATE(PORTADA!$B$2,3,23))<>23,"",23) | T27: =IF(DAY(DATE(PORTADA!$B$2,3,23))<>23,"",SUMIFS(MOVIMIENTOS!$F:$F,MOVIMIENTOS!$A:$A,DATE(PORTADA!$B$2,3,23),MOVIMIENTOS!$C:$C,T$4)) | U27: =IF(DAY(DATE(PORTADA!$B$2,3,23))<>23,"",SUMIFS(MOVIMIENTOS!$F:$F,MOVIMIENTOS!$A:$A,DATE(PORTADA!$B$2,3,23),MOVIMIENTOS!$C:$C,U$4)) | V27: =IF(DAY(DATE(PORTADA!$B$2,3,23))<>23,"",SUMIFS(MOVIMIENTOS!$F:$F,MOVIMIENTOS!$A:$A,DATE(PORTADA!$B$2,3,23),MOVIMIENTOS!$C:$C,V$4)) | W27: =IF(DAY(DATE(PORTADA!$B$2,3,23))<>23,"",SUMIFS(MOVIMIENTOS!$F:$F,MOVIMIENTOS!$A:$A,DATE(PORTADA!$B$2,3,23),MOVIMIENTOS!$C:$C,W$4)) | X27: =IF(DAY(DATE(PORTADA!$B$2,3,23))<>23,"",SUMIFS(MOVIMIENTOS!$F:$F,MOVIMIENTOS!$A:$A,DATE(PORTADA!$B$2,3,23),MOVIMIENTOS!$C:$C,X$4)) | Y27: =IF(DAY(DATE(PORTADA!$B$2,3,23))<>23,"",SUMIFS(MOVIMIENTOS!$F:$F,MOVIMIENTOS!$A:$A,DATE(PORTADA!$B$2,3,23),MOVIMIENTOS!$C:$C,Y$4)) | Z27: =IF(DAY(DATE(PORTADA!$B$2,3,23))<>23,"",SUMIFS(MOVIMIENTOS!$F:$F,MOVIMIENTOS!$A:$A,DATE(PORTADA!$B$2,3,23),MOVIMIENTOS!$C:$C,Z$4)) | AA27: =IF(DAY(DATE(PORTADA!$B$2,3,23))<>23,"",SUM(T27:Z27))
A28: SALUD | B28: DEPORTE | C28: =CATEGORIAS!$E$22 | D28: =SUMIFS(MOVIMIENTOS!$F:$F,MOVIMIENTOS!$A:$A,">="&DATE(PORTADA!$B$2,3,1),MOVIMIENTOS!$A:$A,"<="&EOMONTH(DATE(PORTADA!$B$2,3,1),0),MOVIMIENTOS!$D:$D,$B28) | E28: =C28-D28 | F28: =IFERROR(D28/C28,"") | S28: =IF(DAY(DATE(PORTADA!$B$2,3,24))<>24,"",24) | T28: =IF(DAY(DATE(PORTADA!$B$2,3,24))<>24,"",SUMIFS(MOVIMIENTOS!$F:$F,MOVIMIENTOS!$A:$A,DATE(PORTADA!$B$2,3,24),MOVIMIENTOS!$C:$C,T$4)) | U28: =IF(DAY(DATE(PORTADA!$B$2,3,24))<>24,"",SUMIFS(MOVIMIENTOS!$F:$F,MOVIMIENTOS!$A:$A,DATE(PORTADA!$B$2,3,24),MOVIMIENTOS!$C:$C,U$4)) | V28: =IF(DAY(DATE(PORTADA!$B$2,3,24))<>24,"",SUMIFS(MOVIMIENTOS!$F:$F,MOVIMIENTOS!$A:$A,DATE(PORTADA!$B$2,3,24),MOVIMIENTOS!$C:$C,V$4)) | W28: =IF(DAY(DATE(PORTADA!$B$2,3,24))<>24,"",SUMIFS(MOVIMIENTOS!$F:$F,MOVIMIENTOS!$A:$A,DATE(PORTADA!$B$2,3,24),MOVIMIENTOS!$C:$C,W$4)) | X28: =IF(DAY(DATE(PORTADA!$B$2,3,24))<>24,"",SUMIFS(MOVIMIENTOS!$F:$F,MOVIMIENTOS!$A:$A,DATE(PORTADA!$B$2,3,24),MOVIMIENTOS!$C:$C,X$4)) | Y28: =IF(DAY(DATE(PORTADA!$B$2,3,24))<>24,"",SUMIFS(MOVIMIENTOS!$F:$F,MOVIMIENTOS!$A:$A,DATE(PORTADA!$B$2,3,24),MOVIMIENTOS!$C:$C,Y$4)) | Z28: =IF(DAY(DATE(PORTADA!$B$2,3,24))<>24,"",SUMIFS(MOVIMIENTOS!$F:$F,MOVIMIENTOS!$A:$A,DATE(PORTADA!$B$2,3,24),MOVIMIENTOS!$C:$C,Z$4)) | AA28: =IF(DAY(DATE(PORTADA!$B$2,3,24))<>24,"",SUM(T28:Z28))
A29: AUTO | B29: BENCINA | C29: =CATEGORIAS!$E$23 | D29: =SUMIFS(MOVIMIENTOS!$F:$F,MOVIMIENTOS!$A:$A,">="&DATE(PORTADA!$B$2,3,1),MOVIMIENTOS!$A:$A,"<="&EOMONTH(DATE(PORTADA!$B$2,3,1),0),MOVIMIENTOS!$D:$D,$B29) | E29: =C29-D29 | F29: =IFERROR(D29/C29,"") | S29: =IF(DAY(DATE(PORTADA!$B$2,3,25))<>25,"",25) | T29: =IF(DAY(DATE(PORTADA!$B$2,3,25))<>25,"",SUMIFS(MOVIMIENTOS!$F:$F,MOVIMIENTOS!$A:$A,DATE(PORTADA!$B$2,3,25),MOVIMIENTOS!$C:$C,T$4)) | U29: =IF(DAY(DATE(PORTADA!$B$2,3,25))<>25,"",SUMIFS(MOVIMIENTOS!$F:$F,MOVIMIENTOS!$A:$A,DATE(PORTADA!$B$2,3,25),MOVIMIENTOS!$C:$C,U$4)) | V29: =IF(DAY(DATE(PORTADA!$B$2,3,25))<>25,"",SUMIFS(MOVIMIENTOS!$F:$F,MOVIMIENTOS!$A:$A,DATE(PORTADA!$B$2,3,25),MOVIMIENTOS!$C:$C,V$4)) | W29: =IF(DAY(DATE(PORTADA!$B$2,3,25))<>25,"",SUMIFS(MOVIMIENTOS!$F:$F,MOVIMIENTOS!$A:$A,DATE(PORTADA!$B$2,3,25),MOVIMIENTOS!$C:$C,W$4)) | X29: =IF(DAY(DATE(PORTADA!$B$2,3,25))<>25,"",SUMIFS(MOVIMIENTOS!$F:$F,MOVIMIENTOS!$A:$A,DATE(PORTADA!$B$2,3,25),MOVIMIENTOS!$C:$C,X$4)) | Y29: =IF(DAY(DATE(PORTADA!$B$2,3,25))<>25,"",SUMIFS(MOVIMIENTOS!$F:$F,MOVIMIENTOS!$A:$A,DATE(PORTADA!$B$2,3,25),MOVIMIENTOS!$C:$C,Y$4)) | Z29: =IF(DAY(DATE(PORTADA!$B$2,3,25))<>25,"",SUMIFS(MOVIMIENTOS!$F:$F,MOVIMIENTOS!$A:$A,DATE(PORTADA!$B$2,3,25),MOVIMIENTOS!$C:$C,Z$4)) | AA29: =IF(DAY(DATE(PORTADA!$B$2,3,25))<>25,"",SUM(T29:Z29))
A30: AUTO | B30: OTROS | C30: =CATEGORIAS!$E$24 | D30: =SUMIFS(MOVIMIENTOS!$F:$F,MOVIMIENTOS!$A:$A,">="&DATE(PORTADA!$B$2,3,1),MOVIMIENTOS!$A:$A,"<="&EOMONTH(DATE(PORTADA!$B$2,3,1),0),MOVIMIENTOS!$D:$D,$B30) | E30: =C30-D30 | F30: =IFERROR(D30/C30,"") | S30: =IF(DAY(DATE(PORTADA!$B$2,3,26))<>26,"",26) | T30: =IF(DAY(DATE(PORTADA!$B$2,3,26))<>26,"",SUMIFS(MOVIMIENTOS!$F:$F,MOVIMIENTOS!$A:$A,DATE(PORTADA!$B$2,3,26),MOVIMIENTOS!$C:$C,T$4)) | U30: =IF(DAY(DATE(PORTADA!$B$2,3,26))<>26,"",SUMIFS(MOVIMIENTOS!$F:$F,MOVIMIENTOS!$A:$A,DATE(PORTADA!$B$2,3,26),MOVIMIENTOS!$C:$C,U$4)) | V30: =IF(DAY(DATE(PORTADA!$B$2,3,26))<>26,"",SUMIFS(MOVIMIENTOS!$F:$F,MOVIMIENTOS!$A:$A,DATE(PORTADA!$B$2,3,26),MOVIMIENTOS!$C:$C,V$4)) | W30: =IF(DAY(DATE(PORTADA!$B$2,3,26))<>26,"",SUMIFS(MOVIMIENTOS!$F:$F,MOVIMIENTOS!$A:$A,DATE(PORTADA!$B$2,3,26),MOVIMIENTOS!$C:$C,W$4)) | X30: =IF(DAY(DATE(PORTADA!$B$2,3,26))<>26,"",SUMIFS(MOVIMIENTOS!$F:$F,MOVIMIENTOS!$A:$A,DATE(PORTADA!$B$2,3,26),MOVIMIENTOS!$C:$C,X$4)) | Y30: =IF(DAY(DATE(PORTADA!$B$2,3,26))<>26,"",SUMIFS(MOVIMIENTOS!$F:$F,MOVIMIENTOS!$A:$A,DATE(PORTADA!$B$2,3,26),MOVIMIENTOS!$C:$C,Y$4)) | Z30: =IF(DAY(DATE(PORTADA!$B$2,3,26))<>26,"",SUMIFS(MOVIMIENTOS!$F:$F,MOVIMIENTOS!$A:$A,DATE(PORTADA!$B$2,3,26),MOVIMIENTOS!$C:$C,Z$4)) | AA30: =IF(DAY(DATE(PORTADA!$B$2,3,26))<>26,"",SUM(T30:Z30))
A31: DIVERSION | B31: COPETE | C31: =CATEGORIAS!$E$25 | D31: =SUMIFS(MOVIMIENTOS!$F:$F,MOVIMIENTOS!$A:$A,">="&DATE(PORTADA!$B$2,3,1),MOVIMIENTOS!$A:$A,"<="&EOMONTH(DATE(PORTADA!$B$2,3,1),0),MOVIMIENTOS!$D:$D,$B31) | E31: =C31-D31 | F31: =IFERROR(D31/C31,"") | S31: =IF(DAY(DATE(PORTADA!$B$2,3,27))<>27,"",27) | T31: =IF(DAY(DATE(PORTADA!$B$2,3,27))<>27,"",SUMIFS(MOVIMIENTOS!$F:$F,MOVIMIENTOS!$A:$A,DATE(PORTADA!$B$2,3,27),MOVIMIENTOS!$C:$C,T$4)) | U31: =IF(DAY(DATE(PORTADA!$B$2,3,27))<>27,"",SUMIFS(MOVIMIENTOS!$F:$F,MOVIMIENTOS!$A:$A,DATE(PORTADA!$B$2,3,27),MOVIMIENTOS!$C:$C,U$4)) | V31: =IF(DAY(DATE(PORTADA!$B$2,3,27))<>27,"",SUMIFS(MOVIMIENTOS!$F:$F,MOVIMIENTOS!$A:$A,DATE(PORTADA!$B$2,3,27),MOVIMIENTOS!$C:$C,V$4)) | W31: =IF(DAY(DATE(PORTADA!$B$2,3,27))<>27,"",SUMIFS(MOVIMIENTOS!$F:$F,MOVIMIENTOS!$A:$A,DATE(PORTADA!$B$2,3,27),MOVIMIENTOS!$C:$C,W$4)) | X31: =IF(DAY(DATE(PORTADA!$B$2,3,27))<>27,"",SUMIFS(MOVIMIENTOS!$F:$F,MOVIMIENTOS!$A:$A,DATE(PORTADA!$B$2,3,27),MOVIMIENTOS!$C:$C,X$4)) | Y31: =IF(DAY(DATE(PORTADA!$B$2,3,27))<>27,"",SUMIFS(MOVIMIENTOS!$F:$F,MOVIMIENTOS!$A:$A,DATE(PORTADA!$B$2,3,27),MOVIMIENTOS!$C:$C,Y$4)) | Z31: =IF(DAY(DATE(PORTADA!$B$2,3,27))<>27,"",SUMIFS(MOVIMIENTOS!$F:$F,MOVIMIENTOS!$A:$A,DATE(PORTADA!$B$2,3,27),MOVIMIENTOS!$C:$C,Z$4)) | AA31: =IF(DAY(DATE(PORTADA!$B$2,3,27))<>27,"",SUM(T31:Z31))
A32: DIVERSION | B32: WEED | C32: =CATEGORIAS!$E$26 | D32: =SUMIFS(MOVIMIENTOS!$F:$F,MOVIMIENTOS!$A:$A,">="&DATE(PORTADA!$B$2,3,1),MOVIMIENTOS!$A:$A,"<="&EOMONTH(DATE(PORTADA!$B$2,3,1),0),MOVIMIENTOS!$D:$D,$B32) | E32: =C32-D32 | F32: =IFERROR(D32/C32,"") | S32: =IF(DAY(DATE(PORTADA!$B$2,3,28))<>28,"",28) | T32: =IF(DAY(DATE(PORTADA!$B$2,3,28))<>28,"",SUMIFS(MOVIMIENTOS!$F:$F,MOVIMIENTOS!$A:$A,DATE(PORTADA!$B$2,3,28),MOVIMIENTOS!$C:$C,T$4)) | U32: =IF(DAY(DATE(PORTADA!$B$2,3,28))<>28,"",SUMIFS(MOVIMIENTOS!$F:$F,MOVIMIENTOS!$A:$A,DATE(PORTADA!$B$2,3,28),MOVIMIENTOS!$C:$C,U$4)) | V32: =IF(DAY(DATE(PORTADA!$B$2,3,28))<>28,"",SUMIFS(MOVIMIENTOS!$F:$F,MOVIMIENTOS!$A:$A,DATE(PORTADA!$B$2,3,28),MOVIMIENTOS!$C:$C,V$4)) | W32: =IF(DAY(DATE(PORTADA!$B$2,3,28))<>28,"",SUMIFS(MOVIMIENTOS!$F:$F,MOVIMIENTOS!$A:$A,DATE(PORTADA!$B$2,3,28),MOVIMIENTOS!$C:$C,W$4)) | X32: =IF(DAY(DATE(PORTADA!$B$2,3,28))<>28,"",SUMIFS(MOVIMIENTOS!$F:$F,MOVIMIENTOS!$A:$A,DATE(PORTADA!$B$2,3,28),MOVIMIENTOS!$C:$C,X$4)) | Y32: =IF(DAY(DATE(PORTADA!$B$2,3,28))<>28,"",SUMIFS(MOVIMIENTOS!$F:$F,MOVIMIENTOS!$A:$A,DATE(PORTADA!$B$2,3,28),MOVIMIENTOS!$C:$C,Y$4)) | Z32: =IF(DAY(DATE(PORTADA!$B$2,3,28))<>28,"",SUMIFS(MOVIMIENTOS!$F:$F,MOVIMIENTOS!$A:$A,DATE(PORTADA!$B$2,3,28),MOVIMIENTOS!$C:$C,Z$4)) | AA32: =IF(DAY(DATE(PORTADA!$B$2,3,28))<>28,"",SUM(T32:Z32))
A33: DIVERSION | B33: CARCASA CELULAR | C33: =CATEGORIAS!$E$27 | D33: =SUMIFS(MOVIMIENTOS!$F:$F,MOVIMIENTOS!$A:$A,">="&DATE(PORTADA!$B$2,3,1),MOVIMIENTOS!$A:$A,"<="&EOMONTH(DATE(PORTADA!$B$2,3,1),0),MOVIMIENTOS!$D:$D,$B33) | E33: =C33-D33 | F33: =IFERROR(D33/C33,"") | S33: =IF(DAY(DATE(PORTADA!$B$2,3,29))<>29,"",29) | T33: =IF(DAY(DATE(PORTADA!$B$2,3,29))<>29,"",SUMIFS(MOVIMIENTOS!$F:$F,MOVIMIENTOS!$A:$A,DATE(PORTADA!$B$2,3,29),MOVIMIENTOS!$C:$C,T$4)) | U33: =IF(DAY(DATE(PORTADA!$B$2,3,29))<>29,"",SUMIFS(MOVIMIENTOS!$F:$F,MOVIMIENTOS!$A:$A,DATE(PORTADA!$B$2,3,29),MOVIMIENTOS!$C:$C,U$4)) | V33: =IF(DAY(DATE(PORTADA!$B$2,3,29))<>29,"",SUMIFS(MOVIMIENTOS!$F:$F,MOVIMIENTOS!$A:$A,DATE(PORTADA!$B$2,3,29),MOVIMIENTOS!$C:$C,V$4)) | W33: =IF(DAY(DATE(PORTADA!$B$2,3,29))<>29,"",SUMIFS(MOVIMIENTOS!$F:$F,MOVIMIENTOS!$A:$A,DATE(PORTADA!$B$2,3,29),MOVIMIENTOS!$C:$C,W$4)) | X33: =IF(DAY(DATE(PORTADA!$B$2,3,29))<>29,"",SUMIFS(MOVIMIENTOS!$F:$F,MOVIMIENTOS!$A:$A,DATE(PORTADA!$B$2,3,29),MOVIMIENTOS!$C:$C,X$4)) | Y33: =IF(DAY(DATE(PORTADA!$B$2,3,29))<>29,"",SUMIFS(MOVIMIENTOS!$F:$F,MOVIMIENTOS!$A:$A,DATE(PORTADA!$B$2,3,29),MOVIMIENTOS!$C:$C,Y$4)) | Z33: =IF(DAY(DATE(PORTADA!$B$2,3,29))<>29,"",SUMIFS(MOVIMIENTOS!$F:$F,MOVIMIENTOS!$A:$A,DATE(PORTADA!$B$2,3,29),MOVIMIENTOS!$C:$C,Z$4)) | AA33: =IF(DAY(DATE(PORTADA!$B$2,3,29))<>29,"",SUM(T33:Z33))
A34: DIVERSION | B34: SALIDA CON AMIGOS | C34: =CATEGORIAS!$E$28 | D34: =SUMIFS(MOVIMIENTOS!$F:$F,MOVIMIENTOS!$A:$A,">="&DATE(PORTADA!$B$2,3,1),MOVIMIENTOS!$A:$A,"<="&EOMONTH(DATE(PORTADA!$B$2,3,1),0),MOVIMIENTOS!$D:$D,$B34) | E34: =C34-D34 | F34: =IFERROR(D34/C34,"") | S34: =IF(DAY(DATE(PORTADA!$B$2,3,30))<>30,"",30) | T34: =IF(DAY(DATE(PORTADA!$B$2,3,30))<>30,"",SUMIFS(MOVIMIENTOS!$F:$F,MOVIMIENTOS!$A:$A,DATE(PORTADA!$B$2,3,30),MOVIMIENTOS!$C:$C,T$4)) | U34: =IF(DAY(DATE(PORTADA!$B$2,3,30))<>30,"",SUMIFS(MOVIMIENTOS!$F:$F,MOVIMIENTOS!$A:$A,DATE(PORTADA!$B$2,3,30),MOVIMIENTOS!$C:$C,U$4)) | V34: =IF(DAY(DATE(PORTADA!$B$2,3,30))<>30,"",SUMIFS(MOVIMIENTOS!$F:$F,MOVIMIENTOS!$A:$A,DATE(PORTADA!$B$2,3,30),MOVIMIENTOS!$C:$C,V$4)) | W34: =IF(DAY(DATE(PORTADA!$B$2,3,30))<>30,"",SUMIFS(MOVIMIENTOS!$F:$F,MOVIMIENTOS!$A:$A,DATE(PORTADA!$B$2,3,30),MOVIMIENTOS!$C:$C,W$4)) | X34: =IF(DAY(DATE(PORTADA!$B$2,3,30))<>30,"",SUMIFS(MOVIMIENTOS!$F:$F,MOVIMIENTOS!$A:$A,DATE(PORTADA!$B$2,3,30),MOVIMIENTOS!$C:$C,X$4)) | Y34: =IF(DAY(DATE(PORTADA!$B$2,3,30))<>30,"",SUMIFS(MOVIMIENTOS!$F:$F,MOVIMIENTOS!$A:$A,DATE(PORTADA!$B$2,3,30),MOVIMIENTOS!$C:$C,Y$4)) | Z34: =IF(DAY(DATE(PORTADA!$B$2,3,30))<>30,"",SUMIFS(MOVIMIENTOS!$F:$F,MOVIMIENTOS!$A:$A,DATE(PORTADA!$B$2,3,30),MOVIMIENTOS!$C:$C,Z$4)) | AA34: =IF(DAY(DATE(PORTADA!$B$2,3,30))<>30,"",SUM(T34:Z34))
A35: OTROS | B35: CHICHES | C35: =CATEGORIAS!$E$29 | D35: =SUMIFS(MOVIMIENTOS!$F:$F,MOVIMIENTOS!$A:$A,">="&DATE(PORTADA!$B$2,3,1),MOVIMIENTOS!$A:$A,"<="&EOMONTH(DATE(PORTADA!$B$2,3,1),0),MOVIMIENTOS!$D:$D,$B35) | E35: =C35-D35 | F35: =IFERROR(D35/C35,"") | S35: =IF(DAY(DATE(PORTADA!$B$2,3,31))<>31,"",31) | T35: =IF(DAY(DATE(PORTADA!$B$2,3,31))<>31,"",SUMIFS(MOVIMIENTOS!$F:$F,MOVIMIENTOS!$A:$A,DATE(PORTADA!$B$2,3,31),MOVIMIENTOS!$C:$C,T$4)) | U35: =IF(DAY(DATE(PORTADA!$B$2,3,31))<>31,"",SUMIFS(MOVIMIENTOS!$F:$F,MOVIMIENTOS!$A:$A,DATE(PORTADA!$B$2,3,31),MOVIMIENTOS!$C:$C,U$4)) | V35: =IF(DAY(DATE(PORTADA!$B$2,3,31))<>31,"",SUMIFS(MOVIMIENTOS!$F:$F,MOVIMIENTOS!$A:$A,DATE(PORTADA!$B$2,3,31),MOVIMIENTOS!$C:$C,V$4)) | W35: =IF(DAY(DATE(PORTADA!$B$2,3,31))<>31,"",SUMIFS(MOVIMIENTOS!$F:$F,MOVIMIENTOS!$A:$A,DATE(PORTADA!$B$2,3,31),MOVIMIENTOS!$C:$C,W$4)) | X35: =IF(DAY(DATE(PORTADA!$B$2,3,31))<>31,"",SUMIFS(MOVIMIENTOS!$F:$F,MOVIMIENTOS!$A:$A,DATE(PORTADA!$B$2,3,31),MOVIMIENTOS!$C:$C,X$4)) | Y35: =IF(DAY(DATE(PORTADA!$B$2,3,31))<>31,"",SUMIFS(MOVIMIENTOS!$F:$F,MOVIMIENTOS!$A:$A,DATE(PORTADA!$B$2,3,31),MOVIMIENTOS!$C:$C,Y$4)) | Z35: =IF(DAY(DATE(PORTADA!$B$2,3,31))<>31,"",SUMIFS(MOVIMIENTOS!$F:$F,MOVIMIENTOS!$A:$A,DATE(PORTADA!$B$2,3,31),MOVIMIENTOS!$C:$C,Z$4)) | AA35: =IF(DAY(DATE(PORTADA!$B$2,3,31))<>31,"",SUM(T35:Z35))
A36: OTROS | B36: DONACIONES | C36: =CATEGORIAS!$E$30 | D36: =SUMIFS(MOVIMIENTOS!$F:$F,MOVIMIENTOS!$A:$A,">="&DATE(PORTADA!$B$2,3,1),MOVIMIENTOS!$A:$A,"<="&EOMONTH(DATE(PORTADA!$B$2,3,1),0),MOVIMIENTOS!$D:$D,$B36) | E36: =C36-D36 | F36: =IFERROR(D36/C36,"") | S36: MES | T36: =SUM(T5:T35) | U36: =SUM(U5:U35) | V36: =SUM(V5:V35) | W36: =SUM(W5:W35) | X36: =SUM(X5:X35) | Y36: =SUM(Y5:Y35) | Z36: =SUM(Z5:Z35) | AA36: =SUM(AA5:AA35)
A37: OTROS | B37: PRESTAMOS | C37: =CATEGORIAS!$E$31 | D37: =SUMIFS(MOVIMIENTOS!$F:$F,MOVIMIENTOS!$A:$A,">="&DATE(PORTADA!$B$2,3,1),MOVIMIENTOS!$A:$A,"<="&EOMONTH(DATE(PORTADA!$B$2,3,1),0),MOVIMIENTOS!$D:$D,$B37) | E37: =C37-D37 | F37: =IFERROR(D37/C37,"")
A38: OTROS | B38: LOCOMOCION | C38: =CATEGORIAS!$E$32 | D38: =SUMIFS(MOVIMIENTOS!$F:$F,MOVIMIENTOS!$A:$A,">="&DATE(PORTADA!$B$2,3,1),MOVIMIENTOS!$A:$A,"<="&EOMONTH(DATE(PORTADA!$B$2,3,1),0),MOVIMIENTOS!$D:$D,$B38) | E38: =C38-D38 | F38: =IFERROR(D38/C38,"")
A39: OTROS | B39: OTROS GASTOS | C39: =CATEGORIAS!$E$33 | D39: =SUMIFS(MOVIMIENTOS!$F:$F,MOVIMIENTOS!$A:$A,">="&DATE(PORTADA!$B$2,3,1),MOVIMIENTOS!$A:$A,"<="&EOMONTH(DATE(PORTADA!$B$2,3,1),0),MOVIMIENTOS!$D:$D,$B39) | E39: =C39-D39 | F39: =IFERROR(D39/C39,"")
B40: TOTAL EGRESOS | C40: =SUM(C17:C39) | D40: =SUM(D17:D39) | E40: =SUM(E17:E39)
A42: POR GRUPO
A43: GRUPO | C43: PRESUPUESTO | D43: REAL | E43: DIFERENCIA | F43: % USADO
A44: CUENTAS PERSONALES | C44: =SUMIFS($C$17:$C$39,$A$17:$A$39,$A44) | D44: =SUMIFS($D$17:$D$39,$A$17:$A$39,$A44) | E44: =C44-D44 | F44: =IFERROR(D44/C44,"")
A45: HIJOS | C45: =SUMIFS($C$17:$C$39,$A$17:$A$39,$A45) | D45: =SUMIFS($D$17:$D$39,$A$17:$A$39,$A45) | E45: =C45-D45 | F45: =IFERROR(D45/C45,"")
A46: CASA | C46: =SUMIFS($C$17:$C$39,$A$17:$A$39,$A46) | D46: =SUMIFS($D$17:$D$39,$A$17:$A$39,$A46) | E46: =C46-D46 | F46: =IFERROR(D46/C46,"")
A47: SALUD | C47: =SUMIFS($C$17:$C$39,$A$17:$A$39,$A47) | D47: =SUMIFS($D$17:$D$39,$A$17:$A$39,$A47) | E47: =C47-D47 | F47: =IFERROR(D47/C47,"")
A48: AUTO | C48: =SUMIFS($C$17:$C$39,$A$17:$A$39,$A48) | D48: =SUMIFS($D$17:$D$39,$A$17:$A$39,$A48) | E48: =C48-D48 | F48: =IFERROR(D48/C48,"")
A49: DIVERSION | C49: =SUMIFS($C$17:$C$39,$A$17:$A$39,$A49) | D49: =SUMIFS($D$17:$D$39,$A$17:$A$39,$A49) | E49: =C49-D49 | F49: =IFERROR(D49/C49,"")
A50: OTROS | C50: =SUMIFS($C$17:$C$39,$A$17:$A$39,$A50) | D50: =SUMIFS($D$17:$D$39,$A$17:$A$39,$A50) | E50: =C50-D50 | F50: =IFERROR(D50/C50,"")
A52: SALDO DEL MES
B53: Ingresos menos egresos | C53: =C13-C40 | D53: =D13-D40
B54: Solo gasto | C54: =SUMIFS(CATEGORIAS!$E:$E,CATEGORIAS!$D:$D,"GASTO") | D54: =SUMIFS(MOVIMIENTOS!$F:$F,MOVIMIENTOS!$A:$A,">="&DATE(PORTADA!$B$2,3,1),MOVIMIENTOS!$A:$A,"<="&EOMONTH(DATE(PORTADA!$B$2,3,1),0),MOVIMIENTOS!$E:$E,"GASTO")
B55: Ahorro | C55: =SUMIFS(CATEGORIAS!$E:$E,CATEGORIAS!$D:$D,"AHORRO") | D55: =SUMIFS(MOVIMIENTOS!$F:$F,MOVIMIENTOS!$A:$A,">="&DATE(PORTADA!$B$2,3,1),MOVIMIENTOS!$A:$A,"<="&EOMONTH(DATE(PORTADA!$B$2,3,1),0),MOVIMIENTOS!$E:$E,"AHORRO")
B56: Deuda | C56: =SUMIFS(CATEGORIAS!$E:$E,CATEGORIAS!$D:$D,"DEUDA") | D56: =SUMIFS(MOVIMIENTOS!$F:$F,MOVIMIENTOS!$A:$A,">="&DATE(PORTADA!$B$2,3,1),MOVIMIENTOS!$A:$A,"<="&EOMONTH(DATE(PORTADA!$B$2,3,1),0),MOVIMIENTOS!$E:$E,"DEUDA")

Sheet ABRIL
A1: ABRIL · ingresos y egresos
A2: =CONCATENATE("Año ",PORTADA!$B$2," · verde = lo escribes tú · azul = se calcula solo")
S3: DÍA A DÍA
A4: INGRESOS | S4: DÍA | T4: CUENTAS PERSONALES | U4: HIJOS | V4: CASA | W4: SALUD | X4: AUTO | Y4: DIVERSION | Z4: OTROS | AA4: TOTAL
A5: GRUPO | B5: CATEGORÍA | C5: PRESUPUESTO | D5: REAL | E5: DIFERENCIA | F5: % LOGRO | S5: =IF(DAY(DATE(PORTADA!$B$2,4,1))<>1,"",1) | T5: =IF(DAY(DATE(PORTADA!$B$2,4,1))<>1,"",SUMIFS(MOVIMIENTOS!$F:$F,MOVIMIENTOS!$A:$A,DATE(PORTADA!$B$2,4,1),MOVIMIENTOS!$C:$C,T$4)) | U5: =IF(DAY(DATE(PORTADA!$B$2,4,1))<>1,"",SUMIFS(MOVIMIENTOS!$F:$F,MOVIMIENTOS!$A:$A,DATE(PORTADA!$B$2,4,1),MOVIMIENTOS!$C:$C,U$4)) | V5: =IF(DAY(DATE(PORTADA!$B$2,4,1))<>1,"",SUMIFS(MOVIMIENTOS!$F:$F,MOVIMIENTOS!$A:$A,DATE(PORTADA!$B$2,4,1),MOVIMIENTOS!$C:$C,V$4)) | W5: =IF(DAY(DATE(PORTADA!$B$2,4,1))<>1,"",SUMIFS(MOVIMIENTOS!$F:$F,MOVIMIENTOS!$A:$A,DATE(PORTADA!$B$2,4,1),MOVIMIENTOS!$C:$C,W$4)) | X5: =IF(DAY(DATE(PORTADA!$B$2,4,1))<>1,"",SUMIFS(MOVIMIENTOS!$F:$F,MOVIMIENTOS!$A:$A,DATE(PORTADA!$B$2,4,1),MOVIMIENTOS!$C:$C,X$4)) | Y5: =IF(DAY(DATE(PORTADA!$B$2,4,1))<>1,"",SUMIFS(MOVIMIENTOS!$F:$F,MOVIMIENTOS!$A:$A,DATE(PORTADA!$B$2,4,1),MOVIMIENTOS!$C:$C,Y$4)) | Z5: =IF(DAY(DATE(PORTADA!$B$2,4,1))<>1,"",SUMIFS(MOVIMIENTOS!$F:$F,MOVIMIENTOS!$A:$A,DATE(PORTADA!$B$2,4,1),MOVIMIENTOS!$C:$C,Z$4)) | AA5: =IF(DAY(DATE(PORTADA!$B$2,4,1))<>1,"",SUM(T5:Z5))
A6: SUELDO | B6: QUINCENA | C6: =CATEGORIAS!$E$4 | D6: =SUMIFS(MOVIMIENTOS!$F:$F,MOVIMIENTOS!$A:$A,">="&DATE(PORTADA!$B$2,4,1),MOVIMIENTOS!$A:$A,"<="&EOMONTH(DATE(PORTADA!$B$2,4,1),0),MOVIMIENTOS!$D:$D,$B6) | E6: =D6-C6 | F6: =IFERROR(D6/C6,"") | S6: =IF(DAY(DATE(PORTADA!$B$2,4,2))<>2,"",2) | T6: =IF(DAY(DATE(PORTADA!$B$2,4,2))<>2,"",SUMIFS(MOVIMIENTOS!$F:$F,MOVIMIENTOS!$A:$A,DATE(PORTADA!$B$2,4,2),MOVIMIENTOS!$C:$C,T$4)) | U6: =IF(DAY(DATE(PORTADA!$B$2,4,2))<>2,"",SUMIFS(MOVIMIENTOS!$F:$F,MOVIMIENTOS!$A:$A,DATE(PORTADA!$B$2,4,2),MOVIMIENTOS!$C:$C,U$4)) | V6: =IF(DAY(DATE(PORTADA!$B$2,4,2))<>2,"",SUMIFS(MOVIMIENTOS!$F:$F,MOVIMIENTOS!$A:$A,DATE(PORTADA!$B$2,4,2),MOVIMIENTOS!$C:$C,V$4)) | W6: =IF(DAY(DATE(PORTADA!$B$2,4,2))<>2,"",SUMIFS(MOVIMIENTOS!$F:$F,MOVIMIENTOS!$A:$A,DATE(PORTADA!$B$2,4,2),MOVIMIENTOS!$C:$C,W$4)) | X6: =IF(DAY(DATE(PORTADA!$B$2,4,2))<>2,"",SUMIFS(MOVIMIENTOS!$F:$F,MOVIMIENTOS!$A:$A,DATE(PORTADA!$B$2,4,2),MOVIMIENTOS!$C:$C,X$4)) | Y6: =IF(DAY(DATE(PORTADA!$B$2,4,2))<>2,"",SUMIFS(MOVIMIENTOS!$F:$F,MOVIMIENTOS!$A:$A,DATE(PORTADA!$B$2,4,2),MOVIMIENTOS!$C:$C,Y$4)) | Z6: =IF(DAY(DATE(PORTADA!$B$2,4,2))<>2,"",SUMIFS(MOVIMIENTOS!$F:$F,MOVIMIENTOS!$A:$A,DATE(PORTADA!$B$2,4,2),MOVIMIENTOS!$C:$C,Z$4)) | AA6: =IF(DAY(DATE(PORTADA!$B$2,4,2))<>2,"",SUM(T6:Z6))
A7: SUELDO | B7: PAGO FIN DE MES | C7: =CATEGORIAS!$E$5 | D7: =SUMIFS(MOVIMIENTOS!$F:$F,MOVIMIENTOS!$A:$A,">="&DATE(PORTADA!$B$2,4,1),MOVIMIENTOS!$A:$A,"<="&EOMONTH(DATE(PORTADA!$B$2,4,1),0),MOVIMIENTOS!$D:$D,$B7) | E7: =D7-C7 | F7: =IFERROR(D7/C7,"") | S7: =IF(DAY(DATE(PORTADA!$B$2,4,3))<>3,"",3) | T7: =IF(DAY(DATE(PORTADA!$B$2,4,3))<>3,"",SUMIFS(MOVIMIENTOS!$F:$F,MOVIMIENTOS!$A:$A,DATE(PORTADA!$B$2,4,3),MOVIMIENTOS!$C:$C,T$4)) | U7: =IF(DAY(DATE(PORTADA!$B$2,4,3))<>3,"",SUMIFS(MOVIMIENTOS!$F:$F,MOVIMIENTOS!$A:$A,DATE(PORTADA!$B$2,4,3),MOVIMIENTOS!$C:$C,U$4)) | V7: =IF(DAY(DATE(PORTADA!$B$2,4,3))<>3,"",SUMIFS(MOVIMIENTOS!$F:$F,MOVIMIENTOS!$A:$A,DATE(PORTADA!$B$2,4,3),MOVIMIENTOS!$C:$C,V$4)) | W7: =IF(DAY(DATE(PORTADA!$B$2,4,3))<>3,"",SUMIFS(MOVIMIENTOS!$F:$F,MOVIMIENTOS!$A:$A,DATE(PORTADA!$B$2,4,3),MOVIMIENTOS!$C:$C,W$4)) | X7: =IF(DAY(DATE(PORTADA!$B$2,4,3))<>3,"",SUMIFS(MOVIMIENTOS!$F:$F,MOVIMIENTOS!$A:$A,DATE(PORTADA!$B$2,4,3),MOVIMIENTOS!$C:$C,X$4)) | Y7: =IF(DAY(DATE(PORTADA!$B$2,4,3))<>3,"",SUMIFS(MOVIMIENTOS!$F:$F,MOVIMIENTOS!$A:$A,DATE(PORTADA!$B$2,4,3),MOVIMIENTOS!$C:$C,Y$4)) | Z7: =IF(DAY(DATE(PORTADA!$B$2,4,3))<>3,"",SUMIFS(MOVIMIENTOS!$F:$F,MOVIMIENTOS!$A:$A,DATE(PORTADA!$B$2,4,3),MOVIMIENTOS!$C:$C,Z$4)) | AA7: =IF(DAY(DATE(PORTADA!$B$2,4,3))<>3,"",SUM(T7:Z7))
A8: NEGOCIO | B8: EFFICIENTCHILE | C8: =CATEGORIAS!$E$6 | D8: =SUMIFS(MOVIMIENTOS!$F:$F,MOVIMIENTOS!$A:$A,">="&DATE(PORTADA!$B$2,4,1),MOVIMIENTOS!$A:$A,"<="&EOMONTH(DATE(PORTADA!$B$2,4,1),0),MOVIMIENTOS!$D:$D,$B8) | E8: =D8-C8 | F8: =IFERROR(D8/C8,"") | S8: =IF(DAY(DATE(PORTADA!$B$2,4,4))<>4,"",4) | T8: =IF(DAY(DATE(PORTADA!$B$2,4,4))<>4,"",SUMIFS(MOVIMIENTOS!$F:$F,MOVIMIENTOS!$A:$A,DATE(PORTADA!$B$2,4,4),MOVIMIENTOS!$C:$C,T$4)) | U8: =IF(DAY(DATE(PORTADA!$B$2,4,4))<>4,"",SUMIFS(MOVIMIENTOS!$F:$F,MOVIMIENTOS!$A:$A,DATE(PORTADA!$B$2,4,4),MOVIMIENTOS!$C:$C,U$4)) | V8: =IF(DAY(DATE(PORTADA!$B$2,4,4))<>4,"",SUMIFS(MOVIMIENTOS!$F:$F,MOVIMIENTOS!$A:$A,DATE(PORTADA!$B$2,4,4),MOVIMIENTOS!$C:$C,V$4)) | W8: =IF(DAY(DATE(PORTADA!$B$2,4,4))<>4,"",SUMIFS(MOVIMIENTOS!$F:$F,MOVIMIENTOS!$A:$A,DATE(PORTADA!$B$2,4,4),MOVIMIENTOS!$C:$C,W$4)) | X8: =IF(DAY(DATE(PORTADA!$B$2,4,4))<>4,"",SUMIFS(MOVIMIENTOS!$F:$F,MOVIMIENTOS!$A:$A,DATE(PORTADA!$B$2,4,4),MOVIMIENTOS!$C:$C,X$4)) | Y8: =IF(DAY(DATE(PORTADA!$B$2,4,4))<>4,"",SUMIFS(MOVIMIENTOS!$F:$F,MOVIMIENTOS!$A:$A,DATE(PORTADA!$B$2,4,4),MOVIMIENTOS!$C:$C,Y$4)) | Z8: =IF(DAY(DATE(PORTADA!$B$2,4,4))<>4,"",SUMIFS(MOVIMIENTOS!$F:$F,MOVIMIENTOS!$A:$A,DATE(PORTADA!$B$2,4,4),MOVIMIENTOS!$C:$C,Z$4)) | AA8: =IF(DAY(DATE(PORTADA!$B$2,4,4))<>4,"",SUM(T8:Z8))
A9: NEGOCIO | B9: VENTA DE ARTICULO | C9: =CATEGORIAS!$E$7 | D9: =SUMIFS(MOVIMIENTOS!$F:$F,MOVIMIENTOS!$A:$A,">="&DATE(PORTADA!$B$2,4,1),MOVIMIENTOS!$A:$A,"<="&EOMONTH(DATE(PORTADA!$B$2,4,1),0),MOVIMIENTOS!$D:$D,$B9) | E9: =D9-C9 | F9: =IFERROR(D9/C9,"") | S9: =IF(DAY(DATE(PORTADA!$B$2,4,5))<>5,"",5) | T9: =IF(DAY(DATE(PORTADA!$B$2,4,5))<>5,"",SUMIFS(MOVIMIENTOS!$F:$F,MOVIMIENTOS!$A:$A,DATE(PORTADA!$B$2,4,5),MOVIMIENTOS!$C:$C,T$4)) | U9: =IF(DAY(DATE(PORTADA!$B$2,4,5))<>5,"",SUMIFS(MOVIMIENTOS!$F:$F,MOVIMIENTOS!$A:$A,DATE(PORTADA!$B$2,4,5),MOVIMIENTOS!$C:$C,U$4)) | V9: =IF(DAY(DATE(PORTADA!$B$2,4,5))<>5,"",SUMIFS(MOVIMIENTOS!$F:$F,MOVIMIENTOS!$A:$A,DATE(PORTADA!$B$2,4,5),MOVIMIENTOS!$C:$C,V$4)) | W9: =IF(DAY(DATE(PORTADA!$B$2,4,5))<>5,"",SUMIFS(MOVIMIENTOS!$F:$F,MOVIMIENTOS!$A:$A,DATE(PORTADA!$B$2,4,5),MOVIMIENTOS!$C:$C,W$4)) | X9: =IF(DAY(DATE(PORTADA!$B$2,4,5))<>5,"",SUMIFS(MOVIMIENTOS!$F:$F,MOVIMIENTOS!$A:$A,DATE(PORTADA!$B$2,4,5),MOVIMIENTOS!$C:$C,X$4)) | Y9: =IF(DAY(DATE(PORTADA!$B$2,4,5))<>5,"",SUMIFS(MOVIMIENTOS!$F:$F,MOVIMIENTOS!$A:$A,DATE(PORTADA!$B$2,4,5),MOVIMIENTOS!$C:$C,Y$4)) | Z9: =IF(DAY(DATE(PORTADA!$B$2,4,5))<>5,"",SUMIFS(MOVIMIENTOS!$F:$F,MOVIMIENTOS!$A:$A,DATE(PORTADA!$B$2,4,5),MOVIMIENTOS!$C:$C,Z$4)) | AA9: =IF(DAY(DATE(PORTADA!$B$2,4,5))<>5,"",SUM(T9:Z9))
A10: NEGOCIO | B10: VENTA DE SERVICIO | C10: =CATEGORIAS!$E$8 | D10: =SUMIFS(MOVIMIENTOS!$F:$F,MOVIMIENTOS!$A:$A,">="&DATE(PORTADA!$B$2,4,1),MOVIMIENTOS!$A:$A,"<="&EOMONTH(DATE(PORTADA!$B$2,4,1),0),MOVIMIENTOS!$D:$D,$B10) | E10: =D10-C10 | F10: =IFERROR(D10/C10,"") | S10: =IF(DAY(DATE(PORTADA!$B$2,4,6))<>6,"",6) | T10: =IF(DAY(DATE(PORTADA!$B$2,4,6))<>6,"",SUMIFS(MOVIMIENTOS!$F:$F,MOVIMIENTOS!$A:$A,DATE(PORTADA!$B$2,4,6),MOVIMIENTOS!$C:$C,T$4)) | U10: =IF(DAY(DATE(PORTADA!$B$2,4,6))<>6,"",SUMIFS(MOVIMIENTOS!$F:$F,MOVIMIENTOS!$A:$A,DATE(PORTADA!$B$2,4,6),MOVIMIENTOS!$C:$C,U$4)) | V10: =IF(DAY(DATE(PORTADA!$B$2,4,6))<>6,"",SUMIFS(MOVIMIENTOS!$F:$F,MOVIMIENTOS!$A:$A,DATE(PORTADA!$B$2,4,6),MOVIMIENTOS!$C:$C,V$4)) | W10: =IF(DAY(DATE(PORTADA!$B$2,4,6))<>6,"",SUMIFS(MOVIMIENTOS!$F:$F,MOVIMIENTOS!$A:$A,DATE(PORTADA!$B$2,4,6),MOVIMIENTOS!$C:$C,W$4)) | X10: =IF(DAY(DATE(PORTADA!$B$2,4,6))<>6,"",SUMIFS(MOVIMIENTOS!$F:$F,MOVIMIENTOS!$A:$A,DATE(PORTADA!$B$2,4,6),MOVIMIENTOS!$C:$C,X$4)) | Y10: =IF(DAY(DATE(PORTADA!$B$2,4,6))<>6,"",SUMIFS(MOVIMIENTOS!$F:$F,MOVIMIENTOS!$A:$A,DATE(PORTADA!$B$2,4,6),MOVIMIENTOS!$C:$C,Y$4)) | Z10: =IF(DAY(DATE(PORTADA!$B$2,4,6))<>6,"",SUMIFS(MOVIMIENTOS!$F:$F,MOVIMIENTOS!$A:$A,DATE(PORTADA!$B$2,4,6),MOVIMIENTOS!$C:$C,Z$4)) | AA10: =IF(DAY(DATE(PORTADA!$B$2,4,6))<>6,"",SUM(T10:Z10))
A11: OTROS | B11: COBROS PENDIENTES | C11: =CATEGORIAS!$E$9 | D11: =SUMIFS(MOVIMIENTOS!$F:$F,MOVIMIENTOS!$A:$A,">="&DATE(PORTADA!$B$2,4,1),MOVIMIENTOS!$A:$A,"<="&EOMONTH(DATE(PORTADA!$B$2,4,1),0),MOVIMIENTOS!$D:$D,$B11) | E11: =D11-C11 | F11: =IFERROR(D11/C11,"") | S11: =IF(DAY(DATE(PORTADA!$B$2,4,7))<>7,"",7) | T11: =IF(DAY(DATE(PORTADA!$B$2,4,7))<>7,"",SUMIFS(MOVIMIENTOS!$F:$F,MOVIMIENTOS!$A:$A,DATE(PORTADA!$B$2,4,7),MOVIMIENTOS!$C:$C,T$4)) | U11: =IF(DAY(DATE(PORTADA!$B$2,4,7))<>7,"",SUMIFS(MOVIMIENTOS!$F:$F,MOVIMIENTOS!$A:$A,DATE(PORTADA!$B$2,4,7),MOVIMIENTOS!$C:$C,U$4)) | V11: =IF(DAY(DATE(PORTADA!$B$2,4,7))<>7,"",SUMIFS(MOVIMIENTOS!$F:$F,MOVIMIENTOS!$A:$A,DATE(PORTADA!$B$2,4,7),MOVIMIENTOS!$C:$C,V$4)) | W11: =IF(DAY(DATE(PORTADA!$B$2,4,7))<>7,"",SUMIFS(MOVIMIENTOS!$F:$F,MOVIMIENTOS!$A:$A,DATE(PORTADA!$B$2,4,7),MOVIMIENTOS!$C:$C,W$4)) | X11: =IF(DAY(DATE(PORTADA!$B$2,4,7))<>7,"",SUMIFS(MOVIMIENTOS!$F:$F,MOVIMIENTOS!$A:$A,DATE(PORTADA!$B$2,4,7),MOVIMIENTOS!$C:$C,X$4)) | Y11: =IF(DAY(DATE(PORTADA!$B$2,4,7))<>7,"",SUMIFS(MOVIMIENTOS!$F:$F,MOVIMIENTOS!$A:$A,DATE(PORTADA!$B$2,4,7),MOVIMIENTOS!$C:$C,Y$4)) | Z11: =IF(DAY(DATE(PORTADA!$B$2,4,7))<>7,"",SUMIFS(MOVIMIENTOS!$F:$F,MOVIMIENTOS!$A:$A,DATE(PORTADA!$B$2,4,7),MOVIMIENTOS!$C:$C,Z$4)) | AA11: =IF(DAY(DATE(PORTADA!$B$2,4,7))<>7,"",SUM(T11:Z11))
A12: OTROS | B12: OTROS INGRESOS | C12: =CATEGORIAS!$E$10 | D12: =SUMIFS(MOVIMIENTOS!$F:$F,MOVIMIENTOS!$A:$A,">="&DATE(PORTADA!$B$2,4,1),MOVIMIENTOS!$A:$A,"<="&EOMONTH(DATE(PORTADA!$B$2,4,1),0),MOVIMIENTOS!$D:$D,$B12) | E12: =D12-C12 | F12: =IFERROR(D12/C12,"") | S12: =IF(DAY(DATE(PORTADA!$B$2,4,8))<>8,"",8) | T12: =IF(DAY(DATE(PORTADA!$B$2,4,8))<>8,"",SUMIFS(MOVIMIENTOS!$F:$F,MOVIMIENTOS!$A:$A,DATE(PORTADA!$B$2,4,8),MOVIMIENTOS!$C:$C,T$4)) | U12: =IF(DAY(DATE(PORTADA!$B$2,4,8))<>8,"",SUMIFS(MOVIMIENTOS!$F:$F,MOVIMIENTOS!$A:$A,DATE(PORTADA!$B$2,4,8),MOVIMIENTOS!$C:$C,U$4)) | V12: =IF(DAY(DATE(PORTADA!$B$2,4,8))<>8,"",SUMIFS(MOVIMIENTOS!$F:$F,MOVIMIENTOS!$A:$A,DATE(PORTADA!$B$2,4,8),MOVIMIENTOS!$C:$C,V$4)) | W12: =IF(DAY(DATE(PORTADA!$B$2,4,8))<>8,"",SUMIFS(MOVIMIENTOS!$F:$F,MOVIMIENTOS!$A:$A,DATE(PORTADA!$B$2,4,8),MOVIMIENTOS!$C:$C,W$4)) | X12: =IF(DAY(DATE(PORTADA!$B$2,4,8))<>8,"",SUMIFS(MOVIMIENTOS!$F:$F,MOVIMIENTOS!$A:$A,DATE(PORTADA!$B$2,4,8),MOVIMIENTOS!$C:$C,X$4)) | Y12: =IF(DAY(DATE(PORTADA!$B$2,4,8))<>8,"",SUMIFS(MOVIMIENTOS!$F:$F,MOVIMIENTOS!$A:$A,DATE(PORTADA!$B$2,4,8),MOVIMIENTOS!$C:$C,Y$4)) | Z12: =IF(DAY(DATE(PORTADA!$B$2,4,8))<>8,"",SUMIFS(MOVIMIENTOS!$F:$F,MOVIMIENTOS!$A:$A,DATE(PORTADA!$B$2,4,8),MOVIMIENTOS!$C:$C,Z$4)) | AA12: =IF(DAY(DATE(PORTADA!$B$2,4,8))<>8,"",SUM(T12:Z12))
B13: TOTAL INGRESOS | C13: =SUM(C6:C12) | D13: =SUM(D6:D12) | E13: =SUM(E6:E12) | S13: =IF(DAY(DATE(PORTADA!$B$2,4,9))<>9,"",9) | T13: =IF(DAY(DATE(PORTADA!$B$2,4,9))<>9,"",SUMIFS(MOVIMIENTOS!$F:$F,MOVIMIENTOS!$A:$A,DATE(PORTADA!$B$2,4,9),MOVIMIENTOS!$C:$C,T$4)) | U13: =IF(DAY(DATE(PORTADA!$B$2,4,9))<>9,"",SUMIFS(MOVIMIENTOS!$F:$F,MOVIMIENTOS!$A:$A,DATE(PORTADA!$B$2,4,9),MOVIMIENTOS!$C:$C,U$4)) | V13: =IF(DAY(DATE(PORTADA!$B$2,4,9))<>9,"",SUMIFS(MOVIMIENTOS!$F:$F,MOVIMIENTOS!$A:$A,DATE(PORTADA!$B$2,4,9),MOVIMIENTOS!$C:$C,V$4)) | W13: =IF(DAY(DATE(PORTADA!$B$2,4,9))<>9,"",SUMIFS(MOVIMIENTOS!$F:$F,MOVIMIENTOS!$A:$A,DATE(PORTADA!$B$2,4,9),MOVIMIENTOS!$C:$C,W$4)) | X13: =IF(DAY(DATE(PORTADA!$B$2,4,9))<>9,"",SUMIFS(MOVIMIENTOS!$F:$F,MOVIMIENTOS!$A:$A,DATE(PORTADA!$B$2,4,9),MOVIMIENTOS!$C:$C,X$4)) | Y13: =IF(DAY(DATE(PORTADA!$B$2,4,9))<>9,"",SUMIFS(MOVIMIENTOS!$F:$F,MOVIMIENTOS!$A:$A,DATE(PORTADA!$B$2,4,9),MOVIMIENTOS!$C:$C,Y$4)) | Z13: =IF(DAY(DATE(PORTADA!$B$2,4,9))<>9,"",SUMIFS(MOVIMIENTOS!$F:$F,MOVIMIENTOS!$A:$A,DATE(PORTADA!$B$2,4,9),MOVIMIENTOS!$C:$C,Z$4)) | AA13: =IF(DAY(DATE(PORTADA!$B$2,4,9))<>9,"",SUM(T13:Z13))
S14: =IF(DAY(DATE(PORTADA!$B$2,4,10))<>10,"",10) | T14: =IF(DAY(DATE(PORTADA!$B$2,4,10))<>10,"",SUMIFS(MOVIMIENTOS!$F:$F,MOVIMIENTOS!$A:$A,DATE(PORTADA!$B$2,4,10),MOVIMIENTOS!$C:$C,T$4)) | U14: =IF(DAY(DATE(PORTADA!$B$2,4,10))<>10,"",SUMIFS(MOVIMIENTOS!$F:$F,MOVIMIENTOS!$A:$A,DATE(PORTADA!$B$2,4,10),MOVIMIENTOS!$C:$C,U$4)) | V14: =IF(DAY(DATE(PORTADA!$B$2,4,10))<>10,"",SUMIFS(MOVIMIENTOS!$F:$F,MOVIMIENTOS!$A:$A,DATE(PORTADA!$B$2,4,10),MOVIMIENTOS!$C:$C,V$4)) | W14: =IF(DAY(DATE(PORTADA!$B$2,4,10))<>10,"",SUMIFS(MOVIMIENTOS!$F:$F,MOVIMIENTOS!$A:$A,DATE(PORTADA!$B$2,4,10),MOVIMIENTOS!$C:$C,W$4)) | X14: =IF(DAY(DATE(PORTADA!$B$2,4,10))<>10,"",SUMIFS(MOVIMIENTOS!$F:$F,MOVIMIENTOS!$A:$A,DATE(PORTADA!$B$2,4,10),MOVIMIENTOS!$C:$C,X$4)) | Y14: =IF(DAY(DATE(PORTADA!$B$2,4,10))<>10,"",SUMIFS(MOVIMIENTOS!$F:$F,MOVIMIENTOS!$A:$A,DATE(PORTADA!$B$2,4,10),MOVIMIENTOS!$C:$C,Y$4)) | Z14: =IF(DAY(DATE(PORTADA!$B$2,4,10))<>10,"",SUMIFS(MOVIMIENTOS!$F:$F,MOVIMIENTOS!$A:$A,DATE(PORTADA!$B$2,4,10),MOVIMIENTOS!$C:$C,Z$4)) | AA14: =IF(DAY(DATE(PORTADA!$B$2,4,10))<>10,"",SUM(T14:Z14))
A15: EGRESOS | S15: =IF(DAY(DATE(PORTADA!$B$2,4,11))<>11,"",11) | T15: =IF(DAY(DATE(PORTADA!$B$2,4,11))<>11,"",SUMIFS(MOVIMIENTOS!$F:$F,MOVIMIENTOS!$A:$A,DATE(PORTADA!$B$2,4,11),MOVIMIENTOS!$C:$C,T$4)) | U15: =IF(DAY(DATE(PORTADA!$B$2,4,11))<>11,"",SUMIFS(MOVIMIENTOS!$F:$F,MOVIMIENTOS!$A:$A,DATE(PORTADA!$B$2,4,11),MOVIMIENTOS!$C:$C,U$4)) | V15: =IF(DAY(DATE(PORTADA!$B$2,4,11))<>11,"",SUMIFS(MOVIMIENTOS!$F:$F,MOVIMIENTOS!$A:$A,DATE(PORTADA!$B$2,4,11),MOVIMIENTOS!$C:$C,V$4)) | W15: =IF(DAY(DATE(PORTADA!$B$2,4,11))<>11,"",SUMIFS(MOVIMIENTOS!$F:$F,MOVIMIENTOS!$A:$A,DATE(PORTADA!$B$2,4,11),MOVIMIENTOS!$C:$C,W$4)) | X15: =IF(DAY(DATE(PORTADA!$B$2,4,11))<>11,"",SUMIFS(MOVIMIENTOS!$F:$F,MOVIMIENTOS!$A:$A,DATE(PORTADA!$B$2,4,11),MOVIMIENTOS!$C:$C,X$4)) | Y15: =IF(DAY(DATE(PORTADA!$B$2,4,11))<>11,"",SUMIFS(MOVIMIENTOS!$F:$F,MOVIMIENTOS!$A:$A,DATE(PORTADA!$B$2,4,11),MOVIMIENTOS!$C:$C,Y$4)) | Z15: =IF(DAY(DATE(PORTADA!$B$2,4,11))<>11,"",SUMIFS(MOVIMIENTOS!$F:$F,MOVIMIENTOS!$A:$A,DATE(PORTADA!$B$2,4,11),MOVIMIENTOS!$C:$C,Z$4)) | AA15: =IF(DAY(DATE(PORTADA!$B$2,4,11))<>11,"",SUM(T15:Z15))
A16: GRUPO | B16: CATEGORÍA | C16: PRESUPUESTO | D16: REAL | E16: DIFERENCIA | F16: % USADO | S16: =IF(DAY(DATE(PORTADA!$B$2,4,12))<>12,"",12) | T16: =IF(DAY(DATE(PORTADA!$B$2,4,12))<>12,"",SUMIFS(MOVIMIENTOS!$F:$F,MOVIMIENTOS!$A:$A,DATE(PORTADA!$B$2,4,12),MOVIMIENTOS!$C:$C,T$4)) | U16: =IF(DAY(DATE(PORTADA!$B$2,4,12))<>12,"",SUMIFS(MOVIMIENTOS!$F:$F,MOVIMIENTOS!$A:$A,DATE(PORTADA!$B$2,4,12),MOVIMIENTOS!$C:$C,U$4)) | V16: =IF(DAY(DATE(PORTADA!$B$2,4,12))<>12,"",SUMIFS(MOVIMIENTOS!$F:$F,MOVIMIENTOS!$A:$A,DATE(PORTADA!$B$2,4,12),MOVIMIENTOS!$C:$C,V$4)) | W16: =IF(DAY(DATE(PORTADA!$B$2,4,12))<>12,"",SUMIFS(MOVIMIENTOS!$F:$F,MOVIMIENTOS!$A:$A,DATE(PORTADA!$B$2,4,12),MOVIMIENTOS!$C:$C,W$4)) | X16: =IF(DAY(DATE(PORTADA!$B$2,4,12))<>12,"",SUMIFS(MOVIMIENTOS!$F:$F,MOVIMIENTOS!$A:$A,DATE(PORTADA!$B$2,4,12),MOVIMIENTOS!$C:$C,X$4)) | Y16: =IF(DAY(DATE(PORTADA!$B$2,4,12))<>12,"",SUMIFS(MOVIMIENTOS!$F:$F,MOVIMIENTOS!$A:$A,DATE(PORTADA!$B$2,4,12),MOVIMIENTOS!$C:$C,Y$4)) | Z16: =IF(DAY(DATE(PORTADA!$B$2,4,12))<>12,"",SUMIFS(MOVIMIENTOS!$F:$F,MOVIMIENTOS!$A:$A,DATE(PORTADA!$B$2,4,12),MOVIMIENTOS!$C:$C,Z$4)) | AA16: =IF(DAY(DATE(PORTADA!$B$2,4,12))<>12,"",SUM(T16:Z16))
A17: CUENTAS PERSONALES | B17: PREST. AUTO | C17: =CATEGORIAS!$E$11 | D17: =SUMIFS(MOVIMIENTOS!$F:$F,MOVIMIENTOS!$A:$A,">="&DATE(PORTADA!$B$2,4,1),MOVIMIENTOS!$A:$A,"<="&EOMONTH(DATE(PORTADA!$B$2,4,1),0),MOVIMIENTOS!$D:$D,$B17) | E17: =C17-D17 | F17: =IFERROR(D17/C17,"") | S17: =IF(DAY(DATE(PORTADA!$B$2,4,13))<>13,"",13) | T17: =IF(DAY(DATE(PORTADA!$B$2,4,13))<>13,"",SUMIFS(MOVIMIENTOS!$F:$F,MOVIMIENTOS!$A:$A,DATE(PORTADA!$B$2,4,13),MOVIMIENTOS!$C:$C,T$4)) | U17: =IF(DAY(DATE(PORTADA!$B$2,4,13))<>13,"",SUMIFS(MOVIMIENTOS!$F:$F,MOVIMIENTOS!$A:$A,DATE(PORTADA!$B$2,4,13),MOVIMIENTOS!$C:$C,U$4)) | V17: =IF(DAY(DATE(PORTADA!$B$2,4,13))<>13,"",SUMIFS(MOVIMIENTOS!$F:$F,MOVIMIENTOS!$A:$A,DATE(PORTADA!$B$2,4,13),MOVIMIENTOS!$C:$C,V$4)) | W17: =IF(DAY(DATE(PORTADA!$B$2,4,13))<>13,"",SUMIFS(MOVIMIENTOS!$F:$F,MOVIMIENTOS!$A:$A,DATE(PORTADA!$B$2,4,13),MOVIMIENTOS!$C:$C,W$4)) | X17: =IF(DAY(DATE(PORTADA!$B$2,4,13))<>13,"",SUMIFS(MOVIMIENTOS!$F:$F,MOVIMIENTOS!$A:$A,DATE(PORTADA!$B$2,4,13),MOVIMIENTOS!$C:$C,X$4)) | Y17: =IF(DAY(DATE(PORTADA!$B$2,4,13))<>13,"",SUMIFS(MOVIMIENTOS!$F:$F,MOVIMIENTOS!$A:$A,DATE(PORTADA!$B$2,4,13),MOVIMIENTOS!$C:$C,Y$4)) | Z17: =IF(DAY(DATE(PORTADA!$B$2,4,13))<>13,"",SUMIFS(MOVIMIENTOS!$F:$F,MOVIMIENTOS!$A:$A,DATE(PORTADA!$B$2,4,13),MOVIMIENTOS!$C:$C,Z$4)) | AA17: =IF(DAY(DATE(PORTADA!$B$2,4,13))<>13,"",SUM(T17:Z17))
A18: CUENTAS PERSONALES | B18: AHORRO CASA | C18: =CATEGORIAS!$E$12 | D18: =SUMIFS(MOVIMIENTOS!$F:$F,MOVIMIENTOS!$A:$A,">="&DATE(PORTADA!$B$2,4,1),MOVIMIENTOS!$A:$A,"<="&EOMONTH(DATE(PORTADA!$B$2,4,1),0),MOVIMIENTOS!$D:$D,$B18) | E18: =C18-D18 | F18: =IFERROR(D18/C18,"") | S18: =IF(DAY(DATE(PORTADA!$B$2,4,14))<>14,"",14) | T18: =IF(DAY(DATE(PORTADA!$B$2,4,14))<>14,"",SUMIFS(MOVIMIENTOS!$F:$F,MOVIMIENTOS!$A:$A,DATE(PORTADA!$B$2,4,14),MOVIMIENTOS!$C:$C,T$4)) | U18: =IF(DAY(DATE(PORTADA!$B$2,4,14))<>14,"",SUMIFS(MOVIMIENTOS!$F:$F,MOVIMIENTOS!$A:$A,DATE(PORTADA!$B$2,4,14),MOVIMIENTOS!$C:$C,U$4)) | V18: =IF(DAY(DATE(PORTADA!$B$2,4,14))<>14,"",SUMIFS(MOVIMIENTOS!$F:$F,MOVIMIENTOS!$A:$A,DATE(PORTADA!$B$2,4,14),MOVIMIENTOS!$C:$C,V$4)) | W18: =IF(DAY(DATE(PORTADA!$B$2,4,14))<>14,"",SUMIFS(MOVIMIENTOS!$F:$F,MOVIMIENTOS!$A:$A,DATE(PORTADA!$B$2,4,14),MOVIMIENTOS!$C:$C,W$4)) | X18: =IF(DAY(DATE(PORTADA!$B$2,4,14))<>14,"",SUMIFS(MOVIMIENTOS!$F:$F,MOVIMIENTOS!$A:$A,DATE(PORTADA!$B$2,4,14),MOVIMIENTOS!$C:$C,X$4)) | Y18: =IF(DAY(DATE(PORTADA!$B$2,4,14))<>14,"",SUMIFS(MOVIMIENTOS!$F:$F,MOVIMIENTOS!$A:$A,DATE(PORTADA!$B$2,4,14),MOVIMIENTOS!$C:$C,Y$4)) | Z18: =IF(DAY(DATE(PORTADA!$B$2,4,14))<>14,"",SUMIFS(MOVIMIENTOS!$F:$F,MOVIMIENTOS!$A:$A,DATE(PORTADA!$B$2,4,14),MOVIMIENTOS!$C:$C,Z$4)) | AA18: =IF(DAY(DATE(PORTADA!$B$2,4,14))<>14,"",SUM(T18:Z18))
A19: HIJOS | B19: PENSIONES | C19: =CATEGORIAS!$E$13 | D19: =SUMIFS(MOVIMIENTOS!$F:$F,MOVIMIENTOS!$A:$A,">="&DATE(PORTADA!$B$2,4,1),MOVIMIENTOS!$A:$A,"<="&EOMONTH(DATE(PORTADA!$B$2,4,1),0),MOVIMIENTOS!$D:$D,$B19) | E19: =C19-D19 | F19: =IFERROR(D19/C19,"") | S19: =IF(DAY(DATE(PORTADA!$B$2,4,15))<>15,"",15) | T19: =IF(DAY(DATE(PORTADA!$B$2,4,15))<>15,"",SUMIFS(MOVIMIENTOS!$F:$F,MOVIMIENTOS!$A:$A,DATE(PORTADA!$B$2,4,15),MOVIMIENTOS!$C:$C,T$4)) | U19: =IF(DAY(DATE(PORTADA!$B$2,4,15))<>15,"",SUMIFS(MOVIMIENTOS!$F:$F,MOVIMIENTOS!$A:$A,DATE(PORTADA!$B$2,4,15),MOVIMIENTOS!$C:$C,U$4)) | V19: =IF(DAY(DATE(PORTADA!$B$2,4,15))<>15,"",SUMIFS(MOVIMIENTOS!$F:$F,MOVIMIENTOS!$A:$A,DATE(PORTADA!$B$2,4,15),MOVIMIENTOS!$C:$C,V$4)) | W19: =IF(DAY(DATE(PORTADA!$B$2,4,15))<>15,"",SUMIFS(MOVIMIENTOS!$F:$F,MOVIMIENTOS!$A:$A,DATE(PORTADA!$B$2,4,15),MOVIMIENTOS!$C:$C,W$4)) | X19: =IF(DAY(DATE(PORTADA!$B$2,4,15))<>15,"",SUMIFS(MOVIMIENTOS!$F:$F,MOVIMIENTOS!$A:$A,DATE(PORTADA!$B$2,4,15),MOVIMIENTOS!$C:$C,X$4)) | Y19: =IF(DAY(DATE(PORTADA!$B$2,4,15))<>15,"",SUMIFS(MOVIMIENTOS!$F:$F,MOVIMIENTOS!$A:$A,DATE(PORTADA!$B$2,4,15),MOVIMIENTOS!$C:$C,Y$4)) | Z19: =IF(DAY(DATE(PORTADA!$B$2,4,15))<>15,"",SUMIFS(MOVIMIENTOS!$F:$F,MOVIMIENTOS!$A:$A,DATE(PORTADA!$B$2,4,15),MOVIMIENTOS!$C:$C,Z$4)) | AA19: =IF(DAY(DATE(PORTADA!$B$2,4,15))<>15,"",SUM(T19:Z19))
A20: HIJOS | B20: ROPA Y REGALOS | C20: =CATEGORIAS!$E$14 | D20: =SUMIFS(MOVIMIENTOS!$F:$F,MOVIMIENTOS!$A:$A,">="&DATE(PORTADA!$B$2,4,1),MOVIMIENTOS!$A:$A,"<="&EOMONTH(DATE(PORTADA!$B$2,4,1),0),MOVIMIENTOS!$D:$D,$B20) | E20: =C20-D20 | F20: =IFERROR(D20/C20,"") | S20: =IF(DAY(DATE(PORTADA!$B$2,4,16))<>16,"",16) | T20: =IF(DAY(DATE(PORTADA!$B$2,4,16))<>16,"",SUMIFS(MOVIMIENTOS!$F:$F,MOVIMIENTOS!$A:$A,DATE(PORTADA!$B$2,4,16),MOVIMIENTOS!$C:$C,T$4)) | U20: =IF(DAY(DATE(PORTADA!$B$2,4,16))<>16,"",SUMIFS(MOVIMIENTOS!$F:$F,MOVIMIENTOS!$A:$A,DATE(PORTADA!$B$2,4,16),MOVIMIENTOS!$C:$C,U$4)) | V20: =IF(DAY(DATE(PORTADA!$B$2,4,16))<>16,"",SUMIFS(MOVIMIENTOS!$F:$F,MOVIMIENTOS!$A:$A,DATE(PORTADA!$B$2,4,16),MOVIMIENTOS!$C:$C,V$4)) | W20: =IF(DAY(DATE(PORTADA!$B$2,4,16))<>16,"",SUMIFS(MOVIMIENTOS!$F:$F,MOVIMIENTOS!$A:$A,DATE(PORTADA!$B$2,4,16),MOVIMIENTOS!$C:$C,W$4)) | X20: =IF(DAY(DATE(PORTADA!$B$2,4,16))<>16,"",SUMIFS(MOVIMIENTOS!$F:$F,MOVIMIENTOS!$A:$A,DATE(PORTADA!$B$2,4,16),MOVIMIENTOS!$C:$C,X$4)) | Y20: =IF(DAY(DATE(PORTADA!$B$2,4,16))<>16,"",SUMIFS(MOVIMIENTOS!$F:$F,MOVIMIENTOS!$A:$A,DATE(PORTADA!$B$2,4,16),MOVIMIENTOS!$C:$C,Y$4)) | Z20: =IF(DAY(DATE(PORTADA!$B$2,4,16))<>16,"",SUMIFS(MOVIMIENTOS!$F:$F,MOVIMIENTOS!$A:$A,DATE(PORTADA!$B$2,4,16),MOVIMIENTOS!$C:$C,Z$4)) | AA20: =IF(DAY(DATE(PORTADA!$B$2,4,16))<>16,"",SUM(T20:Z20))
A21: HIJOS | B21: AHORRO EMERGENCIAS | C21: =CATEGORIAS!$E$15 | D21: =SUMIFS(MOVIMIENTOS!$F:$F,MOVIMIENTOS!$A:$A,">="&DATE(PORTADA!$B$2,4,1),MOVIMIENTOS!$A:$A,"<="&EOMONTH(DATE(PORTADA!$B$2,4,1),0),MOVIMIENTOS!$D:$D,$B21) | E21: =C21-D21 | F21: =IFERROR(D21/C21,"") | S21: =IF(DAY(DATE(PORTADA!$B$2,4,17))<>17,"",17) | T21: =IF(DAY(DATE(PORTADA!$B$2,4,17))<>17,"",SUMIFS(MOVIMIENTOS!$F:$F,MOVIMIENTOS!$A:$A,DATE(PORTADA!$B$2,4,17),MOVIMIENTOS!$C:$C,T$4)) | U21: =IF(DAY(DATE(PORTADA!$B$2,4,17))<>17,"",SUMIFS(MOVIMIENTOS!$F:$F,MOVIMIENTOS!$A:$A,DATE(PORTADA!$B$2,4,17),MOVIMIENTOS!$C:$C,U$4)) | V21: =IF(DAY(DATE(PORTADA!$B$2,4,17))<>17,"",SUMIFS(MOVIMIENTOS!$F:$F,MOVIMIENTOS!$A:$A,DATE(PORTADA!$B$2,4,17),MOVIMIENTOS!$C:$C,V$4)) | W21: =IF(DAY(DATE(PORTADA!$B$2,4,17))<>17,"",SUMIFS(MOVIMIENTOS!$F:$F,MOVIMIENTOS!$A:$A,DATE(PORTADA!$B$2,4,17),MOVIMIENTOS!$C:$C,W$4)) | X21: =IF(DAY(DATE(PORTADA!$B$2,4,17))<>17,"",SUMIFS(MOVIMIENTOS!$F:$F,MOVIMIENTOS!$A:$A,DATE(PORTADA!$B$2,4,17),MOVIMIENTOS!$C:$C,X$4)) | Y21: =IF(DAY(DATE(PORTADA!$B$2,4,17))<>17,"",SUMIFS(MOVIMIENTOS!$F:$F,MOVIMIENTOS!$A:$A,DATE(PORTADA!$B$2,4,17),MOVIMIENTOS!$C:$C,Y$4)) | Z21: =IF(DAY(DATE(PORTADA!$B$2,4,17))<>17,"",SUMIFS(MOVIMIENTOS!$F:$F,MOVIMIENTOS!$A:$A,DATE(PORTADA!$B$2,4,17),MOVIMIENTOS!$C:$C,Z$4)) | AA21: =IF(DAY(DATE(PORTADA!$B$2,4,17))<>17,"",SUM(T21:Z21))
A22: HIJOS | B22: SALIDAS CON FAMILIA | C22: =CATEGORIAS!$E$16 | D22: =SUMIFS(MOVIMIENTOS!$F:$F,MOVIMIENTOS!$A:$A,">="&DATE(PORTADA!$B$2,4,1),MOVIMIENTOS!$A:$A,"<="&EOMONTH(DATE(PORTADA!$B$2,4,1),0),MOVIMIENTOS!$D:$D,$B22) | E22: =C22-D22 | F22: =IFERROR(D22/C22,"") | S22: =IF(DAY(DATE(PORTADA!$B$2,4,18))<>18,"",18) | T22: =IF(DAY(DATE(PORTADA!$B$2,4,18))<>18,"",SUMIFS(MOVIMIENTOS!$F:$F,MOVIMIENTOS!$A:$A,DATE(PORTADA!$B$2,4,18),MOVIMIENTOS!$C:$C,T$4)) | U22: =IF(DAY(DATE(PORTADA!$B$2,4,18))<>18,"",SUMIFS(MOVIMIENTOS!$F:$F,MOVIMIENTOS!$A:$A,DATE(PORTADA!$B$2,4,18),MOVIMIENTOS!$C:$C,U$4)) | V22: =IF(DAY(DATE(PORTADA!$B$2,4,18))<>18,"",SUMIFS(MOVIMIENTOS!$F:$F,MOVIMIENTOS!$A:$A,DATE(PORTADA!$B$2,4,18),MOVIMIENTOS!$C:$C,V$4)) | W22: =IF(DAY(DATE(PORTADA!$B$2,4,18))<>18,"",SUMIFS(MOVIMIENTOS!$F:$F,MOVIMIENTOS!$A:$A,DATE(PORTADA!$B$2,4,18),MOVIMIENTOS!$C:$C,W$4)) | X22: =IF(DAY(DATE(PORTADA!$B$2,4,18))<>18,"",SUMIFS(MOVIMIENTOS!$F:$F,MOVIMIENTOS!$A:$A,DATE(PORTADA!$B$2,4,18),MOVIMIENTOS!$C:$C,X$4)) | Y22: =IF(DAY(DATE(PORTADA!$B$2,4,18))<>18,"",SUMIFS(MOVIMIENTOS!$F:$F,MOVIMIENTOS!$A:$A,DATE(PORTADA!$B$2,4,18),MOVIMIENTOS!$C:$C,Y$4)) | Z22: =IF(DAY(DATE(PORTADA!$B$2,4,18))<>18,"",SUMIFS(MOVIMIENTOS!$F:$F,MOVIMIENTOS!$A:$A,DATE(PORTADA!$B$2,4,18),MOVIMIENTOS!$C:$C,Z$4)) | AA22: =IF(DAY(DATE(PORTADA!$B$2,4,18))<>18,"",SUM(T22:Z22))
A23: CASA | B23: COMIDA CASA | C23: =CATEGORIAS!$E$17 | D23: =SUMIFS(MOVIMIENTOS!$F:$F,MOVIMIENTOS!$A:$A,">="&DATE(PORTADA!$B$2,4,1),MOVIMIENTOS!$A:$A,"<="&EOMONTH(DATE(PORTADA!$B$2,4,1),0),MOVIMIENTOS!$D:$D,$B23) | E23: =C23-D23 | F23: =IFERROR(D23/C23,"") | S23: =IF(DAY(DATE(PORTADA!$B$2,4,19))<>19,"",19) | T23: =IF(DAY(DATE(PORTADA!$B$2,4,19))<>19,"",SUMIFS(MOVIMIENTOS!$F:$F,MOVIMIENTOS!$A:$A,DATE(PORTADA!$B$2,4,19),MOVIMIENTOS!$C:$C,T$4)) | U23: =IF(DAY(DATE(PORTADA!$B$2,4,19))<>19,"",SUMIFS(MOVIMIENTOS!$F:$F,MOVIMIENTOS!$A:$A,DATE(PORTADA!$B$2,4,19),MOVIMIENTOS!$C:$C,U$4)) | V23: =IF(DAY(DATE(PORTADA!$B$2,4,19))<>19,"",SUMIFS(MOVIMIENTOS!$F:$F,MOVIMIENTOS!$A:$A,DATE(PORTADA!$B$2,4,19),MOVIMIENTOS!$C:$C,V$4)) | W23: =IF(DAY(DATE(PORTADA!$B$2,4,19))<>19,"",SUMIFS(MOVIMIENTOS!$F:$F,MOVIMIENTOS!$A:$A,DATE(PORTADA!$B$2,4,19),MOVIMIENTOS!$C:$C,W$4)) | X23: =IF(DAY(DATE(PORTADA!$B$2,4,19))<>19,"",SUMIFS(MOVIMIENTOS!$F:$F,MOVIMIENTOS!$A:$A,DATE(PORTADA!$B$2,4,19),MOVIMIENTOS!$C:$C,X$4)) | Y23: =IF(DAY(DATE(PORTADA!$B$2,4,19))<>19,"",SUMIFS(MOVIMIENTOS!$F:$F,MOVIMIENTOS!$A:$A,DATE(PORTADA!$B$2,4,19),MOVIMIENTOS!$C:$C,Y$4)) | Z23: =IF(DAY(DATE(PORTADA!$B$2,4,19))<>19,"",SUMIFS(MOVIMIENTOS!$F:$F,MOVIMIENTOS!$A:$A,DATE(PORTADA!$B$2,4,19),MOVIMIENTOS!$C:$C,Z$4)) | AA23: =IF(DAY(DATE(PORTADA!$B$2,4,19))<>19,"",SUM(T23:Z23))
A24: CASA | B24: COMIDA PERSONAL | C24: =CATEGORIAS!$E$18 | D24: =SUMIFS(MOVIMIENTOS!$F:$F,MOVIMIENTOS!$A:$A,">="&DATE(PORTADA!$B$2,4,1),MOVIMIENTOS!$A:$A,"<="&EOMONTH(DATE(PORTADA!$B$2,4,1),0),MOVIMIENTOS!$D:$D,$B24) | E24: =C24-D24 | F24: =IFERROR(D24/C24,"") | S24: =IF(DAY(DATE(PORTADA!$B$2,4,20))<>20,"",20) | T24: =IF(DAY(DATE(PORTADA!$B$2,4,20))<>20,"",SUMIFS(MOVIMIENTOS!$F:$F,MOVIMIENTOS!$A:$A,DATE(PORTADA!$B$2,4,20),MOVIMIENTOS!$C:$C,T$4)) | U24: =IF(DAY(DATE(PORTADA!$B$2,4,20))<>20,"",SUMIFS(MOVIMIENTOS!$F:$F,MOVIMIENTOS!$A:$A,DATE(PORTADA!$B$2,4,20),MOVIMIENTOS!$C:$C,U$4)) | V24: =IF(DAY(DATE(PORTADA!$B$2,4,20))<>20,"",SUMIFS(MOVIMIENTOS!$F:$F,MOVIMIENTOS!$A:$A,DATE(PORTADA!$B$2,4,20),MOVIMIENTOS!$C:$C,V$4)) | W24: =IF(DAY(DATE(PORTADA!$B$2,4,20))<>20,"",SUMIFS(MOVIMIENTOS!$F:$F,MOVIMIENTOS!$A:$A,DATE(PORTADA!$B$2,4,20),MOVIMIENTOS!$C:$C,W$4)) | X24: =IF(DAY(DATE(PORTADA!$B$2,4,20))<>20,"",SUMIFS(MOVIMIENTOS!$F:$F,MOVIMIENTOS!$A:$A,DATE(PORTADA!$B$2,4,20),MOVIMIENTOS!$C:$C,X$4)) | Y24: =IF(DAY(DATE(PORTADA!$B$2,4,20))<>20,"",SUMIFS(MOVIMIENTOS!$F:$F,MOVIMIENTOS!$A:$A,DATE(PORTADA!$B$2,4,20),MOVIMIENTOS!$C:$C,Y$4)) | Z24: =IF(DAY(DATE(PORTADA!$B$2,4,20))<>20,"",SUMIFS(MOVIMIENTOS!$F:$F,MOVIMIENTOS!$A:$A,DATE(PORTADA!$B$2,4,20),MOVIMIENTOS!$C:$C,Z$4)) | AA24: =IF(DAY(DATE(PORTADA!$B$2,4,20))<>20,"",SUM(T24:Z24))
A25: CASA | B25: CUENTAS | C25: =CATEGORIAS!$E$19 | D25: =SUMIFS(MOVIMIENTOS!$F:$F,MOVIMIENTOS!$A:$A,">="&DATE(PORTADA!$B$2,4,1),MOVIMIENTOS!$A:$A,"<="&EOMONTH(DATE(PORTADA!$B$2,4,1),0),MOVIMIENTOS!$D:$D,$B25) | E25: =C25-D25 | F25: =IFERROR(D25/C25,"") | S25: =IF(DAY(DATE(PORTADA!$B$2,4,21))<>21,"",21) | T25: =IF(DAY(DATE(PORTADA!$B$2,4,21))<>21,"",SUMIFS(MOVIMIENTOS!$F:$F,MOVIMIENTOS!$A:$A,DATE(PORTADA!$B$2,4,21),MOVIMIENTOS!$C:$C,T$4)) | U25: =IF(DAY(DATE(PORTADA!$B$2,4,21))<>21,"",SUMIFS(MOVIMIENTOS!$F:$F,MOVIMIENTOS!$A:$A,DATE(PORTADA!$B$2,4,21),MOVIMIENTOS!$C:$C,U$4)) | V25: =IF(DAY(DATE(PORTADA!$B$2,4,21))<>21,"",SUMIFS(MOVIMIENTOS!$F:$F,MOVIMIENTOS!$A:$A,DATE(PORTADA!$B$2,4,21),MOVIMIENTOS!$C:$C,V$4)) | W25: =IF(DAY(DATE(PORTADA!$B$2,4,21))<>21,"",SUMIFS(MOVIMIENTOS!$F:$F,MOVIMIENTOS!$A:$A,DATE(PORTADA!$B$2,4,21),MOVIMIENTOS!$C:$C,W$4)) | X25: =IF(DAY(DATE(PORTADA!$B$2,4,21))<>21,"",SUMIFS(MOVIMIENTOS!$F:$F,MOVIMIENTOS!$A:$A,DATE(PORTADA!$B$2,4,21),MOVIMIENTOS!$C:$C,X$4)) | Y25: =IF(DAY(DATE(PORTADA!$B$2,4,21))<>21,"",SUMIFS(MOVIMIENTOS!$F:$F,MOVIMIENTOS!$A:$A,DATE(PORTADA!$B$2,4,21),MOVIMIENTOS!$C:$C,Y$4)) | Z25: =IF(DAY(DATE(PORTADA!$B$2,4,21))<>21,"",SUMIFS(MOVIMIENTOS!$F:$F,MOVIMIENTOS!$A:$A,DATE(PORTADA!$B$2,4,21),MOVIMIENTOS!$C:$C,Z$4)) | AA25: =IF(DAY(DATE(PORTADA!$B$2,4,21))<>21,"",SUM(T25:Z25))
A26: SALUD | B26: MEDICAMENTOS | C26: =CATEGORIAS!$E$20 | D26: =SUMIFS(MOVIMIENTOS!$F:$F,MOVIMIENTOS!$A:$A,">="&DATE(PORTADA!$B$2,4,1),MOVIMIENTOS!$A:$A,"<="&EOMONTH(DATE(PORTADA!$B$2,4,1),0),MOVIMIENTOS!$D:$D,$B26) | E26: =C26-D26 | F26: =IFERROR(D26/C26,"") | S26: =IF(DAY(DATE(PORTADA!$B$2,4,22))<>22,"",22) | T26: =IF(DAY(DATE(PORTADA!$B$2,4,22))<>22,"",SUMIFS(MOVIMIENTOS!$F:$F,MOVIMIENTOS!$A:$A,DATE(PORTADA!$B$2,4,22),MOVIMIENTOS!$C:$C,T$4)) | U26: =IF(DAY(DATE(PORTADA!$B$2,4,22))<>22,"",SUMIFS(MOVIMIENTOS!$F:$F,MOVIMIENTOS!$A:$A,DATE(PORTADA!$B$2,4,22),MOVIMIENTOS!$C:$C,U$4)) | V26: =IF(DAY(DATE(PORTADA!$B$2,4,22))<>22,"",SUMIFS(MOVIMIENTOS!$F:$F,MOVIMIENTOS!$A:$A,DATE(PORTADA!$B$2,4,22),MOVIMIENTOS!$C:$C,V$4)) | W26: =IF(DAY(DATE(PORTADA!$B$2,4,22))<>22,"",SUMIFS(MOVIMIENTOS!$F:$F,MOVIMIENTOS!$A:$A,DATE(PORTADA!$B$2,4,22),MOVIMIENTOS!$C:$C,W$4)) | X26: =IF(DAY(DATE(PORTADA!$B$2,4,22))<>22,"",SUMIFS(MOVIMIENTOS!$F:$F,MOVIMIENTOS!$A:$A,DATE(PORTADA!$B$2,4,22),MOVIMIENTOS!$C:$C,X$4)) | Y26: =IF(DAY(DATE(PORTADA!$B$2,4,22))<>22,"",SUMIFS(MOVIMIENTOS!$F:$F,MOVIMIENTOS!$A:$A,DATE(PORTADA!$B$2,4,22),MOVIMIENTOS!$C:$C,Y$4)) | Z26: =IF(DAY(DATE(PORTADA!$B$2,4,22))<>22,"",SUMIFS(MOVIMIENTOS!$F:$F,MOVIMIENTOS!$A:$A,DATE(PORTADA!$B$2,4,22),MOVIMIENTOS!$C:$C,Z$4)) | AA26: =IF(DAY(DATE(PORTADA!$B$2,4,22))<>22,"",SUM(T26:Z26))
A27: SALUD | B27: ROPA | C27: =CATEGORIAS!$E$21 | D27: =SUMIFS(MOVIMIENTOS!$F:$F,MOVIMIENTOS!$A:$A,">="&DATE(PORTADA!$B$2,4,1),MOVIMIENTOS!$A:$A,"<="&EOMONTH(DATE(PORTADA!$B$2,4,1),0),MOVIMIENTOS!$D:$D,$B27) | E27: =C27-D27 | F27: =IFERROR(D27/C27,"") | S27: =IF(DAY(DATE(PORTADA!$B$2,4,23))<>23,"",23) | T27: =IF(DAY(DATE(PORTADA!$B$2,4,23))<>23,"",SUMIFS(MOVIMIENTOS!$F:$F,MOVIMIENTOS!$A:$A,DATE(PORTADA!$B$2,4,23),MOVIMIENTOS!$C:$C,T$4)) | U27: =IF(DAY(DATE(PORTADA!$B$2,4,23))<>23,"",SUMIFS(MOVIMIENTOS!$F:$F,MOVIMIENTOS!$A:$A,DATE(PORTADA!$B$2,4,23),MOVIMIENTOS!$C:$C,U$4)) | V27: =IF(DAY(DATE(PORTADA!$B$2,4,23))<>23,"",SUMIFS(MOVIMIENTOS!$F:$F,MOVIMIENTOS!$A:$A,DATE(PORTADA!$B$2,4,23),MOVIMIENTOS!$C:$C,V$4)) | W27: =IF(DAY(DATE(PORTADA!$B$2,4,23))<>23,"",SUMIFS(MOVIMIENTOS!$F:$F,MOVIMIENTOS!$A:$A,DATE(PORTADA!$B$2,4,23),MOVIMIENTOS!$C:$C,W$4)) | X27: =IF(DAY(DATE(PORTADA!$B$2,4,23))<>23,"",SUMIFS(MOVIMIENTOS!$F:$F,MOVIMIENTOS!$A:$A,DATE(PORTADA!$B$2,4,23),MOVIMIENTOS!$C:$C,X$4)) | Y27: =IF(DAY(DATE(PORTADA!$B$2,4,23))<>23,"",SUMIFS(MOVIMIENTOS!$F:$F,MOVIMIENTOS!$A:$A,DATE(PORTADA!$B$2,4,23),MOVIMIENTOS!$C:$C,Y$4)) | Z27: =IF(DAY(DATE(PORTADA!$B$2,4,23))<>23,"",SUMIFS(MOVIMIENTOS!$F:$F,MOVIMIENTOS!$A:$A,DATE(PORTADA!$B$2,4,23),MOVIMIENTOS!$C:$C,Z$4)) | AA27: =IF(DAY(DATE(PORTADA!$B$2,4,23))<>23,"",SUM(T27:Z27))
A28: SALUD | B28: DEPORTE | C28: =CATEGORIAS!$E$22 | D28: =SUMIFS(MOVIMIENTOS!$F:$F,MOVIMIENTOS!$A:$A,">="&DATE(PORTADA!$B$2,4,1),MOVIMIENTOS!$A:$A,"<="&EOMONTH(DATE(PORTADA!$B$2,4,1),0),MOVIMIENTOS!$D:$D,$B28) | E28: =C28-D28 | F28: =IFERROR(D28/C28,"") | S28: =IF(DAY(DATE(PORTADA!$B$2,4,24))<>24,"",24) | T28: =IF(DAY(DATE(PORTADA!$B$2,4,24))<>24,"",SUMIFS(MOVIMIENTOS!$F:$F,MOVIMIENTOS!$A:$A,DATE(PORTADA!$B$2,4,24),MOVIMIENTOS!$C:$C,T$4)) | U28: =IF(DAY(DATE(PORTADA!$B$2,4,24))<>24,"",SUMIFS(MOVIMIENTOS!$F:$F,MOVIMIENTOS!$A:$A,DATE(PORTADA!$B$2,4,24),MOVIMIENTOS!$C:$C,U$4)) | V28: =IF(DAY(DATE(PORTADA!$B$2,4,24))<>24,"",SUMIFS(MOVIMIENTOS!$F:$F,MOVIMIENTOS!$A:$A,DATE(PORTADA!$B$2,4,24),MOVIMIENTOS!$C:$C,V$4)) | W28: =IF(DAY(DATE(PORTADA!$B$2,4,24))<>24,"",SUMIFS(MOVIMIENTOS!$F:$F,MOVIMIENTOS!$A:$A,DATE(PORTADA!$B$2,4,24),MOVIMIENTOS!$C:$C,W$4)) | X28: =IF(DAY(DATE(PORTADA!$B$2,4,24))<>24,"",SUMIFS(MOVIMIENTOS!$F:$F,MOVIMIENTOS!$A:$A,DATE(PORTADA!$B$2,4,24),MOVIMIENTOS!$C:$C,X$4)) | Y28: =IF(DAY(DATE(PORTADA!$B$2,4,24))<>24,"",SUMIFS(MOVIMIENTOS!$F:$F,MOVIMIENTOS!$A:$A,DATE(PORTADA!$B$2,4,24),MOVIMIENTOS!$C:$C,Y$4)) | Z28: =IF(DAY(DATE(PORTADA!$B$2,4,24))<>24,"",SUMIFS(MOVIMIENTOS!$F:$F,MOVIMIENTOS!$A:$A,DATE(PORTADA!$B$2,4,24),MOVIMIENTOS!$C:$C,Z$4)) | AA28: =IF(DAY(DATE(PORTADA!$B$2,4,24))<>24,"",SUM(T28:Z28))
A29: AUTO | B29: BENCINA | C29: =CATEGORIAS!$E$23 | D29: =SUMIFS(MOVIMIENTOS!$F:$F,MOVIMIENTOS!$A:$A,">="&DATE(PORTADA!$B$2,4,1),MOVIMIENTOS!$A:$A,"<="&EOMONTH(DATE(PORTADA!$B$2,4,1),0),MOVIMIENTOS!$D:$D,$B29) | E29: =C29-D29 | F29: =IFERROR(D29/C29,"") | S29: =IF(DAY(DATE(PORTADA!$B$2,4,25))<>25,"",25) | T29: =IF(DAY(DATE(PORTADA!$B$2,4,25))<>25,"",SUMIFS(MOVIMIENTOS!$F:$F,MOVIMIENTOS!$A:$A,DATE(PORTADA!$B$2,4,25),MOVIMIENTOS!$C:$C,T$4)) | U29: =IF(DAY(DATE(PORTADA!$B$2,4,25))<>25,"",SUMIFS(MOVIMIENTOS!$F:$F,MOVIMIENTOS!$A:$A,DATE(PORTADA!$B$2,4,25),MOVIMIENTOS!$C:$C,U$4)) | V29: =IF(DAY(DATE(PORTADA!$B$2,4,25))<>25,"",SUMIFS(MOVIMIENTOS!$F:$F,MOVIMIENTOS!$A:$A,DATE(PORTADA!$B$2,4,25),MOVIMIENTOS!$C:$C,V$4)) | W29: =IF(DAY(DATE(PORTADA!$B$2,4,25))<>25,"",SUMIFS(MOVIMIENTOS!$F:$F,MOVIMIENTOS!$A:$A,DATE(PORTADA!$B$2,4,25),MOVIMIENTOS!$C:$C,W$4)) | X29: =IF(DAY(DATE(PORTADA!$B$2,4,25))<>25,"",SUMIFS(MOVIMIENTOS!$F:$F,MOVIMIENTOS!$A:$A,DATE(PORTADA!$B$2,4,25),MOVIMIENTOS!$C:$C,X$4)) | Y29: =IF(DAY(DATE(PORTADA!$B$2,4,25))<>25,"",SUMIFS(MOVIMIENTOS!$F:$F,MOVIMIENTOS!$A:$A,DATE(PORTADA!$B$2,4,25),MOVIMIENTOS!$C:$C,Y$4)) | Z29: =IF(DAY(DATE(PORTADA!$B$2,4,25))<>25,"",SUMIFS(MOVIMIENTOS!$F:$F,MOVIMIENTOS!$A:$A,DATE(PORTADA!$B$2,4,25),MOVIMIENTOS!$C:$C,Z$4)) | AA29: =IF(DAY(DATE(PORTADA!$B$2,4,25))<>25,"",SUM(T29:Z29))
A30: AUTO | B30: OTROS | C30: =CATEGORIAS!$E$24 | D30: =SUMIFS(MOVIMIENTOS!$F:$F,MOVIMIENTOS!$A:$A,">="&DATE(PORTADA!$B$2,4,1),MOVIMIENTOS!$A:$A,"<="&EOMONTH(DATE(PORTADA!$B$2,4,1),0),MOVIMIENTOS!$D:$D,$B30) | E30: =C30-D30 | F30: =IFERROR(D30/C30,"") | S30: =IF(DAY(DATE(PORTADA!$B$2,4,26))<>26,"",26) | T30: =IF(DAY(DATE(PORTADA!$B$2,4,26))<>26,"",SUMIFS(MOVIMIENTOS!$F:$F,MOVIMIENTOS!$A:$A,DATE(PORTADA!$B$2,4,26),MOVIMIENTOS!$C:$C,T$4)) | U30: =IF(DAY(DATE(PORTADA!$B$2,4,26))<>26,"",SUMIFS(MOVIMIENTOS!$F:$F,MOVIMIENTOS!$A:$A,DATE(PORTADA!$B$2,4,26),MOVIMIENTOS!$C:$C,U$4)) | V30: =IF(DAY(DATE(PORTADA!$B$2,4,26))<>26,"",SUMIFS(MOVIMIENTOS!$F:$F,MOVIMIENTOS!$A:$A,DATE(PORTADA!$B$2,4,26),MOVIMIENTOS!$C:$C,V$4)) | W30: =IF(DAY(DATE(PORTADA!$B$2,4,26))<>26,"",SUMIFS(MOVIMIENTOS!$F:$F,MOVIMIENTOS!$A:$A,DATE(PORTADA!$B$2,4,26),MOVIMIENTOS!$C:$C,W$4)) | X30: =IF(DAY(DATE(PORTADA!$B$2,4,26))<>26,"",SUMIFS(MOVIMIENTOS!$F:$F,MOVIMIENTOS!$A:$A,DATE(PORTADA!$B$2,4,26),MOVIMIENTOS!$C:$C,X$4)) | Y30: =IF(DAY(DATE(PORTADA!$B$2,4,26))<>26,"",SUMIFS(MOVIMIENTOS!$F:$F,MOVIMIENTOS!$A:$A,DATE(PORTADA!$B$2,4,26),MOVIMIENTOS!$C:$C,Y$4)) | Z30: =IF(DAY(DATE(PORTADA!$B$2,4,26))<>26,"",SUMIFS(MOVIMIENTOS!$F:$F,MOVIMIENTOS!$A:$A,DATE(PORTADA!$B$2,4,26),MOVIMIENTOS!$C:$C,Z$4)) | AA30: =IF(DAY(DATE(PORTADA!$B$2,4,26))<>26,"",SUM(T30:Z30))
A31: DIVERSION | B31: COPETE | C31: =CATEGORIAS!$E$25 | D31: =SUMIFS(MOVIMIENTOS!$F:$F,MOVIMIENTOS!$A:$A,">="&DATE(PORTADA!$B$2,4,1),MOVIMIENTOS!$A:$A,"<="&EOMONTH(DATE(PORTADA!$B$2,4,1),0),MOVIMIENTOS!$D:$D,$B31) | E31: =C31-D31 | F31: =IFERROR(D31/C31,"") | S31: =IF(DAY(DATE(PORTADA!$B$2,4,27))<>27,"",27) | T31: =IF(DAY(DATE(PORTADA!$B$2,4,27))<>27,"",SUMIFS(MOVIMIENTOS!$F:$F,MOVIMIENTOS!$A:$A,DATE(PORTADA!$B$2,4,27),MOVIMIENTOS!$C:$C,T$4)) | U31: =IF(DAY(DATE(PORTADA!$B$2,4,27))<>27,"",SUMIFS(MOVIMIENTOS!$F:$F,MOVIMIENTOS!$A:$A,DATE(PORTADA!$B$2,4,27),MOVIMIENTOS!$C:$C,U$4)) | V31: =IF(DAY(DATE(PORTADA!$B$2,4,27))<>27,"",SUMIFS(MOVIMIENTOS!$F:$F,MOVIMIENTOS!$A:$A,DATE(PORTADA!$B$2,4,27),MOVIMIENTOS!$C:$C,V$4)) | W31: =IF(DAY(DATE(PORTADA!$B$2,4,27))<>27,"",SUMIFS(MOVIMIENTOS!$F:$F,MOVIMIENTOS!$A:$A,DATE(PORTADA!$B$2,4,27),MOVIMIENTOS!$C:$C,W$4)) | X31: =IF(DAY(DATE(PORTADA!$B$2,4,27))<>27,"",SUMIFS(MOVIMIENTOS!$F:$F,MOVIMIENTOS!$A:$A,DATE(PORTADA!$B$2,4,27),MOVIMIENTOS!$C:$C,X$4)) | Y31: =IF(DAY(DATE(PORTADA!$B$2,4,27))<>27,"",SUMIFS(MOVIMIENTOS!$F:$F,MOVIMIENTOS!$A:$A,DATE(PORTADA!$B$2,4,27),MOVIMIENTOS!$C:$C,Y$4)) | Z31: =IF(DAY(DATE(PORTADA!$B$2,4,27))<>27,"",SUMIFS(MOVIMIENTOS!$F:$F,MOVIMIENTOS!$A:$A,DATE(PORTADA!$B$2,4,27),MOVIMIENTOS!$C:$C,Z$4)) | AA31: =IF(DAY(DATE(PORTADA!$B$2,4,27))<>27,"",SUM(T31:Z31))
A32: DIVERSION | B32: WEED | C32: =CATEGORIAS!$E$26 | D32: =SUMIFS(MOVIMIENTOS!$F:$F,MOVIMIENTOS!$A:$A,">="&DATE(PORTADA!$B$2,4,1),MOVIMIENTOS!$A:$A,"<="&EOMONTH(DATE(PORTADA!$B$2,4,1),0),MOVIMIENTOS!$D:$D,$B32) | E32: =C32-D32 | F32: =IFERROR(D32/C32,"") | S32: =IF(DAY(DATE(PORTADA!$B$2,4,28))<>28,"",28) | T32: =IF(DAY(DATE(PORTADA!$B$2,4,28))<>28,"",SUMIFS(MOVIMIENTOS!$F:$F,MOVIMIENTOS!$A:$A,DATE(PORTADA!$B$2,4,28),MOVIMIENTOS!$C:$C,T$4)) | U32: =IF(DAY(DATE(PORTADA!$B$2,4,28))<>28,"",SUMIFS(MOVIMIENTOS!$F:$F,MOVIMIENTOS!$A:$A,DATE(PORTADA!$B$2,4,28),MOVIMIENTOS!$C:$C,U$4)) | V32: =IF(DAY(DATE(PORTADA!$B$2,4,28))<>28,"",SUMIFS(MOVIMIENTOS!$F:$F,MOVIMIENTOS!$A:$A,DATE(PORTADA!$B$2,4,28),MOVIMIENTOS!$C:$C,V$4)) | W32: =IF(DAY(DATE(PORTADA!$B$2,4,28))<>28,"",SUMIFS(MOVIMIENTOS!$F:$F,MOVIMIENTOS!$A:$A,DATE(PORTADA!$B$2,4,28),MOVIMIENTOS!$C:$C,W$4)) | X32: =IF(DAY(DATE(PORTADA!$B$2,4,28))<>28,"",SUMIFS(MOVIMIENTOS!$F:$F,MOVIMIENTOS!$A:$A,DATE(PORTADA!$B$2,4,28),MOVIMIENTOS!$C:$C,X$4)) | Y32: =IF(DAY(DATE(PORTADA!$B$2,4,28))<>28,"",SUMIFS(MOVIMIENTOS!$F:$F,MOVIMIENTOS!$A:$A,DATE(PORTADA!$B$2,4,28),MOVIMIENTOS!$C:$C,Y$4)) | Z32: =IF(DAY(DATE(PORTADA!$B$2,4,28))<>28,"",SUMIFS(MOVIMIENTOS!$F:$F,MOVIMIENTOS!$A:$A,DATE(PORTADA!$B$2,4,28),MOVIMIENTOS!$C:$C,Z$4)) | AA32: =IF(DAY(DATE(PORTADA!$B$2,4,28))<>28,"",SUM(T32:Z32))
A33: DIVERSION | B33: CARCASA CELULAR | C33: =CATEGORIAS!$E$27 | D33: =SUMIFS(MOVIMIENTOS!$F:$F,MOVIMIENTOS!$A:$A,">="&DATE(PORTADA!$B$2,4,1),MOVIMIENTOS!$A:$A,"<="&EOMONTH(DATE(PORTADA!$B$2,4,1),0),MOVIMIENTOS!$D:$D,$B33) | E33: =C33-D33 | F33: =IFERROR(D33/C33,"") | S33: =IF(DAY(DATE(PORTADA!$B$2,4,29))<>29,"",29) | T33: =IF(DAY(DATE(PORTADA!$B$2,4,29))<>29,"",SUMIFS(MOVIMIENTOS!$F:$F,MOVIMIENTOS!$A:$A,DATE(PORTADA!$B$2,4,29),MOVIMIENTOS!$C:$C,T$4)) | U33: =IF(DAY(DATE(PORTADA!$B$2,4,29))<>29,"",SUMIFS(MOVIMIENTOS!$F:$F,MOVIMIENTOS!$A:$A,DATE(PORTADA!$B$2,4,29),MOVIMIENTOS!$C:$C,U$4)) | V33: =IF(DAY(DATE(PORTADA!$B$2,4,29))<>29,"",SUMIFS(MOVIMIENTOS!$F:$F,MOVIMIENTOS!$A:$A,DATE(PORTADA!$B$2,4,29),MOVIMIENTOS!$C:$C,V$4)) | W33: =IF(DAY(DATE(PORTADA!$B$2,4,29))<>29,"",SUMIFS(MOVIMIENTOS!$F:$F,MOVIMIENTOS!$A:$A,DATE(PORTADA!$B$2,4,29),MOVIMIENTOS!$C:$C,W$4)) | X33: =IF(DAY(DATE(PORTADA!$B$2,4,29))<>29,"",SUMIFS(MOVIMIENTOS!$F:$F,MOVIMIENTOS!$A:$A,DATE(PORTADA!$B$2,4,29),MOVIMIENTOS!$C:$C,X$4)) | Y33: =IF(DAY(DATE(PORTADA!$B$2,4,29))<>29,"",SUMIFS(MOVIMIENTOS!$F:$F,MOVIMIENTOS!$A:$A,DATE(PORTADA!$B$2,4,29),MOVIMIENTOS!$C:$C,Y$4)) | Z33: =IF(DAY(DATE(PORTADA!$B$2,4,29))<>29,"",SUMIFS(MOVIMIENTOS!$F:$F,MOVIMIENTOS!$A:$A,DATE(PORTADA!$B$2,4,29),MOVIMIENTOS!$C:$C,Z$4)) | AA33: =IF(DAY(DATE(PORTADA!$B$2,4,29))<>29,"",SUM(T33:Z33))
